Workbook

Sheet 2021
A1: TABELA DE PREÇO
A2: CLIENTES | B2: PELETIZAR | C2: FLANELAR | D2: CALANDRAR | E2: MALHA P/ FARDO
A3: AIR SLAID | E3: 10,50 O KILO
A4: AMBERT TEXTIL | C4: ord 12221,12170 2xR$0,35 p/mts
A5: BERGON COMERCIO | C5: demais ordens R$0,37 p/mts 16/03
A6: BERGON COMERCIO | C6: 2x 0,40 p/mts
A7: CHUMBRECAS/MX72 | C7: 2x 0,60 p/mts
A8: COLEÇÃO TEXTIL | B8: 1x 0,30 p/mts
A9: COMPOMAX | C9: 0,27 P/mts
A10: COVOLAN BENEFIC. | B10: 1x 0,30 p/mts | E10: 10,50 O KILO
A11: CIPATEX | C11: DUBLAR C/ SPUNLACE 1,20
A12: ECOSIMPLE IND. | B12: 1,8 P/mts | C12: DUBLAGEM TUPY 4,10 / TERMOFIXAR 1,20
A13: IBIRAPUERA TEXTIL | B13: 0,95p/mts
A14: IRMAOS JURGENSEN | B14: 1x 0,30 p/mts
A15: INNOVATIV IND. | B15: 1x 0,45 p/mts | C15: 2x -0,65 p/mts / Lona 0,75 p/mts / TELA DUBLARE 1X = 0,50 p/mts / Felpar 0,75 | E15: 10,50 O KILO
A16: IRINEU MENEGHEL | C16: 1X 0,40 p/mts
A17: ITALYTEX TEXTIL | D17: 1x 0,30 p/mts
A18: MAC ROSE | C18: 3x 0,75 p/mts
A19: J.BESAN COMERCIAL | C19: 1X 0,30 p/mts 2x 0,50 p/mts
A20: NOSSA SRA DO BELEM | B20: 1x 0,30 p/mts
A21: SELENE IND. | B21: 1x 0,28 p/mts | C21: 1X 0,30 p/mts 2x 0,50 p/mts | D21: 0,77 p/mts
A22: TEXION TEXTIL | B22: 1x 0,30 p/mts | C22: Calandrar e Felpar 0,80 p/ mts /Calandrar e Felpar Million 1,10 p/mts | D22: 0,50 p/mts
A23: TEXION TEXTIL | C23: DUBLAR C/ CRETONE 0,70 DUBLAR C/ SPUNLACE 0,70 | D23: LONA CUSTOM 0,80
A24: TEXPOY TEXTIL | C24: 2x 0,50 p/mts 3x 0,70 p/mts
A25: MX72 | C25: 2x 0,65 p/mts
A26: TEXTIL FAVERO | B26: 1x 0,30 p/mts | C26: 3x 0,75 p/mts
A27: TRAMAS DO BRASIL | E27: 10,50 O KILO
A28: TEC. PANAMERICANA | B28: 0,45 p/mts
A29: ZAVATEX | D29: 0,50 P/MTS

Sheet 2022-2023
B2: Cliente | C2: Processo | D2: Artigo | E2: Passagem | F2: Valor | G2: Coluna1 | H2: Obsevação
B3: Wameltex (Eliseu/Grilo) | C3: Dublagem/Espelhamento | E3: 1 | F3: 1.05 | G3: p/m | H3: 1.15
B4: Air Slaid | C4: Malha | F4: 15.6 | G4: p/ kg
B5: Ambert Textil | C5: Flanelar | D5: Ordem 12221,12170 | E5: 2 | F5: 0.55 | G5: p/ m | H5: 0.63
B6: Aparatos | G6: 5.12 | H6: 10.7
B7: Aparatos | D7: C/NOSSO FORRO | H7: 6.9
B8: Aparatos | D8: ESPELHAMENTO | H8: 6.7
B9: Aparatos | D9: C/TNT | H9: 6.1
B10: Bergon Comércio | C10: Flanelar | D10: 0,50 E LEVA E RETIRA | E10: 2 | F10: 0.55 | G10: p/ m | H10: 0.6
B11: Bergon Comércio | C11: Flanelar | D11: Demais ordens | F11: 0.37 | G11: p/ m
B12: Calmart | C12: Lixar | E12: 1 | G12: p/m | H12: 0.6
B13: Calmart | C13: Dublagem | E13: 1 | G13: p/m | H13: 2.14
B14: Chumbrecas/MX72 | C14: Flanelar | E14: 2 | F14: 0.6 | G14: p/ m | H14: 1
B15: Cipatex | C15: Flanelar | D15: Dublar com Spunlace | F15: 1.4 | G15: p/ m | H15: 1.61
B16: Coleção Textil | C16: Peletizar | E16: 1 | F16: 0.3 | G16: p/ m | H16: 0.34
B17: Compomax | C17: Flanelar | F17: 0.27 | G17: p/ m | H17: 0.3
B18: Covolan Benefic. | C18: Peletizar | E18: 1 | F18: 0.3 | G18: p/ m | H18: 0.34
B19: Covolan Benefic. | C19: Malha | F19: 15.6 | G19: p/ kg
B20: DB RAINBOW | C20: Dublagem | E20: 1 | F20: 2.2 | G20: p/m | H20: 2.55
B21: Ecosimple Ind. | C21: Flanelar/Peletizar | D21: LISO/LISTRA | F21: 1.8 | G21: p/ m | H21: 2.57
B22: Ecosimple Ind. | C22: Dublagem/Cretone | D22: Dublagem Tupy/New Tweed | F22: 5.63 | G22: p/ m | H22: 6.19
B23: Ecosimple Ind. | C23: Calandrar/Termofixar | E23: 1 | F23: 1.4 | G23: p/m | H23: 1.61
B24: Ecosimple Ind. | C24: Dublagem TNT | D24: TNT= R$ 1,42 | G24: p/m | H24: 4.63
B25: Ecosimple Ind. | C25: Calandrar | G25: p/m
B26: Ecosimple Ind. | C26: Flanelar | D26: Rubus flanelado/Vision/lana Color | E26: 4 | F26: 4.2 | G26: p/m | H26: 4.83
B27: Ecosimple Ind. | C27: Peletizar | D27: Lona Duty Stone/Lona Cargo | E27: 1 | F27: 2.8 | G27: p/m | H27: 3.22
B28: Ecosimple Ind. | C28: Felpar/Flanelar | D28: Lana Vert/Grain/Max/Milao/Alana /alba | E28: 1 | F28: 2.3 | G28: p/m | H28: 2.64
B29: Ecosimple Ind. | C29: Espelhamento | D29: C/ Filme Single | E29: 1 | F29: 2.4 | G29: p/m | H29: 2.76
B30: Ecosimple Ind. | C30: Dublag. Cretone lote de tecido comprado | G30: p/m | H30: 2.4
B31: Ecosimple Ind. | C31: Calandrar/Felpar | G31: p/m | H31: 4.25
B32: Ecosimple Ind. | C32: Flanelar | G32: p/ m | H32: 1.61
B33: Ecosimple Ind. | C33: Flanelar | D33: Casaco /1002-1916090170 | G33: p/m | H33: 4.83
B34: Ecosimple Ind. | C34: Flanelar | D34: Tela | E34: 2 | G34: p/m | H34: 2.64
B35: Ecosimple Ind. | C35: Termofixar | D35: Sami/Maquinetado/Sublime | G35: p/m | H35: 3.65
B36: Ecosimple Ind. | C36: Espelhamento / At 150 ou 100 | D36: Filme + Mão de obra | G36: p/m | H36: 4.6
B37: Ecosimple Ind. | C37: Termofixar + flanelar | D37: 1002090010-0000 | E37: 2 | G37: p/m | H37: 3.65
B38: DB RAINBOW | C38: Flanelar/Peletizado | E38: 1 | F38: 0.3 | G38: p/m | H38: 0.55
B39: Engebank | C39: Dublagem | E39: 1 | G39: p/m | H39: 8.6
B40: Estopas Americana | C40: Dublagem | E40: 1 | F40: 5.2 | G40: p/m | H40: 5.98
B41: Estopas Americana | C41: Flanela | E41: 1 | F41: 0.85 | G41: p/m | H41: 0.98
B42: Estopas Americana | C42: 2 X LADOS | E42: 1 | F42: 0.95 | G42: p/m | H42: 1.09
B43: Iberfios | C43: Peletizado | E43: 1 | G43: p/m | H43: 0.5
B44: Ibirapuera Textil | C44: Peletizar | E44: 1 | F44: 0.95 | G44: p/ m | H44: 1.09
B45: Ibirapuera Textil | C45: Flanelado | E45: 2 | G45: p/m | H45: 0.6
B46: Innovativ Ind. | C46: Flanelamento /Espelhamento | E46: 1 | H46: 3.2
B47: Innovativ Ind. | C47: Peletizar/lixa | E47: 1 | F47: 0.52 | G47: p/ m | H47: 0.57
B48: Innovativ Ind. | C48: Flanelar | E48: 2 | F48: 0.65 | G48: p/ m | H48: 0.75
B49: Innovativ Ind. | C49: Flanelar | D49: Lona | F49: 0.86 | G49: p/ m | H49: 0.95
B50: Innovativ Ind. | C50: Flanelar | D50: Tela Dublare | E50: 1 | F50: 0.5 | G50: p/ m | H50: 0.57
B51: Innovativ Ind. | C51: Felpar | D51: Felpar | F51: 0.86 | G51: p/ m | H51: 0.95
B52: Innovativ Ind. | C52: Felpar | D52: Lolla | E52: 3 | G52: p/m | H52: 1.29
B53: Innovativ Ind. | C53: Malha | F53: 15.6 | G53: p/ kg
B54: Irineu Meneghel | C54: Flanelar | E54: 1 | F54: 0.4 | G54: p/ m | H54: 0.46
B55: Irmãos Jurgensen | C55: Peletizar | E55: 1 | F55: 0.3 | G55: p/ m | H55: 0.34
B56: Italytex Textil | C56: Calandrar | E56: 1 | F56: 0.3 | G56: p/ m | H56: 0.34
B57: J. Besan Comercial | C57: Flanelar | E57: 1 | F57: 0.3 | G57: p/ m | H57: 0.34
B58: J. Besan Comercial | C58: J. Besan Comercial Dublagem c/ Cobrança de Filme e TNT | E58: 1 | F58: 1 + 1,20 + 1,20 = 3,40 | G58: P/m
B59: J. Besan Comercial | C59: Calandra | E59: 2 | F59: 0.57 | G59: p/ m | H59: 0.6
B60: JRJ | C60: Dublagem | E60: 1 | G60: p/m | H60: 6.1
B61: JRJ | C61: Peletização | E61: 1 | G61: p/m | H61: 0.6
B62: JRJ | C62: Peletizado/Calandrado | E62: 1 | G62: p/m | H62: 1.2
B63: Jumirim Malhas | C63: felpar | E63: 1 | G63: p/m | H63: 1.34
B64: LAMATEX | C64: FLANELA | E64: 1 | F64: 1 | G64: P/M | H64: 1.1
B65: Lartex/Sunfabrics | C65: Espelhamento | D65: Insumo + mão de obra | E65: 1 | G65: p/m | H65: 2.15
B66: Lartex/Sunfabrics | C66: Dublagem C/ SPUNTEC | E66: 1 | F66: 4.5 | G66: p/m | H66: 4.5
B67: Limpanos | C67: FLANELA | E67: 1 | G67: p/m | H67: 1.04
B68: Limpanos | F68: 0.85 | G68: p/m | H68: 0.98
B69: Mac Rose | C69: Flanelar | E69: 3 | F69: 0.75 | G69: p/ m | H69: 0.86
B70: MX72 | C70: Flanelar | E70: 2 | F70: 0.85 | G70: p/ m | H70: 0.98
B71: NM | C71: ESPELHAMENTO | D71: insumo = 1,19 + Mão de obra= 1,10 | G71: p/m | H71: 2.29
B72: NM | C72: Dublagem/Spuntec | F72: 4.06 | G72: p/m | H72: 4.47
B73: NM | C73: TAPETE DE 2MTS | G73: p/m | H73: 10.5
B74: NM | C74: Dublagem | D74: M.O 1,10 + TNT 0,82 + Filme 1,19 | H74: 3.11
B75: Nossa Sra. Do Belém | C75: Peletizar | E75: 1 | F75: 0.5 | G75: p/ m | H75: 0.57
B76: Porcher do Brasil | C76: FELPA/PELETIZAR | G76: p/m | H76: 1.7
B77: PROTEXTIL | C77: Espelhamento É só O Filme | D77: HM 20 = 1,07 + M.O = 1,10 | F77: 2.17 | H77: 2.39
B78: PROTEXTIL | C78: Dublagem É QDO VAI tnt | D78: TPU PX= 1,12 + M.O = 1,10 | F78: 2.22 | H78: 2.44
B79: PROTEXTIL | C79: Dublagem É QDO VAI tnt | D79: TPU 25= 3,25 = M.O= 1,21 | H79: 3.35
B80: PROTEXTIL | C80: DUBLAGEM | D80: TNT 1,95 / HM 20 1,07 / M.O 1,10 | F80: 4.12 | H80: 4.53
B81: RENATO | C81: FILME + M.O | E81: 1 | F81: 3.6 | G81: P/M | H81: 3.96
B82: Renovatex | C82: Espelhamento | E82: 1 | F82: 1.92 | G82: P/M | H82: 2.11
B83: Renovatex | C83: Calandrar | E83: 1 | F83: 0.5 | G83: p/m | H83: 0.55
B84: Renovatex | C84: Dublar c/Adesivo e TNT | E84: 1 | F84: 3.8 | G84: p/m | H84: 4.18
B85: RRN | C85: Espelhamento | E85: 1 | F85: 0.7 | G85: p/m | H85: 1.15
B86: RRN | C86: Dublar c/ Adesivo e TNT | D86: Marisol/Penha | E86: 1 | F86: 1.4 | G86: p/m | H86: 1.71
B87: Selene Ind. | C87: Peletizar | E87: 1 | F87: 0.28 | G87: p/ m | H87: 0.32
B88: Selene Ind. | C88: Flanelar | E88: 1 | F88: 0.3 | G88: p/ m | H88: 0.34
B89: Selene Ind. | C89: Flanelar | E89: 2 | F89: 0.5 | G89: p/ m | H89: 0.57
B90: Selene Ind. | C90: Calandrar | F90: 0.77 | G90: p/ m | H90: 0.88
B91: Sextou | E91: 1 | G91: p/m | H91: 3.95
B92: Tavares e Filhos (Mucio) | C92: flanela | E92: 1 | G92: p/m | H92: 0.95
B93: Tec Niker | C93: Dulagem/Single | E93: 1 | G93: p/m | H93: 1.75
B94: Tec. Americana | C94: Barreira | E94: 1 | G94: p/m | H94: 9.7
B95: Tec. Chuahy | C95: Calandra | E95: 1 | G95: p/m | H95: 0.55
B96: Tec. Panamericana | C96: Peletizar=Lixa | F96: 0.52 | G96: p/ m | H96: 0.57
B97: Tec. Panamericana | C97: Calandra/ Peletização | D97: Sarja | E97: 1 | F97: 1.4 | G97: p/m | H97: 1.61
B98: Tec. Panamericana | C98: Espelhamento c/ Smelltex 150 | F98: 3.35 | G98: p/m | H98: 3.68
B99: Tec. Panamericana | D99: Tec. Lona Estonada | F99: 0.55 | G99: p/m | H99: 1.1
B100: Tec. Panamericana | C100: Dublar c/Filme +TNT | D100: HM 35 = 1,39 | F100: 3 | G100: p/m | H100: 5.6
B101: Tec. panamericana | C101: Espelhamento c/Filme TPU | D101: Tecidos Tapeçaria | G101: p/m | H101: 2.1
...

Sheet 2024
B1: Cliente | C1: Processo | D1: Artigo | E1: Passadas | F1: Valor anterior | G1: Valor atual | H1: Unid | I1: Preço/metro | J1: Data de atualização | K1: Obs | L1: MO | M1: Colas | N1: Forro
B2: Ademir Maceti | C2: Calandra | G2: 0.65 | H2: metro linear
B3: Ademir Maceti | C3: Emborrachamento | G3: =4.1+1.5 -> 5.6 | H3: metro linear
B4: AG Textil Eireli | C4: Peletização | E4: 1 | G4: 0.65 | H4: metro linear | I4: =G4/E4 -> 0.65 | L4: =G4-M4-N4 -> 0.65 | M4: =IF(B4="Texion Textil",0,IF(C4="Malha",'Custos insumos'!$B$24,IF(C4="Dublagem Cretone",'Custos insumos'!$D$7,IF(C4="Dublagem Spun",'Custos insumos'!$D$4,IF(C4="Espelhamento",'Custos insumos'!$B$11,IF(C4="Espelhamento 2x",2*'Custos insumos'!$B$11,IF(C4="Esp. + Pel.",'Custos insumos'!$B$11,IF(C4="Pel. + Spun",'Custos insumos'!$D$4,IF(C4="Dublagem Cretone PES",'Custos insumos'!$D$7,IF(C4="Dublagem Barreira",'Custos insumos'!$D$11,IF(C4="Dublagem - MO + Filme",'Custos insumos'!$D$4,))))))))))) -> 0 | N4: =IF(B4="Texion Textil",0,IF(B4="Três Elos",0,IF(C4="Malha",0,IF(C4="Dublagem Cretone",'Custos insumos'!$D$23,IF(C4="Dublagem Spun",'Custos insumos'!$D$19,IF(C4="Espelhamento",0,IF(C4="Espelhamento 2x",0,IF(C4="Esp. + Pel.",0,IF(C4="Pel. + Spun",'Custos insumos'!$D$19,IF(C4="Dublagem Cretone PES",'Custos insumos'!$F$25,IF(C4="Dublagem Barreira",'Custos insumos'!$D$22,))))))))))) -> 0
B5: Air Slaid | C5: Malha | E5: 1 | F5: 18.9 | G5: 20.9 | H5: kg | I5: =G5/E5 -> 20.9 | J5: 45301 | L5: =G5-M5-N5 -> 8.4 | M5: =IF(B5="Texion Textil",0,IF(C5="Malha",'Custos insumos'!$B$24,IF(C5="Dublagem Cretone",'Custos insumos'!$D$7,IF(C5="Dublagem Spun",'Custos insumos'!$D$4,IF(C5="Espelhamento",'Custos insumos'!$B$11,IF(C5="Espelhamento 2x",2*'Custos insumos'!$B$11,IF(C5="Esp. + Pel.",'Custos insumos'!$B$11,IF(C5="Pel. + Spun",'Custos insumos'!$D$4,IF(C5="Dublagem Cretone PES",'Custos insumos'!$D$7,IF(C5="Dublagem Barreira",'Custos insumos'!$D$11,IF(C5="Dublagem - MO + Filme",'Custos insumos'!$D$4,))))))))))) -> 12.5 | N5: =IF(B5="Texion Textil",0,IF(B5="Três Elos",0,IF(C5="Malha",0,IF(C5="Dublagem Cretone",'Custos insumos'!$D$23,IF(C5="Dublagem Spun",'Custos insumos'!$D$19,IF(C5="Espelhamento",0,IF(C5="Espelhamento 2x",0,IF(C5="Esp. + Pel.",0,IF(C5="Pel. + Spun",'Custos insumos'!$D$19,IF(C5="Dublagem Cretone PES",'Custos insumos'!$F$25,IF(C5="Dublagem Barreira",'Custos insumos'!$D$22,))))))))))) -> 0
B6: Aparatos | C6: Dublagem Cretone PES | E6: 1 | G6: 6.5 | H6: metro linear | I6: =G6/E6 -> 6.5 | J6: 45301 | K6: Insumos fornecidos por Tapajos | L6: =G6-M6-N6 -> 2.21 | M6: =IF(B6="Texion Textil",0,IF(C6="Malha",'Custos insumos'!$B$24,IF(C6="Dublagem Cretone",'Custos insumos'!$D$7,IF(C6="Dublagem Spun",'Custos insumos'!$D$4,IF(C6="Espelhamento",'Custos insumos'!$B$11,IF(C6="Espelhamento 2x",2*'Custos insumos'!$B$11,IF(C6="Esp. + Pel.",'Custos insumos'!$B$11,IF(C6="Pel. + Spun",'Custos insumos'!$D$4,IF(C6="Dublagem Cretone PES",'Custos insumos'!$D$7,IF(C6="Dublagem Barreira",'Custos insumos'!$D$11,IF(C6="Dublagem - MO + Filme",'Custos insumos'!$D$4,IF(C6="Dublagem Cretone HM50",'Custos insumos'!$D$26,IF(C6="Dublagem Cretone HM70",'Custos insumos'!$F$10,))))))))))))) -> 1.962 | N6: =IF(B6="Texion Textil",0,IF(B6="Três Elos",0,IF(C6="Malha",0,IF(C6="Dublagem Cretone",'Custos insumos'!$D$23,IF(C6="Dublagem Spun",'Custos insumos'!$D$19,IF(C6="Espelhamento",0,IF(C6="Espelhamento 2x",0,IF(C6="Esp. + Pel.",0,IF(C6="Pel. + Spun",'Custos insumos'!$D$19,IF(C6="Dublagem Cretone PES",'Custos insumos'!$F$25,IF(C6="Dublagem Barreira",'Custos insumos'!$D$22,))))))))))) -> 2.328
B7: Aparatos | C7: Dublagem Spun | D7: Novo | E7: 1 | G7: 6.5 | H7: metro linear | I7: =G7/E7 -> 6.5 | J7: 45301 | K7: Insumos fornecidos por Tapajos | L7: =G7-M7-N7 -> 4.4858 | M7: =IF(B7="Texion Textil",0,IF(C7="Malha",'Custos insumos'!$B$24,IF(C7="Dublagem Cretone",'Custos insumos'!$D$7,IF(C7="Dublagem Spun",'Custos insumos'!$D$4,IF(C7="Espelhamento",'Custos insumos'!$B$11,IF(C7="Espelhamento 2x",2*'Custos insumos'!$B$11,IF(C7="Esp. + Pel.",'Custos insumos'!$B$11,IF(C7="Pel. + Spun",'Custos insumos'!$D$4,IF(C7="Dublagem Cretone PES",'Custos insumos'!$D$7,IF(C7="Dublagem Barreira",'Custos insumos'!$D$11,IF(C7="Dublagem - MO + Filme",'Custos insumos'!$D$4,IF(C7="Dublagem Cretone HM50",'Custos insumos'!$D$26,IF(C7="Dublagem Cretone HM70",'Custos insumos'!$F$10,))))))))))))) -> 1.1232 | N7: =IF(B7="Texion Textil",0,IF(B7="Três Elos",0,IF(C7="Malha",0,IF(C7="Dublagem Cretone",'Custos insumos'!$D$23,IF(C7="Dublagem Spun",'Custos insumos'!$D$19,IF(C7="Espelhamento",0,IF(C7="Espelhamento 2x",0,IF(C7="Esp. + Pel.",0,IF(C7="Pel. + Spun",'Custos insumos'!$D$19,IF(C7="Dublagem Cretone PES",'Custos insumos'!$F$25,IF(C7="Dublagem Barreira",'Custos insumos'!$D$22,))))))))))) -> 0.891
B8: Aparatos | C8: Dublagem Cretone | E8: 1 | F8: 10.7 | G8: =F8+(F8*0.1) -> 11.77 | H8: metro linear | I8: =G8/E8 -> 11.77 | J8: 45301 | K8: Insumos fornecidos por Tapajos; TNT= R$ 1,42 + Filme HM20/35 = R$ 1,1 | L8: =G8-M8-N8 -> 7.48 | M8: =IF(B8="Texion Textil",0,IF(C8="Malha",'Custos insumos'!$B$24,IF(C8="Dublagem Cretone",'Custos insumos'!$D$7,IF(C8="Dublagem Spun",'Custos insumos'!$D$4,IF(C8="Espelhamento",'Custos insumos'!$B$11,IF(C8="Espelhamento 2x",2*'Custos insumos'!$B$11,IF(C8="Esp. + Pel.",'Custos insumos'!$B$11,IF(C8="Pel. + Spun",'Custos insumos'!$D$4,IF(C8="Dublagem Cretone PES",'Custos insumos'!$D$7,IF(C8="Dublagem Barreira",'Custos insumos'!$D$11,IF(C8="Dublagem - MO + Filme",'Custos insumos'!$D$4,IF(C8="Dublagem Cretone HM50",'Custos insumos'!$D$26,IF(C8="Dublagem Cretone HM70",'Custos insumos'!$F$10,))))))))))))) -> 1.962 | N8: =IF(B8="Texion Textil",0,IF(B8="Três Elos",0,IF(C8="Malha",0,IF(C8="Dublagem Cretone",'Custos insumos'!$D$23,IF(C8="Dublagem Spun",'Custos insumos'!$D$19,IF(C8="Espelhamento",0,IF(C8="Espelhamento 2x",0,IF(C8="Esp. + Pel.",0,IF(C8="Pel. + Spun",'Custos insumos'!$D$19,IF(C8="Dublagem Cretone PES",'Custos insumos'!$F$25,IF(C8="Dublagem Barreira",'Custos insumos'!$D$22,))))))))))) -> 2.328
B9: Aparatos | C9: Dublagem Spun | E9: 1 | F9: 10.7 | G9: =F9+(F9*0.1) -> 11.77 | H9: metro linear | I9: =G9/E9 -> 11.77 | J9: 45301 | K9: Insumos fornecidos por Tapajos | L9: =G9-M9-N9 -> 9.7558 | M9: =IF(B9="Texion Textil",0,IF(C9="Malha",'Custos insumos'!$B$24,IF(C9="Dublagem Cretone",'Custos insumos'!$D$7,IF(C9="Dublagem Spun",'Custos insumos'!$D$4,IF(C9="Espelhamento",'Custos insumos'!$B$11,IF(C9="Espelhamento 2x",2*'Custos insumos'!$B$11,IF(C9="Esp. + Pel.",'Custos insumos'!$B$11,IF(C9="Pel. + Spun",'Custos insumos'!$D$4,IF(C9="Dublagem Cretone PES",'Custos insumos'!$D$7,IF(C9="Dublagem Barreira",'Custos insumos'!$D$11,IF(C9="Dublagem - MO + Filme",'Custos insumos'!$D$4,IF(C9="Dublagem Cretone HM50",'Custos insumos'!$D$26,IF(C9="Dublagem Cretone HM70",'Custos insumos'!$F$10,))))))))))))) -> 1.1232 | N9: =IF(B9="Texion Textil",0,IF(B9="Três Elos",0,IF(C9="Malha",0,IF(C9="Dublagem Cretone",'Custos insumos'!$D$23,IF(C9="Dublagem Spun",'Custos insumos'!$D$19,IF(C9="Espelhamento",0,IF(C9="Espelhamento 2x",0,IF(C9="Esp. + Pel.",0,IF(C9="Pel. + Spun",'Custos insumos'!$D$19,IF(C9="Dublagem Cretone PES",'Custos insumos'!$F$25,IF(C9="Dublagem Barreira",'Custos insumos'!$D$22,))))))))))) -> 0.891
B10: Aparatos | C10: Espelhamento | E10: 1 | F10: 6.7 | G10: =F10+(F10*0.1) -> 7.37 | H10: metro linear | I10: =G10/E10 -> 7.37 | J10: 45301 | K10: Insumos fornecidos por Tapajos | L10: =G10-M10-N10 -> 6.3114997 | M10: =IF(B10="Texion Textil",0,IF(C10="Malha",'Custos insumos'!$B$24,IF(C10="Dublagem Cretone",'Custos insumos'!$D$7,IF(C10="Dublagem Spun",'Custos insumos'!$D$4,IF(C10="Espelhamento",'Custos insumos'!$B$11,IF(C10="Espelhamento 2x",2*'Custos insumos'!$B$11,IF(C10="Esp. + Pel.",'Custos insumos'!$B$11,IF(C10="Pel. + Spun",'Custos insumos'!$D$4,IF(C10="Dublagem Cretone PES",'Custos insumos'!$D$7,IF(C10="Dublagem Barreira",'Custos insumos'!$D$11,IF(C10="Dublagem - MO + Filme",'Custos insumos'!$D$4,IF(C10="Dublagem Cretone HM50",'Custos insumos'!$D$26,IF(C10="Dublagem Cretone HM70",'Custos insumos'!$F$10,))))))))))))) -> 1.0585003 | N10: =IF(B10="Texion Textil",0,IF(B10="Três Elos",0,IF(C10="Malha",0,IF(C10="Dublagem Cretone",'Custos insumos'!$D$23,IF(C10="Dublagem Spun",'Custos insumos'!$D$19,IF(C10="Espelhamento",0,IF(C10="Espelhamento 2x",0,IF(C10="Esp. + Pel.",0,IF(C10="Pel. + Spun",'Custos insumos'!$D$19,IF(C10="Dublagem Cretone PES",'Custos insumos'!$F$25,IF(C10="Dublagem Barreira",'Custos insumos'!$D$22,))))))))))) -> 0
B11: Bergon | C11: Felpagem | D11: 12221 e 12179 | E11: 2 | F11: 0.5 | G11: 0.5 | H11: metro linear | I11: =G11/E11 -> 0.25 | J11: 45301 | L11: =G11-M11-N11 -> 0.5 | M11: =IF(B11="Texion Textil",0,IF(C11="Malha",'Custos insumos'!$B$24,IF(C11="Dublagem Cretone",'Custos insumos'!$D$7,IF(C11="Dublagem Spun",'Custos insumos'!$D$4,IF(C11="Espelhamento",'Custos insumos'!$B$11,IF(C11="Espelhamento 2x",2*'Custos insumos'!$B$11,IF(C11="Esp. + Pel.",'Custos insumos'!$B$11,IF(C11="Pel. + Spun",'Custos insumos'!$D$4,IF(C11="Dublagem Cretone PES",'Custos insumos'!$D$7,IF(C11="Dublagem Barreira",'Custos insumos'!$D$11,IF(C11="Dublagem - MO + Filme",'Custos insumos'!$D$4,IF(C11="Dublagem Cretone HM50",'Custos insumos'!$D$26,IF(C11="Dublagem Cretone HM70",'Custos insumos'!$F$10,))))))))))))) -> 0 | N11: =IF(B11="Texion Textil",0,IF(B11="Três Elos",0,IF(C11="Malha",0,IF(C11="Dublagem Cretone",'Custos insumos'!$D$23,IF(C11="Dublagem Spun",'Custos insumos'!$D$19,IF(C11="Espelhamento",0,IF(C11="Espelhamento 2x",0,IF(C11="Esp. + Pel.",0,IF(C11="Pel. + Spun",'Custos insumos'!$D$19,IF(C11="Dublagem Cretone PES",'Custos insumos'!$F$25,IF(C11="Dublagem Barreira",'Custos insumos'!$D$22,))))))))))) -> 0
A12: ok | B12: Bergon | C12: Felpagem | D12: 12142 | E12: 2 | F12: 0.35 | G12: 0.35 | H12: metro linear | I12: =G12/E12 -> 0.175 | J12: 45301 | L12: =G12-M12-N12 -> 0.35 | M12: =IF(B12="Texion Textil",0,IF(C12="Malha",'Custos insumos'!$B$24,IF(C12="Dublagem Cretone",'Custos insumos'!$D$7,IF(C12="Dublagem Spun",'Custos insumos'!$D$4,IF(C12="Espelhamento",'Custos insumos'!$B$11,IF(C12="Espelhamento 2x",2*'Custos insumos'!$B$11,IF(C12="Esp. + Pel.",'Custos insumos'!$B$11,IF(C12="Pel. + Spun",'Custos insumos'!$D$4,IF(C12="Dublagem Cretone PES",'Custos insumos'!$D$7,IF(C12="Dublagem Barreira",'Custos insumos'!$D$11,IF(C12="Dublagem - MO + Filme",'Custos insumos'!$D$4,IF(C12="Dublagem Cretone HM50",'Custos insumos'!$D$26,IF(C12="Dublagem Cretone HM70",'Custos insumos'!$F$10,))))))))))))) -> 0 | N12: =IF(B12="Texion Textil",0,IF(B12="Três Elos",0,IF(C12="Malha",0,IF(C12="Dublagem Cretone",'Custos insumos'!$D$23,IF(C12="Dublagem Spun",'Custos insumos'!$D$19,IF(C12="Espelhamento",0,IF(C12="Espelhamento 2x",0,IF(C12="Esp. + Pel.",0,IF(C12="Pel. + Spun",'Custos insumos'!$D$19,IF(C12="Dublagem Cretone PES",'Custos insumos'!$F$25,IF(C12="Dublagem Barreira",'Custos insumos'!$D$22,))))))))))) -> 0
A13: ok | B13: Bergon | C13: Peletização | E13: 1 | G13: 0.45 | H13: metro linear | I13: =G13/E13 -> 0.45 | J13: 45301 | L13: =G13-M13-N13 -> 0.45 | M13: =IF(B13="Texion Textil",0,IF(C13="Malha",'Custos insumos'!$B$24,IF(C13="Dublagem Cretone",'Custos insumos'!$D$7,IF(C13="Dublagem Spun",'Custos insumos'!$D$4,IF(C13="Espelhamento",'Custos insumos'!$B$11,IF(C13="Espelhamento 2x",2*'Custos insumos'!$B$11,IF(C13="Esp. + Pel.",'Custos insumos'!$B$11,IF(C13="Pel. + Spun",'Custos insumos'!$D$4,IF(C13="Dublagem Cretone PES",'Custos insumos'!$D$7,IF(C13="Dublagem Barreira",'Custos insumos'!$D$11,IF(C13="Dublagem - MO + Filme",'Custos insumos'!$D$4,IF(C13="Dublagem Cretone HM50",'Custos insumos'!$D$26,IF(C13="Dublagem Cretone HM70",'Custos insumos'!$F$10,))))))))))))) -> 0 | N13: =IF(B13="Texion Textil",0,IF(B13="Três Elos",0,IF(C13="Malha",0,IF(C13="Dublagem Cretone",'Custos insumos'!$D$23,IF(C13="Dublagem Spun",'Custos insumos'!$D$19,IF(C13="Espelhamento",0,IF(C13="Espelhamento 2x",0,IF(C13="Esp. + Pel.",0,IF(C13="Pel. + Spun",'Custos insumos'!$D$19,IF(C13="Dublagem Cretone PES",'Custos insumos'!$F$25,IF(C13="Dublagem Barreira",'Custos insumos'!$D$22,))))))))))) -> 0
A14: ok | B14: Bergon | C14: Calandra | E14: 1 | G14: 0.65 | H14: metro linear | I14: =G14/E14 -> 0.65 | J14: 45301 | L14: =G14-M14-N14 -> 0.65 | M14: =IF(B14="Texion Textil",0,IF(C14="Malha",'Custos insumos'!$B$24,IF(C14="Dublagem Cretone",'Custos insumos'!$D$7,IF(C14="Dublagem Spun",'Custos insumos'!$D$4,IF(C14="Espelhamento",'Custos insumos'!$B$11,IF(C14="Espelhamento 2x",2*'Custos insumos'!$B$11,IF(C14="Esp. + Pel.",'Custos insumos'!$B$11,IF(C14="Pel. + Spun",'Custos insumos'!$D$4,IF(C14="Dublagem Cretone PES",'Custos insumos'!$D$7,IF(C14="Dublagem Barreira",'Custos insumos'!$D$11,IF(C14="Dublagem - MO + Filme",'Custos insumos'!$D$4,IF(C14="Dublagem Cretone HM50",'Custos insumos'!$D$26,IF(C14="Dublagem Cretone HM70",'Custos insumos'!$F$10,))))))))))))) -> 0 | N14: =IF(B14="Texion Textil",0,IF(B14="Três Elos",0,IF(C14="Malha",0,IF(C14="Dublagem Cretone",'Custos insumos'!$D$23,IF(C14="Dublagem Spun",'Custos insumos'!$D$19,IF(C14="Espelhamento",0,IF(C14="Espelhamento 2x",0,IF(C14="Esp. + Pel.",0,IF(C14="Pel. + Spun",'Custos insumos'!$D$19,IF(C14="Dublagem Cretone PES",'Custos insumos'!$F$25,IF(C14="Dublagem Barreira",'Custos insumos'!$D$22,))))))))))) -> 0
A15: ok | B15: Bergon | C15: Espelhamento - MO | E15: 1 | G15: 1.15 | H15: metro linear | I15: =G15/E15 -> 1.15 | J15: 45301 | K15: Mão de obra | L15: =G15-M15-N15 -> 1.15 | M15: =IF(B15="Texion Textil",0,IF(C15="Malha",'Custos insumos'!$B$24,IF(C15="Dublagem Cretone",'Custos insumos'!$D$7,IF(C15="Dublagem Spun",'Custos insumos'!$D$4,IF(C15="Espelhamento",'Custos insumos'!$B$11,IF(C15="Espelhamento 2x",2*'Custos insumos'!$B$11,IF(C15="Esp. + Pel.",'Custos insumos'!$B$11,IF(C15="Pel. + Spun",'Custos insumos'!$D$4,IF(C15="Dublagem Cretone PES",'Custos insumos'!$D$7,IF(C15="Dublagem Barreira",'Custos insumos'!$D$11,IF(C15="Dublagem - MO + Filme",'Custos insumos'!$D$4,IF(C15="Dublagem Cretone HM50",'Custos insumos'!$D$26,IF(C15="Dublagem Cretone HM70",'Custos insumos'!$F$10,))))))))))))) -> 0 | N15: =IF(B15="Texion Textil",0,IF(B15="Três Elos",0,IF(C15="Malha",0,IF(C15="Dublagem Cretone",'Custos insumos'!$D$23,IF(C15="Dublagem Spun",'Custos insumos'!$D$19,IF(C15="Espelhamento",0,IF(C15="Espelhamento 2x",0,IF(C15="Esp. + Pel.",0,IF(C15="Pel. + Spun",'Custos insumos'!$D$19,IF(C15="Dublagem Cretone PES",'Custos insumos'!$F$25,IF(C15="Dublagem Barreira",'Custos insumos'!$D$22,))))))))))) -> 0
A16: ok | B16: Bergon | C16: Espelhamento | E16: 1 | G16: 2.35 | H16: metro linear | I16: =G16/E16 -> 2.35 | J16: 45301 | K16: Mão de obra e insumos | L16: =G16-M16-N16 -> 1.2914997 | M16: =IF(B16="Texion Textil",0,IF(C16="Malha",'Custos insumos'!$B$24,IF(C16="Dublagem Cretone",'Custos insumos'!$D$7,IF(C16="Dublagem Spun",'Custos insumos'!$D$4,IF(C16="Espelhamento",'Custos insumos'!$B$11,IF(C16="Espelhamento 2x",2*'Custos insumos'!$B$11,IF(C16="Esp. + Pel.",'Custos insumos'!$B$11,IF(C16="Pel. + Spun",'Custos insumos'!$D$4,IF(C16="Dublagem Cretone PES",'Custos insumos'!$D$7,IF(C16="Dublagem Barreira",'Custos insumos'!$D$11,IF(C16="Dublagem - MO + Filme",'Custos insumos'!$D$4,IF(C16="Dublagem Cretone HM50",'Custos insumos'!$D$26,IF(C16="Dublagem Cretone HM70",'Custos insumos'!$F$10,))))))))))))) -> 1.0585003 | N16: =IF(B16="Texion Textil",0,IF(B16="Três Elos",0,IF(C16="Malha",0,IF(C16="Dublagem Cretone",'Custos insumos'!$D$23,IF(C16="Dublagem Spun",'Custos insumos'!$D$19,IF(C16="Espelhamento",0,IF(C16="Espelhamento 2x",0,IF(C16="Esp. + Pel.",0,IF(C16="Pel. + Spun",'Custos insumos'!$D$19,IF(C16="Dublagem Cretone PES",'Custos insumos'!$F$25,IF(C16="Dublagem Barreira",'Custos insumos'!$D$22,))))))))))) -> 0
A17: ok | B17: Bergon | C17: Dublagem Spun - MO | E17: 1 | G17: 1.15 | H17: metro linear | I17: =G17/E17 -> 1.15 | J17: 45301 | K17: Mão de obra | L17: =G17-M17-N17 -> 1.15 | M17: =IF(B17="Texion Textil",0,IF(C17="Malha",'Custos insumos'!$B$24,IF(C17="Dublagem Cretone",'Custos insumos'!$D$7,IF(C17="Dublagem Spun",'Custos insumos'!$D$4,IF(C17="Espelhamento",'Custos insumos'!$B$11,IF(C17="Espelhamento 2x",2*'Custos insumos'!$B$11,IF(C17="Esp. + Pel.",'Custos insumos'!$B$11,IF(C17="Pel. + Spun",'Custos insumos'!$D$4,IF(C17="Dublagem Cretone PES",'Custos insumos'!$D$7,IF(C17="Dublagem Barreira",'Custos insumos'!$D$11,IF(C17="Dublagem - MO + Filme",'Custos insumos'!$D$4,IF(C17="Dublagem Cretone HM50",'Custos insumos'!$D$26,IF(C17="Dublagem Cretone HM70",'Custos insumos'!$F$10,))))))))))))) -> 0 | N17: =IF(B17="Texion Textil",0,IF(B17="Três Elos",0,IF(C17="Malha",0,IF(C17="Dublagem Cretone",'Custos insumos'!$D$23,IF(C17="Dublagem Spun",'Custos insumos'!$D$19,IF(C17="Espelhamento",0,IF(C17="Espelhamento 2x",0,IF(C17="Esp. + Pel.",0,IF(C17="Pel. + Spun",'Custos insumos'!$D$19,IF(C17="Dublagem Cretone PES",'Custos insumos'!$F$25,IF(C17="Dublagem Barreira",'Custos insumos'!$D$22,))))))))))) -> 0
A18: ok | B18: Bergon | C18: Dublagem Spun | E18: 1 | G18: 4.5 | H18: metro linear | I18: =G18/E18 -> 4.5 | J18: 45301 | K18: Mão de obra e insumos | L18: =G18-M18-N18 -> 2.4858 | M18: =IF(B18="Texion Textil",0,IF(C18="Malha",'Custos insumos'!$B$24,IF(C18="Dublagem Cretone",'Custos insumos'!$D$7,IF(C18="Dublagem Spun",'Custos insumos'!$D$4,IF(C18="Espelhamento",'Custos insumos'!$B$11,IF(C18="Espelhamento 2x",2*'Custos insumos'!$B$11,IF(C18="Esp. + Pel.",'Custos insumos'!$B$11,IF(C18="Pel. + Spun",'Custos insumos'!$D$4,IF(C18="Dublagem Cretone PES",'Custos insumos'!$D$7,IF(C18="Dublagem Barreira",'Custos insumos'!$D$11,IF(C18="Dublagem - MO + Filme",'Custos insumos'!$D$4,IF(C18="Dublagem Cretone HM50",'Custos insumos'!$D$26,IF(C18="Dublagem Cretone HM70",'Custos insumos'!$F$10,))))))))))))) -> 1.1232 | N18: =IF(B18="Texion Textil",0,IF(B18="Três Elos",0,IF(C18="Malha",0,IF(C18="Dublagem Cretone",'Custos insumos'!$D$23,IF(C18="Dublagem Spun",'Custos insumos'!$D$19,IF(C18="Espelhamento",0,IF(C18="Espelhamento 2x",0,IF(C18="Esp. + Pel.",0,IF(C18="Pel. + Spun",'Custos insumos'!$D$19,IF(C18="Dublagem Cretone PES",'Custos insumos'!$F$25,IF(C18="Dublagem Barreira",'Custos insumos'!$D$22,))))))))))) -> 0.891
A19: ok | B19: Bergon | C19: Dublagem Cretone - MO | E19: 1 | G19: 1.15 | H19: metro linear | I19: =G19/E19 -> 1.15 | J19: 45301 | K19: Mão de obra | L19: =G19-M19-N19 -> 1.15 | M19: =IF(B19="Texion Textil",0,IF(C19="Malha",'Custos insumos'!$B$24,IF(C19="Dublagem Cretone",'Custos insumos'!$D$7,IF(C19="Dublagem Spun",'Custos insumos'!$D$4,IF(C19="Espelhamento",'Custos insumos'!$B$11,IF(C19="Espelhamento 2x",2*'Custos insumos'!$B$11,IF(C19="Esp. + Pel.",'Custos insumos'!$B$11,IF(C19="Pel. + Spun",'Custos insumos'!$D$4,IF(C19="Dublagem Cretone PES",'Custos insumos'!$D$7,IF(C19="Dublagem Barreira",'Custos insumos'!$D$11,IF(C19="Dublagem - MO + Filme",'Custos insumos'!$D$4,IF(C19="Dublagem Cretone HM50",'Custos insumos'!$D$26,IF(C19="Dublagem Cretone HM70",'Custos insumos'!$F$10,))))))))))))) -> 0 | N19: =IF(B19="Texion Textil",0,IF(B19="Três Elos",0,IF(C19="Malha",0,IF(C19="Dublagem Cretone",'Custos insumos'!$D$23,IF(C19="Dublagem Spun",'Custos insumos'!$D$19,IF(C19="Espelhamento",0,IF(C19="Espelhamento 2x",0,IF(C19="Esp. + Pel.",0,IF(C19="Pel. + Spun",'Custos insumos'!$D$19,IF(C19="Dublagem Cretone PES",'Custos insumos'!$F$25,IF(C19="Dublagem Barreira",'Custos insumos'!$D$22,))))))))))) -> 0
A20: ok | B20: By For man | C20: Felpagem | E20: 1 | G20: 1.1 | H20: metro linear | I20: =G20/E20 -> 1.1 | L20: =G20-M20-N20 -> 1.1 | M20: =IF(B20="Texion Textil",0,IF(C20="Malha",'Custos insumos'!$B$24,IF(C20="Dublagem Cretone",'Custos insumos'!$D$7,IF(C20="Dublagem Spun",'Custos insumos'!$D$4,IF(C20="Espelhamento",'Custos insumos'!$B$11,IF(C20="Espelhamento 2x",2*'Custos insumos'!$B$11,IF(C20="Esp. + Pel.",'Custos insumos'!$B$11,IF(C20="Pel. + Spun",'Custos insumos'!$D$4,IF(C20="Dublagem Cretone PES",'Custos insumos'!$D$7,IF(C20="Dublagem Barreira",'Custos insumos'!$D$11,IF(C20="Dublagem - MO + Filme",'Custos insumos'!$D$4,IF(C20="Dublagem Cretone HM50",'Custos insumos'!$D$26,IF(C20="Dublagem Cretone HM70",'Custos insumos'!$F$10,))))))))))))) -> 0 | N20: =IF(B20="Texion Textil",0,IF(B20="Três Elos",0,IF(C20="Malha",0,IF(C20="Dublagem Cretone",'Custos insumos'!$D$23,IF(C20="Dublagem Spun",'Custos insumos'!$D$19,IF(C20="Espelhamento",0,IF(C20="Espelhamento 2x",0,IF(C20="Esp. + Pel.",0,IF(C20="Pel. + Spun",'Custos insumos'!$D$19,IF(C20="Dublagem Cretone PES",'Custos insumos'!$F$25,IF(C20="Dublagem Barreira",'Custos insumos'!$D$22,))))))))))) -> 0
B21: Calmart | C21: Peletização | E21: 1 | F21: 0.6 | G21: 0.65 | H21: metro linear | I21: =G21/E21 -> 0.65 | J21: 45301 | L21: =G21-M21-N21 -> 0.65 | M21: =IF(B21="Texion Textil",0,IF(C21="Malha",'Custos insumos'!$B$24,IF(C21="Dublagem Cretone",'Custos insumos'!$D$7,IF(C21="Dublagem Spun",'Custos insumos'!$D$4,IF(C21="Espelhamento",'Custos insumos'!$B$11,IF(C21="Espelhamento 2x",2*'Custos insumos'!$B$11,IF(C21="Esp. + Pel.",'Custos insumos'!$B$11,IF(C21="Pel. + Spun",'Custos insumos'!$D$4,IF(C21="Dublagem Cretone PES",'Custos insumos'!$D$7,IF(C21="Dublagem Barreira",'Custos insumos'!$D$11,IF(C21="Dublagem - MO + Filme",'Custos insumos'!$D$4,IF(C21="Dublagem Cretone HM50",'Custos insumos'!$D$26,IF(C21="Dublagem Cretone HM70",'Custos insumos'!$F$10,))))))))))))) -> 0 | N21: =IF(B21="Texion Textil",0,IF(B21="Três Elos",0,IF(C21="Malha",0,IF(C21="Dublagem Cretone",'Custos insumos'!$D$23,IF(C21="Dublagem Spun",'Custos insumos'!$D$19,IF(C21="Espelhamento",0,IF(C21="Espelhamento 2x",0,IF(C21="Esp. + Pel.",0,IF(C21="Pel. + Spun",'Custos insumos'!$D$19,IF(C21="Dublagem Cretone PES",'Custos insumos'!$F$25,IF(C21="Dublagem Barreira",'Custos insumos'!$D$22,))))))))))) -> 0
A22: ok | B22: Calmart | C22: Dublagem Cretone - MO | E22: 1 | F22: 2.14 | G22: =1.19+1.15 -> 2.34 | H22: metro linear | I22: =G22/E22 -> 2.34 | J22: 45301 | K22: Mão de obra e filme | L22: =G22-M22-N22 -> 0.378 | M22: ='Custos insumos'!D7 -> 1.962 | N22: 0
A23: ok | B23: Chumbrecas/MX72/Tavares e Filhos | C23: Felpagem | E23: 3 | F23: 1 | G23: 1.1 | H23: metro linear | I23: =G23/E23 -> 0.36666667 | J23: 45301 | L23: =G23-M23-N23 -> 1.1 | M23: =IF(B23="Texion Textil",0,IF(C23="Malha",'Custos insumos'!$B$24,IF(C23="Dublagem Cretone",'Custos insumos'!$D$7,IF(C23="Dublagem Spun",'Custos insumos'!$D$4,IF(C23="Espelhamento",'Custos insumos'!$B$11,IF(C23="Espelhamento 2x",2*'Custos insumos'!$B$11,IF(C23="Esp. + Pel.",'Custos insumos'!$B$11,IF(C23="Pel. + Spun",'Custos insumos'!$D$4,IF(C23="Dublagem Cretone PES",'Custos insumos'!$D$7,IF(C23="Dublagem Barreira",'Custos insumos'!$D$11,IF(C23="Dublagem - MO + Filme",'Custos insumos'!$D$4,IF(C23="Dublagem Cretone HM50",'Custos insumos'!$D$26,IF(C23="Dublagem Cretone HM70",'Custos insumos'!$F$10,))))))))))))) -> 0 | N23: =IF(B23="Texion Textil",0,IF(B23="Três Elos",0,IF(C23="Malha",0,IF(C23="Dublagem Cretone",'Custos insumos'!$D$23,IF(C23="Dublagem Spun",'Custos insumos'!$D$19,IF(C23="Espelhamento",0,IF(C23="Espelhamento 2x",0,IF(C23="Esp. + Pel.",0,IF(C23="Pel. + Spun",'Custos insumos'!$D$19,IF(C23="Dublagem Cretone PES",'Custos insumos'!$F$25,IF(C23="Dublagem Barreira",'Custos insumos'!$D$22,))))))))))) -> 0
B24: Coleção Textil | C24: Peletização | E24: 1 | F24: 0.5 | G24: 0.75 | H24: metro linear | I24: =G24/E24 -> 0.75 | J24: 45301 | L24: 0.75 | M24: =IF(B24="Texion Textil",0,IF(C24="Malha",'Custos insumos'!$B$24,IF(C24="Dublagem Cretone",'Custos insumos'!$D$7,IF(C24="Dublagem Spun",'Custos insumos'!$D$4,IF(C24="Espelhamento",'Custos insumos'!$B$11,IF(C24="Espelhamento 2x",2*'Custos insumos'!$B$11,IF(C24="Esp. + Pel.",'Custos insumos'!$B$11,IF(C24="Pel. + Spun",'Custos insumos'!$D$4,IF(C24="Dublagem Cretone PES",'Custos insumos'!$D$7,IF(C24="Dublagem Barreira",'Custos insumos'!$D$11,IF(C24="Dublagem - MO + Filme",'Custos insumos'!$D$4,IF(C24="Dublagem Cretone HM50",'Custos insumos'!$D$26,IF(C24="Dublagem Cretone HM70",'Custos insumos'!$F$10,))))))))))))) -> 0 | N24: =IF(B24="Texion Textil",0,IF(B24="Três Elos",0,IF(C24="Malha",0,IF(C24="Dublagem Cretone",'Custos insumos'!$D$23,IF(C24="Dublagem Spun",'Custos insumos'!$D$19,IF(C24="Espelhamento",0,IF(C24="Espelhamento 2x",0,IF(C24="Esp. + Pel.",0,IF(C24="Pel. + Spun",'Custos insumos'!$D$19,IF(C24="Dublagem Cretone PES",'Custos insumos'!$F$25,IF(C24="Dublagem Barreira",'Custos insumos'!$D$22,))))))))))) -> 0
B25: Coleção Textil | C25: Peletização | D25: Duas passadas | E25: 2 | F25: 0.5 | G25: 1.25 | H25: metro linear | I25: =G25/E25 -> 0.625 | J25: 45301 | L25: =G25-M25-N25 -> 1.25 | M25: =IF(B25="Texion Textil",0,IF(C25="Malha",'Custos insumos'!$B$24,IF(C25="Dublagem Cretone",'Custos insumos'!$D$7,IF(C25="Dublagem Spun",'Custos insumos'!$D$4,IF(C25="Espelhamento",'Custos insumos'!$B$11,IF(C25="Espelhamento 2x",2*'Custos insumos'!$B$11,IF(C25="Esp. + Pel.",'Custos insumos'!$B$11,IF(C25="Pel. + Spun",'Custos insumos'!$D$4,IF(C25="Dublagem Cretone PES",'Custos insumos'!$D$7,IF(C25="Dublagem Barreira",'Custos insumos'!$D$11,IF(C25="Dublagem - MO + Filme",'Custos insumos'!$D$4,IF(C25="Dublagem Cretone HM50",'Custos insumos'!$D$26,IF(C25="Dublagem Cretone HM70",'Custos insumos'!$F$10,))))))))))))) -> 0 | N25: =IF(B25="Texion Textil",0,IF(B25="Três Elos",0,IF(C25="Malha",0,IF(C25="Dublagem Cretone",'Custos insumos'!$D$23,IF(C25="Dublagem Spun",'Custos insumos'!$D$19,IF(C25="Espelhamento",0,IF(C25="Espelhamento 2x",0,IF(C25="Esp. + Pel.",0,IF(C25="Pel. + Spun",'Custos insumos'!$D$19,IF(C25="Dublagem Cretone PES",'Custos insumos'!$F$25,IF(C25="Dublagem Barreira",'Custos insumos'!$D$22,))))))))))) -> 0
B26: Compomax | C26: Felpagem | E26: 3 | F26: 0.3 | G26: 0.4 | H26: metro linear | I26: =G26/E26 -> 0.13333333 | J26: 45301 | L26: =G26-M26-N26 -> 0.4 | M26: =IF(B26="Texion Textil",0,IF(C26="Malha",'Custos insumos'!$B$24,IF(C26="Dublagem Cretone",'Custos insumos'!$D$7,IF(C26="Dublagem Spun",'Custos insumos'!$D$4,IF(C26="Espelhamento",'Custos insumos'!$B$11,IF(C26="Espelhamento 2x",2*'Custos insumos'!$B$11,IF(C26="Esp. + Pel.",'Custos insumos'!$B$11,IF(C26="Pel. + Spun",'Custos insumos'!$D$4,IF(C26="Dublagem Cretone PES",'Custos insumos'!$D$7,IF(C26="Dublagem Barreira",'Custos insumos'!$D$11,IF(C26="Dublagem - MO + Filme",'Custos insumos'!$D$4,IF(C26="Dublagem Cretone HM50",'Custos insumos'!$D$26,IF(C26="Dublagem Cretone HM70",'Custos insumos'!$F$10,))))))))))))) -> 0 | N26: =IF(B26="Texion Textil",0,IF(B26="Três Elos",0,IF(C26="Malha",0,IF(C26="Dublagem Cretone",'Custos insumos'!$D$23,IF(C26="Dublagem Spun",'Custos insumos'!$D$19,IF(C26="Espelhamento",0,IF(C26="Espelhamento 2x",0,IF(C26="Esp. + Pel.",0,IF(C26="Pel. + Spun",'Custos insumos'!$D$19,IF(C26="Dublagem Cretone PES",'Custos insumos'!$F$25,IF(C26="Dublagem Barreira",'Custos insumos'!$D$22,))))))))))) -> 0
B27: Covolan Benefic. | C27: Peletização | E27: 1 | F27: 0.5 | G27: 0.55 | H27: metro linear | I27: =G27/E27 -> 0.55 | J27: 45301 | L27: =G27-M27-N27 -> 0.55 | M27: =IF(B27="Texion Textil",0,IF(C27="Malha",'Custos insumos'!$B$24,IF(C27="Dublagem Cretone",'Custos insumos'!$D$7,IF(C27="Dublagem Spun",'Custos insumos'!$D$4,IF(C27="Espelhamento",'Custos insumos'!$B$11,IF(C27="Espelhamento 2x",2*'Custos insumos'!$B$11,IF(C27="Esp. + Pel.",'Custos insumos'!$B$11,IF(C27="Pel. + Spun",'Custos insumos'!$D$4,IF(C27="Dublagem Cretone PES",'Custos insumos'!$D$7,IF(C27="Dublagem Barreira",'Custos insumos'!$D$11,IF(C27="Dublagem - MO + Filme",'Custos insumos'!$D$4,IF(C27="Dublagem Cretone HM50",'Custos insumos'!$D$26,IF(C27="Dublagem Cretone HM70",'Custos insumos'!$F$10,))))))))))))) -> 0 | N27: =IF(B27="Texion Textil",0,IF(B27="Três Elos",0,IF(C27="Malha",0,IF(C27="Dublagem Cretone",'Custos insumos'!$D$23,IF(C27="Dublagem Spun",'Custos insumos'!$D$19,IF(C27="Espelhamento",0,IF(C27="Espelhamento 2x",0,IF(C27="Esp. + Pel.",0,IF(C27="Pel. + Spun",'Custos insumos'!$D$19,IF(C27="Dublagem Cretone PES",'Custos insumos'!$F$25,IF(C27="Dublagem Barreira",'Custos insumos'!$D$22,))))))))))) -> 0
B28: Covolan Benefic. | C28: Malha | E28: 1 | F28: 18.9 | G28: 20.9 | H28: kg | I28: =G28/E28 -> 20.9 | J28: 45301 | L28: =G28-M28-N28 -> 8.4 | M28: =IF(B28="Texion Textil",0,IF(C28="Malha",'Custos insumos'!$B$24,IF(C28="Dublagem Cretone",'Custos insumos'!$D$7,IF(C28="Dublagem Spun",'Custos insumos'!$D$4,IF(C28="Espelhamento",'Custos insumos'!$B$11,IF(C28="Espelhamento 2x",2*'Custos insumos'!$B$11,IF(C28="Esp. + Pel.",'Custos insumos'!$B$11,IF(C28="Pel. + Spun",'Custos insumos'!$D$4,IF(C28="Dublagem Cretone PES",'Custos insumos'!$D$7,IF(C28="Dublagem Barreira",'Custos insumos'!$D$11,IF(C28="Dublagem - MO + Filme",'Custos insumos'!$D$4,IF(C28="Dublagem Cretone HM50",'Custos insumos'!$D$26,IF(C28="Dublagem Cretone HM70",'Custos insumos'!$F$10,))))))))))))) -> 12.5 | N28: =IF(B28="Texion Textil",0,IF(B28="Três Elos",0,IF(C28="Malha",0,IF(C28="Dublagem Cretone",'Custos insumos'!$D$23,IF(C28="Dublagem Spun",'Custos insumos'!$D$19,IF(C28="Espelhamento",0,IF(C28="Espelhamento 2x",0,IF(C28="Esp. + Pel.",0,IF(C28="Pel. + Spun",'Custos insumos'!$D$19,IF(C28="Dublagem Cretone PES",'Custos insumos'!$F$25,IF(C28="Dublagem Barreira",'Custos insumos'!$D$22,))))))))))) -> 0
B29: DB RAINBOW | C29: Dublagem | E29: 1 | F29: 0.86 | G29: - | H29: metro linear | I29: =G29/E29 -> #VALUE! | J29: 45301 | L29: =G29-M29-N29 -> #VALUE! | M29: =IF(B29="Texion Textil",0,IF(C29="Malha",'Custos insumos'!$B$24,IF(C29="Dublagem Cretone",'Custos insumos'!$D$7,IF(C29="Dublagem Spun",'Custos insumos'!$D$4,IF(C29="Espelhamento",'Custos insumos'!$B$11,IF(C29="Espelhamento 2x",2*'Custos insumos'!$B$11,IF(C29="Esp. + Pel.",'Custos insumos'!$B$11,IF(C29="Pel. + Spun",'Custos insumos'!$D$4,IF(C29="Dublagem Cretone PES",'Custos insumos'!$D$7,IF(C29="Dublagem Barreira",'Custos insumos'!$D$11,IF(C29="Dublagem - MO + Filme",'Custos insumos'!$D$4,IF(C29="Dublagem Cretone HM50",'Custos insumos'!$D$26,IF(C29="Dublagem Cretone HM70",'Custos insumos'!$F$10,))))))))))))) -> 0 | N29: =IF(B29="Texion Textil",0,IF(B29="Três Elos",0,IF(C29="Malha",0,IF(C29="Dublagem Cretone",'Custos insumos'!$D$23,IF(C29="Dublagem Spun",'Custos insumos'!$D$19,IF(C29="Espelhamento",0,IF(C29="Espelhamento 2x",0,IF(C29="Esp. + Pel.",0,IF(C29="Pel. + Spun",'Custos insumos'!$D$19,IF(C29="Dublagem Cretone PES",'Custos insumos'!$F$25,IF(C29="Dublagem Barreira",'Custos insumos'!$D$22,))))))))))) -> 0
A30: ok | B30: DB RAINBOW | C30: Felpagem | E30: 1 | F30: 0.34 | G30: - | H30: metro linear | I30: =G30/E30 -> #VALUE! | J30: 45301 | L30: =G30-M30-N30 -> #VALUE! | M30: =IF(B30="Texion Textil",0,IF(C30="Malha",'Custos insumos'!$B$24,IF(C30="Dublagem Cretone",'Custos insumos'!$D$7,IF(C30="Dublagem Spun",'Custos insumos'!$D$4,IF(C30="Espelhamento",'Custos insumos'!$B$11,IF(C30="Espelhamento 2x",2*'Custos insumos'!$B$11,IF(C30="Esp. + Pel.",'Custos insumos'!$B$11,IF(C30="Pel. + Spun",'Custos insumos'!$D$4,IF(C30="Dublagem Cretone PES",'Custos insumos'!$D$7,IF(C30="Dublagem Barreira",'Custos insumos'!$D$11,IF(C30="Dublagem - MO + Filme",'Custos insumos'!$D$4,IF(C30="Dublagem Cretone HM50",'Custos insumos'!$D$26,IF(C30="Dublagem Cretone HM70",'Custos insumos'!$F$10,))))))))))))) -> 0 | N30: =IF(B30="Texion Textil",0,IF(B30="Três Elos",0,IF(C30="Malha",0,IF(C30="Dublagem Cretone",'Custos insumos'!$D$23,IF(C30="Dublagem Spun",'Custos insumos'!$D$19,IF(C30="Espelhamento",0,IF(C30="Espelhamento 2x",0,IF(C30="Esp. + Pel.",0,IF(C30="Pel. + Spun",'Custos insumos'!$D$19,IF(C30="Dublagem Cretone PES",'Custos insumos'!$F$25,IF(C30="Dublagem Barreira",'Custos insumos'!$D$22,))))))))))) -> 0
A31: ok | B31: DB RAINBOW | C31: Peletização | E31: 1 | F31: 0.34 | G31: - | H31: metro linear | I31: =G31/E31 -> #VALUE! | J31: 45301 | L31: =G31-M31-N31 -> #VALUE! | M31: =IF(B31="Texion Textil",0,IF(C31="Malha",'Custos insumos'!$B$24,IF(C31="Dublagem Cretone",'Custos insumos'!$D$7,IF(C31="Dublagem Spun",'Custos insumos'!$D$4,IF(C31="Espelhamento",'Custos insumos'!$B$11,IF(C31="Espelhamento 2x",2*'Custos insumos'!$B$11,IF(C31="Esp. + Pel.",'Custos insumos'!$B$11,IF(C31="Pel. + Spun",'Custos insumos'!$D$4,IF(C31="Dublagem Cretone PES",'Custos insumos'!$D$7,IF(C31="Dublagem Barreira",'Custos insumos'!$D$11,IF(C31="Dublagem - MO + Filme",'Custos insumos'!$D$4,IF(C31="Dublagem Cretone HM50",'Custos insumos'!$D$26,IF(C31="Dublagem Cretone HM70",'Custos insumos'!$F$10,))))))))))))) -> 0 | N31: =IF(B31="Texion Textil",0,IF(B31="Três Elos",0,IF(C31="Malha",0,IF(C31="Dublagem Cretone",'Custos insumos'!$D$23,IF(C31="Dublagem Spun",'Custos insumos'!$D$19,IF(C31="Espelhamento",0,IF(C31="Espelhamento 2x",0,IF(C31="Esp. + Pel.",0,IF(C31="Pel. + Spun",'Custos insumos'!$D$19,IF(C31="Dublagem Cretone PES",'Custos insumos'!$F$25,IF(C31="Dublagem Barreira",'Custos insumos'!$D$22,))))))))))) -> 0
A32: ok | B32: Ecosimple Ind. | C32: Fel. + Cal. | D32: Diversos | E32: 4 | F32: 4.25 | G32: 4.2 | H32: metro linear | I32: =G32/E32 -> 1.05 | J32: 45260 | K32: Felpar e termofixar | L32: =G32-M32-N32 -> 4.2 | M32: =IF(B32="Texion Textil",0,IF(C32="Malha",'Custos insumos'!$B$24,IF(C32="Dublagem Cretone",'Custos insumos'!$D$7,IF(C32="Dublagem Spun",'Custos insumos'!$D$4,IF(C32="Espelhamento",'Custos insumos'!$B$11,IF(C32="Espelhamento 2x",2*'Custos insumos'!$B$11,IF(C32="Esp. + Pel.",'Custos insumos'!$B$11,IF(C32="Pel. + Spun",'Custos insumos'!$D$4,IF(C32="Dublagem Cretone PES",'Custos insumos'!$D$7,IF(C32="Dublagem Barreira",'Custos insumos'!$D$11,IF(C32="Dublagem - MO + Filme",'Custos insumos'!$D$4,IF(C32="Dublagem Cretone HM50",'Custos insumos'!$D$26,IF(C32="Dublagem Cretone HM70",'Custos insumos'!$F$10,))))))))))))) -> 0 | N32: =IF(B32="Texion Textil",0,IF(B32="Três Elos",0,IF(C32="Malha",0,IF(C32="Dublagem Cretone",'Custos insumos'!$D$23,IF(C32="Dublagem Spun",'Custos insumos'!$D$19,IF(C32="Espelhamento",0,IF(C32="Espelhamento 2x",0,IF(C32="Esp. + Pel.",0,IF(C32="Pel. + Spun",'Custos insumos'!$D$19,IF(C32="Dublagem Cretone PES",'Custos insumos'!$F$25,IF(C32="Dublagem Barreira",'Custos insumos'!$D$22,))))))))))) -> 0
A33: ok | B33: Ecosimple Ind. | C33: Dublagem Juta | D33: Juta | E33: 1 | G33: 4.55 | H33: metro linear | I33: =G33/E33 -> 4.55 | J33: 45260 | K33: Insumos fornecidos por Tapajos | L33: =G33-M33-N33 -> 4.05 | M33: =IF(B33="Texion Textil",0,IF(C33="Malha",'Custos insumos'!$B$24,IF(C33="Dublagem Cretone",'Custos insumos'!$D$7,IF(C33="Dublagem Spun",'Custos insumos'!$D$4,IF(C33="Espelhamento",'Custos insumos'!$B$11,IF(C33="Espelhamento 2x",2*'Custos insumos'!$B$11,IF(C33="Esp. + Pel.",'Custos insumos'!$B$11,IF(C33="Pel. + Spun",'Custos insumos'!$D$4,IF(C33="Dublagem Cretone PES",'Custos insumos'!$D$7,IF(C33="Dublagem Barreira",'Custos insumos'!$D$11,IF(C33="Dublagem - MO + Filme",'Custos insumos'!$D$4,IF(C33="Dublagem Cretone HM50",'Custos insumos'!$D$26,IF(C33="Dublagem Cretone HM70",'Custos insumos'!$F$10,))))))))))))) -> 0 | N33: 0.5
A34: ok | B34: Ecosimple Ind. | C34: Dublagem Cretone - MO (Juta) | D34: Apenas cola (HM35; L:1,55m) e MO | E34: 1 | F34: 6.19 | G34: 2.9 | H34: metro linear | I34: =G34/E34 -> 2.9 | J34: 45260 | K34: Insumos fornecidos por Tapajos | L34: =G34-M34-N34 -> 2.9 | M34: =IF(B34="Texion Textil",0,IF(C34="Malha",'Custos insumos'!$B$24,IF(C34="Dublagem Cretone",'Custos insumos'!$D$7,IF(C34="Dublagem Spun",'Custos insumos'!$D$4,IF(C34="Espelhamento",'Custos insumos'!$B$11,IF(C34="Espelhamento 2x",2*'Custos insumos'!$B$11,IF(C34="Esp. + Pel.",'Custos insumos'!$B$11,IF(C34="Pel. + Spun",'Custos insumos'!$D$4,IF(C34="Dublagem Cretone PES",'Custos insumos'!$D$7,IF(C34="Dublagem Barreira",'Custos insumos'!$D$11,IF(C34="Dublagem - MO + Filme",'Custos insumos'!$D$4,IF(C34="Dublagem Cretone HM50",'Custos insumos'!$D$26,IF(C34="Dublagem Cretone HM70",'Custos insumos'!$F$10,))))))))))))) -> 0 | N34: =IF(B34="Texion Textil",0,IF(B34="Três Elos",0,IF(C34="Malha",0,IF(C34="Dublagem Cretone",'Custos insumos'!$D$23,IF(C34="Dublagem Spun",'Custos insumos'!$D$19,IF(C34="Espelhamento",0,IF(C34="Espelhamento 2x",0,IF(C34="Esp. + Pel.",0,IF(C34="Pel. + Spun",'Custos insumos'!$D$19,IF(C34="Dublagem Cretone PES",'Custos insumos'!$F$25,IF(C34="Dublagem Barreira",'Custos insumos'!$D$22,))))))))))) -> 0
A35: ok | B35: Ecosimple Ind. | C35: Dublagem Cretone | D35: Dublagem Tupy/New Tweed | E35: 1 | F35: 6.19 | G35: 6.1 | H35: metro linear | I35: =G35/E35 -> 6.1 | J35: 45260 | K35: Insumos fornecidos por Tapajos | L35: =G35-M35-N35 -> 1.81 | M35: =IF(B35="Texion Textil",0,IF(C35="Malha",'Custos insumos'!$B$24,IF(C35="Dublagem Cretone",'Custos insumos'!$D$7,IF(C35="Dublagem Spun",'Custos insumos'!$D$4,IF(C35="Espelhamento",'Custos insumos'!$B$11,IF(C35="Espelhamento 2x",2*'Custos insumos'!$B$11,IF(C35="Esp. + Pel.",'Custos insumos'!$B$11,IF(C35="Pel. + Spun",'Custos insumos'!$D$4,IF(C35="Dublagem Cretone PES",'Custos insumos'!$D$7,IF(C35="Dublagem Barreira",'Custos insumos'!$D$11,IF(C35="Dublagem - MO + Filme",'Custos insumos'!$D$4,IF(C35="Dublagem Cretone HM50",'Custos insumos'!$D$26,IF(C35="Dublagem Cretone HM70",'Custos insumos'!$F$10,))))))))))))) -> 1.962 | N35: =IF(B35="Texion Textil",0,IF(B35="Três Elos",0,IF(C35="Malha",0,IF(C35="Dublagem Cretone",'Custos insumos'!$D$23,IF(C35="Dublagem Spun",'Custos insumos'!$D$19,IF(C35="Espelhamento",0,IF(C35="Espelhamento 2x",0,IF(C35="Esp. + Pel.",0,IF(C35="Pel. + Spun",'Custos insumos'!$D$19,IF(C35="Dublagem Cretone PES",'Custos insumos'!$F$25,IF(C35="Dublagem Barreira",'Custos insumos'!$D$22,))))))))))) -> 2.328
A36: ok | B36: Ecosimple Ind. | C36: Dublagem Cretone PES - 1,6 | D36: 1,60m | E36: 1 | G36: 4.6 | H36: metro linear | I36: =G36/E36 -> 4.6 | J36: 45260 | K36: Insumos fornecidos por Tapajos | L36: =G36-M36-N36 -> 1.3312 | M36: ='Custos insumos'!F5 -> 0.9408 | N36: ='Custos insumos'!F25 -> 2.328
A37: ok | B37: Ecosimple Ind. | C37: Dublagem Cretone PES | E37: 1 | G37: 4.9 | H37: metro linear | I37: =G37/E37 -> 4.9 | J37: 45260 | K37: Insumos fornecidos por Tapajos | L37: =G37-M37-N37 -> 0.61 | M37: =IF(B37="Texion Textil",0,IF(C37="Malha",'Custos insumos'!$B$24,IF(C37="Dublagem Cretone",'Custos insumos'!$D$7,IF(C37="Dublagem Spun",'Custos insumos'!$D$4,IF(C37="Espelhamento",'Custos insumos'!$B$11,IF(C37="Espelhamento 2x",2*'Custos insumos'!$B$11,IF(C37="Esp. + Pel.",'Custos insumos'!$B$11,IF(C37="Pel. + Spun",'Custos insumos'!$D$4,IF(C37="Dublagem Cretone PES",'Custos insumos'!$D$7,IF(C37="Dublagem Barreira",'Custos insumos'!$D$11,IF(C37="Dublagem - MO + Filme",'Custos insumos'!$D$4,IF(C37="Dublagem Cretone HM50",'Custos insumos'!$D$26,IF(C37="Dublagem Cretone HM70",'Custos insumos'!$F$10,))))))))))))) -> 1.962 | N37: =IF(B37="Texion Textil",0,IF(B37="Três Elos",0,IF(C37="Malha",0,IF(C37="Dublagem Cretone",'Custos insumos'!$D$23,IF(C37="Dublagem Spun",'Custos insumos'!$D$19,IF(C37="Espelhamento",0,IF(C37="Espelhamento 2x",0,IF(C37="Esp. + Pel.",0,IF(C37="Pel. + Spun",'Custos insumos'!$D$19,IF(C37="Dublagem Cretone PES",'Custos insumos'!$F$25,IF(C37="Dublagem Barreira",'Custos insumos'!$D$22,))))))))))) -> 2.328
A38: ok | B38: Ecosimple Ind. | C38: Dublagem Spun | D38: Diversos | E38: 1 | F38: 4.63 | G38: 4.6 | H38: metro linear | I38: =G38/E38 -> 4.6 | J38: 45260 | K38: Insumos fornecidos por Tapajos | L38: =G38-M38-N38 -> 2.5858 | M38: =IF(B38="Texion Textil",0,IF(C38="Malha",'Custos insumos'!$B$24,IF(C38="Dublagem Cretone",'Custos insumos'!$D$7,IF(C38="Dublagem Spun",'Custos insumos'!$D$4,IF(C38="Espelhamento",'Custos insumos'!$B$11,IF(C38="Espelhamento 2x",2*'Custos insumos'!$B$11,IF(C38="Esp. + Pel.",'Custos insumos'!$B$11,IF(C38="Pel. + Spun",'Custos insumos'!$D$4,IF(C38="Dublagem Cretone PES",'Custos insumos'!$D$7,IF(C38="Dublagem Barreira",'Custos insumos'!$D$11,IF(C38="Dublagem - MO + Filme",'Custos insumos'!$D$4,IF(C38="Dublagem Cretone HM50",'Custos insumos'!$D$26,IF(C38="Dublagem Cretone HM70",'Custos insumos'!$F$10,))))))))))))) -> 1.1232 | N38: =IF(B38="Texion Textil",0,IF(B38="Três Elos",0,IF(C38="Malha",0,IF(C38="Dublagem Cretone",'Custos insumos'!$D$23,IF(C38="Dublagem Spun",'Custos insumos'!$D$19,IF(C38="Espelhamento",0,IF(C38="Espelhamento 2x",0,IF(C38="Esp. + Pel.",0,IF(C38="Pel. + Spun",'Custos insumos'!$D$19,IF(C38="Dublagem Cretone PES",'Custos insumos'!$F$25,IF(C38="Dublagem Barreira",'Custos insumos'!$D$22,))))))))))) -> 0.891
A39: ok | B39: Ecosimple Ind. | C39: Espelhamento | D39: C/ Filme Single | E39: 1 | F39: 2.76 | G39: 2.75 | H39: metro linear | I39: =G39/E39 -> 2.75 | J39: 45260 | K39: Espelhamento - TBU BC - Insumos fornecidos por Tapajos | L39: =G39-M39-N39 -> 1.6914997 | M39: =IF(B39="Texion Textil",0,IF(C39="Malha",'Custos insumos'!$B$24,IF(C39="Dublagem Cretone",'Custos insumos'!$D$7,IF(C39="Dublagem Spun",'Custos insumos'!$D$4,IF(C39="Espelhamento",'Custos insumos'!$B$11,IF(C39="Espelhamento 2x",2*'Custos insumos'!$B$11,IF(C39="Esp. + Pel.",'Custos insumos'!$B$11,IF(C39="Pel. + Spun",'Custos insumos'!$D$4,IF(C39="Dublagem Cretone PES",'Custos insumos'!$D$7,IF(C39="Dublagem Barreira",'Custos insumos'!$D$11,IF(C39="Dublagem - MO + Filme",'Custos insumos'!$D$4,IF(C39="Dublagem Cretone HM50",'Custos insumos'!$D$26,IF(C39="Dublagem Cretone HM70",'Custos insumos'!$F$10,))))))))))))) -> 1.0585003 | N39: =IF(B39="Texion Textil",0,IF(B39="Três Elos",0,IF(C39="Malha",0,IF(C39="Dublagem Cretone",'Custos insumos'!$D$23,IF(C39="Dublagem Spun",'Custos insumos'!$D$19,IF(C39="Espelhamento",0,IF(C39="Espelhamento 2x",0,IF(C39="Esp. + Pel.",0,IF(C39="Pel. + Spun",'Custos insumos'!$D$19,IF(C39="Dublagem Cretone PES",'Custos insumos'!$F$25,IF(C39="Dublagem Barreira",'Custos insumos'!$D$22,))))))))))) -> 0
A40: ok | B40: Ecosimple Ind. | C40: Espelhamento anti-chama | D40: Filme + Mão de obra | E40: 1 | F40: 4.6 | G40: 4.6 | H40: metro linear | I40: =G40/E40 -> 4.6 | J40: 45260 | K40: Espelhamento - Anti chama 150 ou 100 - Insumos fornecidos por Tapajos | L40: =G40-M40-N40 -> 4.6 | M40: =IF(B40="Texion Textil",0,IF(C40="Malha",'Custos insumos'!$B$24,IF(C40="Dublagem Cretone",'Custos insumos'!$D$7,IF(C40="Dublagem Spun",'Custos insumos'!$D$4,IF(C40="Espelhamento",'Custos insumos'!$B$11,IF(C40="Espelhamento 2x",2*'Custos insumos'!$B$11,IF(C40="Esp. + Pel.",'Custos insumos'!$B$11,IF(C40="Pel. + Spun",'Custos insumos'!$D$4,IF(C40="Dublagem Cretone PES",'Custos insumos'!$D$7,IF(C40="Dublagem Barreira",'Custos insumos'!$D$11,IF(C40="Dublagem - MO + Filme",'Custos insumos'!$D$4,IF(C40="Dublagem Cretone HM50",'Custos insumos'!$D$26,IF(C40="Dublagem Cretone HM70",'Custos insumos'!$F$10,))))))))))))) -> 0 | N40: =IF(B40="Texion Textil",0,IF(B40="Três Elos",0,IF(C40="Malha",0,IF(C40="Dublagem Cretone",'Custos insumos'!$D$23,IF(C40="Dublagem Spun",'Custos insumos'!$D$19,IF(C40="Espelhamento",0,IF(C40="Espelhamento 2x",0,IF(C40="Esp. + Pel.",0,IF(C40="Pel. + Spun",'Custos insumos'!$D$19,IF(C40="Dublagem Cretone PES",'Custos insumos'!$F$25,IF(C40="Dublagem Barreira",'Custos insumos'!$D$22,))))))))))) -> 0
A41: ok | B41: Ecosimple Ind. | C41: Felpagem | D41: Rubus flanelado/Vision/lana Color/ Casaco/ Andino/ Sarape/ Xadrez/jacquard | E41: 4 | F41: 4.83 | G41: 4.8 | H41: metro linear | I41: =G41/E41 -> 1.2 | J41: 45260 | L41: =G41-M41-N41 -> 4.8 | M41: =IF(B41="Texion Textil",0,IF(C41="Malha",'Custos insumos'!$B$24,IF(C41="Dublagem Cretone",'Custos insumos'!$D$7,IF(C41="Dublagem Spun",'Custos insumos'!$D$4,IF(C41="Espelhamento",'Custos insumos'!$B$11,IF(C41="Espelhamento 2x",2*'Custos insumos'!$B$11,IF(C41="Esp. + Pel.",'Custos insumos'!$B$11,IF(C41="Pel. + Spun",'Custos insumos'!$D$4,IF(C41="Dublagem Cretone PES",'Custos insumos'!$D$7,IF(C41="Dublagem Barreira",'Custos insumos'!$D$11,IF(C41="Dublagem - MO + Filme",'Custos insumos'!$D$4,IF(C41="Dublagem Cretone HM50",'Custos insumos'!$D$26,IF(C41="Dublagem Cretone HM70",'Custos insumos'!$F$10,))))))))))))) -> 0 | N41: =IF(B41="Texion Textil",0,IF(B41="Três Elos",0,IF(C41="Malha",0,IF(C41="Dublagem Cretone",'Custos insumos'!$D$23,IF(C41="Dublagem Spun",'Custos insumos'!$D$19,IF(C41="Espelhamento",0,IF(C41="Espelhamento 2x",0,IF(C41="Esp. + Pel.",0,IF(C41="Pel. + Spun",'Custos insumos'!$D$19,IF(C41="Dublagem Cretone PES",'Custos insumos'!$F$25,IF(C41="Dublagem Barreira",'Custos insumos'!$D$22,))))))))))) -> 0
A42: ok | B42: Ecosimple Ind. | C42: Felpagem | D42: Lana Vert/Grain/Max/Milao/Alana /alba/ Tela / LANA SHOT/Kihei/Panama | E42: 2 | F42: 2.64 | G42: 2.6 | H42: metro linear | I42: =G42/E42 -> 1.3 | J42: 45260 | L42: =G42-M42-N42 -> 2.6 | M42: =IF(B42="Texion Textil",0,IF(C42="Malha",'Custos insumos'!$B$24,IF(C42="Dublagem Cretone",'Custos insumos'!$D$7,IF(C42="Dublagem Spun",'Custos insumos'!$D$4,IF(C42="Espelhamento",'Custos insumos'!$B$11,IF(C42="Espelhamento 2x",2*'Custos insumos'!$B$11,IF(C42="Esp. + Pel.",'Custos insumos'!$B$11,IF(C42="Pel. + Spun",'Custos insumos'!$D$4,IF(C42="Dublagem Cretone PES",'Custos insumos'!$D$7,IF(C42="Dublagem Barreira",'Custos insumos'!$D$11,IF(C42="Dublagem - MO + Filme",'Custos insumos'!$D$4,IF(C42="Dublagem Cretone HM50",'Custos insumos'!$D$26,IF(C42="Dublagem Cretone HM70",'Custos insumos'!$F$10,))))))))))))) -> 0 | N42: =IF(B42="Texion Textil",0,IF(B42="Três Elos",0,IF(C42="Malha",0,IF(C42="Dublagem Cretone",'Custos insumos'!$D$23,IF(C42="Dublagem Spun",'Custos insumos'!$D$19,IF(C42="Espelhamento",0,IF(C42="Espelhamento 2x",0,IF(C42="Esp. + Pel.",0,IF(C42="Pel. + Spun",'Custos insumos'!$D$19,IF(C42="Dublagem Cretone PES",'Custos insumos'!$F$25,IF(C42="Dublagem Barreira",'Custos insumos'!$D$22,))))))))))) -> 0
A43: ok | B43: Ecosimple Ind. | C43: Felpagem | D43: Panama | E43: 2 | F43: 2.64 | G43: 1.7 | H43: metro linear | I43: =G43/E43 -> 0.85 | J43: 45260 | L43: =G43-M43-N43 -> 1.7 | M43: =IF(B43="Texion Textil",0,IF(C43="Malha",'Custos insumos'!$B$24,IF(C43="Dublagem Cretone",'Custos insumos'!$D$7,IF(C43="Dublagem Spun",'Custos insumos'!$D$4,IF(C43="Espelhamento",'Custos insumos'!$B$11,IF(C43="Espelhamento 2x",2*'Custos insumos'!$B$11,IF(C43="Esp. + Pel.",'Custos insumos'!$B$11,IF(C43="Pel. + Spun",'Custos insumos'!$D$4,IF(C43="Dublagem Cretone PES",'Custos insumos'!$D$7,IF(C43="Dublagem Barreira",'Custos insumos'!$D$11,IF(C43="Dublagem - MO + Filme",'Custos insumos'!$D$4,IF(C43="Dublagem Cretone HM50",'Custos insumos'!$D$26,IF(C43="Dublagem Cretone HM70",'Custos insumos'!$F$10,))))))))))))) -> 0 | N43: =IF(B43="Texion Textil",0,IF(B43="Três Elos",0,IF(C43="Malha",0,IF(C43="Dublagem Cretone",'Custos insumos'!$D$23,IF(C43="Dublagem Spun",'Custos insumos'!$D$19,IF(C43="Espelhamento",0,IF(C43="Espelhamento 2x",0,IF(C43="Esp. + Pel.",0,IF(C43="Pel. + Spun",'Custos insumos'!$D$19,IF(C43="Dublagem Cretone PES",'Custos insumos'!$F$25,IF(C43="Dublagem Barreira",'Custos insumos'!$D$22,))))))))))) -> 0
A44: ok | B44: Ecosimple Ind. | C44: Fel. + Pel. | D44: LISO/LISTRA | E44: 1 | F44: 2.57 | G44: 2.5 | H44: metro linear | I44: =G44/E44 -> 2.5 | J44: 45260 | L44: =G44-M44-N44 -> 2.5 | M44: =IF(B44="Texion Textil",0,IF(C44="Malha",'Custos insumos'!$B$24,IF(C44="Dublagem Cretone",'Custos insumos'!$D$7,IF(C44="Dublagem Spun",'Custos insumos'!$D$4,IF(C44="Espelhamento",'Custos insumos'!$B$11,IF(C44="Espelhamento 2x",2*'Custos insumos'!$B$11,IF(C44="Esp. + Pel.",'Custos insumos'!$B$11,IF(C44="Pel. + Spun",'Custos insumos'!$D$4,IF(C44="Dublagem Cretone PES",'Custos insumos'!$D$7,IF(C44="Dublagem Barreira",'Custos insumos'!$D$11,IF(C44="Dublagem - MO + Filme",'Custos insumos'!$D$4,IF(C44="Dublagem Cretone HM50",'Custos insumos'!$D$26,IF(C44="Dublagem Cretone HM70",'Custos insumos'!$F$10,))))))))))))) -> 0 | N44: =IF(B44="Texion Textil",0,IF(B44="Três Elos",0,IF(C44="Malha",0,IF(C44="Dublagem Cretone",'Custos insumos'!$D$23,IF(C44="Dublagem Spun",'Custos insumos'!$D$19,IF(C44="Espelhamento",0,IF(C44="Espelhamento 2x",0,IF(C44="Esp. + Pel.",0,IF(C44="Pel. + Spun",'Custos insumos'!$D$19,IF(C44="Dublagem Cretone PES",'Custos insumos'!$F$25,IF(C44="Dublagem Barreira",'Custos insumos'!$D$22,))))))))))) -> 0
A45: ok | B45: Ecosimple Ind. | C45: Peletização | D45: Lona Duty Stone/Lona Cargo | E45: 1 | F45: 3.22 | G45: 0.7 | H45: metro linear | I45: =G45/E45 -> 0.7 | J45: 45260 | K45: Alterado de 3,15 para 0,7 de acordo com o contato com a Marisa em 04'24 | L45: =G45-M45-N45 -> 0.7 | M45: =IF(B45="Texion Textil",0,IF(C45="Malha",'Custos insumos'!$B$24,IF(C45="Dublagem Cretone",'Custos insumos'!$D$7,IF(C45="Dublagem Spun",'Custos insumos'!$D$4,IF(C45="Espelhamento",'Custos insumos'!$B$11,IF(C45="Espelhamento 2x",2*'Custos insumos'!$B$11,IF(C45="Esp. + Pel.",'Custos insumos'!$B$11,IF(C45="Pel. + Spun",'Custos insumos'!$D$4,IF(C45="Dublagem Cretone PES",'Custos insumos'!$D$7,IF(C45="Dublagem Barreira",'Custos insumos'!$D$11,IF(C45="Dublagem - MO + Filme",'Custos insumos'!$D$4,IF(C45="Dublagem Cretone HM50",'Custos insumos'!$D$26,IF(C45="Dublagem Cretone HM70",'Custos insumos'!$F$10,))))))))))))) -> 0 | N45: =IF(B45="Texion Textil",0,IF(B45="Três Elos",0,IF(C45="Malha",0,IF(C45="Dublagem Cretone",'Custos insumos'!$D$23,IF(C45="Dublagem Spun",'Custos insumos'!$D$19,IF(C45="Espelhamento",0,IF(C45="Espelhamento 2x",0,IF(C45="Esp. + Pel.",0,IF(C45="Pel. + Spun",'Custos insumos'!$D$19,IF(C45="Dublagem Cretone PES",'Custos insumos'!$F$25,IF(C45="Dublagem Barreira",'Custos insumos'!$D$22,))))))))))) -> 0
A46: ok | B46: Ecosimple Ind. | C46: Calandra + Peletização | E46: 1 | F46: 3.6 | G46: 1.4 | H46: metro linear | I46: =G46/E46 -> 1.4 | J46: 45260 | K46: Alterado de 1,60 para 0,7 de acordo com o contato com a Marisa em 04'24 | L46: =G46-M46-N46 -> 1.4 | M46: =IF(B46="Texion Textil",0,IF(C46="Malha",'Custos insumos'!$B$24,IF(C46="Dublagem Cretone",'Custos insumos'!$D$7,IF(C46="Dublagem Spun",'Custos insumos'!$D$4,IF(C46="Espelhamento",'Custos insumos'!$B$11,IF(C46="Espelhamento 2x",2*'Custos insumos'!$B$11,IF(C46="Esp. + Pel.",'Custos insumos'!$B$11,IF(C46="Pel. + Spun",'Custos insumos'!$D$4,IF(C46="Dublagem Cretone PES",'Custos insumos'!$D$7,IF(C46="Dublagem Barreira",'Custos insumos'!$D$11,IF(C46="Dublagem - MO + Filme",'Custos insumos'!$D$4,IF(C46="Dublagem Cretone HM50",'Custos insumos'!$D$26,IF(C46="Dublagem Cretone HM70",'Custos insumos'!$F$10,))))))))))))) -> 0 | N46: =IF(B46="Texion Textil",0,IF(B46="Três Elos",0,IF(C46="Malha",0,IF(C46="Dublagem Cretone",'Custos insumos'!$D$23,IF(C46="Dublagem Spun",'Custos insumos'!$D$19,IF(C46="Espelhamento",0,IF(C46="Espelhamento 2x",0,IF(C46="Esp. + Pel.",0,IF(C46="Pel. + Spun",'Custos insumos'!$D$19,IF(C46="Dublagem Cretone PES",'Custos insumos'!$F$25,IF(C46="Dublagem Barreira",'Custos insumos'!$D$22,))))))))))) -> 0
A47: ok | B47: Ecosimple Ind. | C47: Calandra | D47: Sami/Maquinetado/Sublime | E47: 1 | F47: 3.6 | G47: 0.7 | H47: metro linear | I47: =G47/E47 -> 0.7 | J47: 45260 | K47: Alterado de 1,60 para 0,7 de acordo com o contato com a Marisa em 04'24 | L47: =G47-M47-N47 -> 0.7 | M47: =IF(B47="Texion Textil",0,IF(C47="Malha",'Custos insumos'!$B$24,IF(C47="Dublagem Cretone",'Custos insumos'!$D$7,IF(C47="Dublagem Spun",'Custos insumos'!$D$4,IF(C47="Espelhamento",'Custos insumos'!$B$11,IF(C47="Espelhamento 2x",2*'Custos insumos'!$B$11,IF(C47="Esp. + Pel.",'Custos insumos'!$B$11,IF(C47="Pel. + Spun",'Custos insumos'!$D$4,IF(C47="Dublagem Cretone PES",'Custos insumos'!$D$7,IF(C47="Dublagem Barreira",'Custos insumos'!$D$11,IF(C47="Dublagem - MO + Filme",'Custos insumos'!$D$4,IF(C47="Dublagem Cretone HM50",'Custos insumos'!$D$26,IF(C47="Dublagem Cretone HM70",'Custos insumos'!$F$10,))))))))))))) -> 0 | N47: =IF(B47="Texion Textil",0,IF(B47="Três Elos",0,IF(C47="Malha",0,IF(C47="Dublagem Cretone",'Custos insumos'!$D$23,IF(C47="Dublagem Spun",'Custos insumos'!$D$19,IF(C47="Espelhamento",0,IF(C47="Espelhamento 2x",0,IF(C47="Esp. + Pel.",0,IF(C47="Pel. + Spun",'Custos insumos'!$D$19,IF(C47="Dublagem Cretone PES",'Custos insumos'!$F$25,IF(C47="Dublagem Barreira",'Custos insumos'!$D$22,))))))))))) -> 0
A48: ok | B48: Engebank | C48: Dublagem Spun | E48: 1 | F48: 8.6 | G48: 8.6 | H48: metro linear | I48: =G48/E48 -> 8.6 | J48: 45301 | L48: =G48-M48-N48 -> 6.5858 | M48: =IF(B48="Texion Textil",0,IF(C48="Malha",'Custos insumos'!$B$24,IF(C48="Dublagem Cretone",'Custos insumos'!$D$7,IF(C48="Dublagem Spun",'Custos insumos'!$D$4,IF(C48="Espelhamento",'Custos insumos'!$B$11,IF(C48="Espelhamento 2x",2*'Custos insumos'!$B$11,IF(C48="Esp. + Pel.",'Custos insumos'!$B$11,IF(C48="Pel. + Spun",'Custos insumos'!$D$4,IF(C48="Dublagem Cretone PES",'Custos insumos'!$D$7,IF(C48="Dublagem Barreira",'Custos insumos'!$D$11,IF(C48="Dublagem - MO + Filme",'Custos insumos'!$D$4,IF(C48="Dublagem Cretone HM50",'Custos insumos'!$D$26,IF(C48="Dublagem Cretone HM70",'Custos insumos'!$F$10,))))))))))))) -> 1.1232 | N48: =IF(B48="Texion Textil",0,IF(B48="Três Elos",0,IF(C48="Malha",0,IF(C48="Dublagem Cretone",'Custos insumos'!$D$23,IF(C48="Dublagem Spun",'Custos insumos'!$D$19,IF(C48="Espelhamento",0,IF(C48="Espelhamento 2x",0,IF(C48="Esp. + Pel.",0,IF(C48="Pel. + Spun",'Custos insumos'!$D$19,IF(C48="Dublagem Cretone PES",'Custos insumos'!$F$25,IF(C48="Dublagem Barreira",'Custos insumos'!$D$22,))))))))))) -> 0.891
A49: ok | B49: Estopas Americana | C49: Calandra | E49: 1 | G49: 0.75 | H49: metro linear | I49: =G49/E49 -> 0.75 | J49: 45301 | L49: =G49-M49-N49 -> 0.75 | M49: =IF(B49="Texion Textil",0,IF(C49="Malha",'Custos insumos'!$B$24,IF(C49="Dublagem Cretone",'Custos insumos'!$D$7,IF(C49="Dublagem Spun",'Custos insumos'!$D$4,IF(C49="Espelhamento",'Custos insumos'!$B$11,IF(C49="Espelhamento 2x",2*'Custos insumos'!$B$11,IF(C49="Esp. + Pel.",'Custos insumos'!$B$11,IF(C49="Pel. + Spun",'Custos insumos'!$D$4,IF(C49="Dublagem Cretone PES",'Custos insumos'!$D$7,IF(C49="Dublagem Barreira",'Custos insumos'!$D$11,IF(C49="Dublagem - MO + Filme",'Custos insumos'!$D$4,IF(C49="Dublagem Cretone HM50",'Custos insumos'!$D$26,IF(C49="Dublagem Cretone HM70",'Custos insumos'!$F$10,))))))))))))) -> 0 | N49: =IF(B49="Texion Textil",0,IF(B49="Três Elos",0,IF(C49="Malha",0,IF(C49="Dublagem Cretone",'Custos insumos'!$D$23,IF(C49="Dublagem Spun",'Custos insumos'!$D$19,IF(C49="Espelhamento",0,IF(C49="Espelhamento 2x",0,IF(C49="Esp. + Pel.",0,IF(C49="Pel. + Spun",'Custos insumos'!$D$19,IF(C49="Dublagem Cretone PES",'Custos insumos'!$F$25,IF(C49="Dublagem Barreira",'Custos insumos'!$D$22,))))))))))) -> 0
B50: Estopas Americana | C50: Dublagem Tapete | E50: 1 | F50: 2.5 | G50: 4.5 | H50: metro linear | I50: =G50/E50 -> 4.5 | J50: 45301 | L50: =G50-M50-N50 -> 4.5 | M50: =IF(B50="Texion Textil",0,IF(C50="Malha",'Custos insumos'!$B$24,IF(C50="Dublagem Cretone",'Custos insumos'!$D$7,IF(C50="Dublagem Spun",'Custos insumos'!$D$4,IF(C50="Espelhamento",'Custos insumos'!$B$11,IF(C50="Espelhamento 2x",2*'Custos insumos'!$B$11,IF(C50="Esp. + Pel.",'Custos insumos'!$B$11,IF(C50="Pel. + Spun",'Custos insumos'!$D$4,IF(C50="Dublagem Cretone PES",'Custos insumos'!$D$7,IF(C50="Dublagem Barreira",'Custos insumos'!$D$11,IF(C50="Dublagem - MO + Filme",'Custos insumos'!$D$4,IF(C50="Dublagem Cretone HM50",'Custos insumos'!$D$26,IF(C50="Dublagem Cretone HM70",'Custos insumos'!$F$10,))))))))))))) -> 0 | N50: =IF(B50="Texion Textil",0,IF(B50="Três Elos",0,IF(C50="Malha",0,IF(C50="Dublagem Cretone",'Custos insumos'!$D$23,IF(C50="Dublagem Spun",'Custos insumos'!$D$19,IF(C50="Espelhamento",0,IF(C50="Espelhamento 2x",0,IF(C50="Esp. + Pel.",0,IF(C50="Pel. + Spun",'Custos insumos'!$D$19,IF(C50="Dublagem Cretone PES",'Custos insumos'!$F$25,IF(C50="Dublagem Barreira",'Custos insumos'!$D$22,))))))))))) -> 0
B51: Estopas Americana | C51: Dublagem Tapete - MO | E51: 1 | F51: 2.5 | G51: 4.5 | H51: metro linear | I51: =G51/E51 -> 4.5 | J51: 45301 | L51: =G51-M51-N51 -> 4.5 | M51: =IF(B51="Texion Textil",0,IF(C51="Malha",'Custos insumos'!$B$24,IF(C51="Dublagem Cretone",'Custos insumos'!$D$7,IF(C51="Dublagem Spun",'Custos insumos'!$D$4,IF(C51="Espelhamento",'Custos insumos'!$B$11,IF(C51="Espelhamento 2x",2*'Custos insumos'!$B$11,IF(C51="Esp. + Pel.",'Custos insumos'!$B$11,IF(C51="Pel. + Spun",'Custos insumos'!$D$4,IF(C51="Dublagem Cretone PES",'Custos insumos'!$D$7,IF(C51="Dublagem Barreira",'Custos insumos'!$D$11,IF(C51="Dublagem - MO + Filme",'Custos insumos'!$D$4,IF(C51="Dublagem Cretone HM50",'Custos insumos'!$D$26,IF(C51="Dublagem Cretone HM70",'Custos insumos'!$F$10,))))))))))))) -> 0 | N51: =IF(B51="Texion Textil",0,IF(B51="Três Elos",0,IF(C51="Malha",0,IF(C51="Dublagem Cretone",'Custos insumos'!$D$23,IF(C51="Dublagem Spun",'Custos insumos'!$D$19,IF(C51="Espelhamento",0,IF(C51="Espelhamento 2x",0,IF(C51="Esp. + Pel.",0,IF(C51="Pel. + Spun",'Custos insumos'!$D$19,IF(C51="Dublagem Cretone PES",'Custos insumos'!$F$25,IF(C51="Dublagem Barreira",'Custos insumos'!$D$22,))))))))))) -> 0
B52: Estopas Americana | C52: Dublagem Spun | E52: 1 | F52: 5.98 | G52: 6.1 | H52: metro linear | I52: =G52/E52 -> 6.1 | J52: 45301 | L52: =G52-M52-N52 -> 4.0858 | M52: =IF(B52="Texion Textil",0,IF(C52="Malha",'Custos insumos'!$B$24,IF(C52="Dublagem Cretone",'Custos insumos'!$D$7,IF(C52="Dublagem Spun",'Custos insumos'!$D$4,IF(C52="Espelhamento",'Custos insumos'!$B$11,IF(C52="Espelhamento 2x",2*'Custos insumos'!$B$11,IF(C52="Esp. + Pel.",'Custos insumos'!$B$11,IF(C52="Pel. + Spun",'Custos insumos'!$D$4,IF(C52="Dublagem Cretone PES",'Custos insumos'!$D$7,IF(C52="Dublagem Barreira",'Custos insumos'!$D$11,IF(C52="Dublagem - MO + Filme",'Custos insumos'!$D$4,IF(C52="Dublagem Cretone HM50",'Custos insumos'!$D$26,IF(C52="Dublagem Cretone HM70",'Custos insumos'!$F$10,))))))))))))) -> 1.1232 | N52: =IF(B52="Texion Textil",0,IF(B52="Três Elos",0,IF(C52="Malha",0,IF(C52="Dublagem Cretone",'Custos insumos'!$D$23,IF(C52="Dublagem Spun",'Custos insumos'!$D$19,IF(C52="Espelhamento",0,IF(C52="Espelhamento 2x",0,IF(C52="Esp. + Pel.",0,IF(C52="Pel. + Spun",'Custos insumos'!$D$19,IF(C52="Dublagem Cretone PES",'Custos insumos'!$F$25,IF(C52="Dublagem Barreira",'Custos insumos'!$D$22,))))))))))) -> 0.891
B53: Estopas Americana | C53: Felpagem | E53: 2 | F53: 0.98 | G53: 1.05 | H53: metro linear | I53: =G53/E53 -> 0.525 | J53: 45301 | L53: =G53-M53-N53 -> 1.05 | M53: =IF(B53="Texion Textil",0,IF(C53="Malha",'Custos insumos'!$B$24,IF(C53="Dublagem Cretone",'Custos insumos'!$D$7,IF(C53="Dublagem Spun",'Custos insumos'!$D$4,IF(C53="Espelhamento",'Custos insumos'!$B$11,IF(C53="Espelhamento 2x",2*'Custos insumos'!$B$11,IF(C53="Esp. + Pel.",'Custos insumos'!$B$11,IF(C53="Pel. + Spun",'Custos insumos'!$D$4,IF(C53="Dublagem Cretone PES",'Custos insumos'!$D$7,IF(C53="Dublagem Barreira",'Custos insumos'!$D$11,IF(C53="Dublagem - MO + Filme",'Custos insumos'!$D$4,IF(C53="Dublagem Cretone HM50",'Custos insumos'!$D$26,IF(C53="Dublagem Cretone HM70",'Custos insumos'!$F$10,))))))))))))) -> 0 | N53: =IF(B53="Texion Textil",0,IF(B53="Três Elos",0,IF(C53="Malha",0,IF(C53="Dublagem Cretone",'Custos insumos'!$D$23,IF(C53="Dublagem Spun",'Custos insumos'!$D$19,IF(C53="Espelhamento",0,IF(C53="Espelhamento 2x",0,IF(C53="Esp. + Pel.",0,IF(C53="Pel. + Spun",'Custos insumos'!$D$19,IF(C53="Dublagem Cretone PES",'Custos insumos'!$F$25,IF(C53="Dublagem Barreira",'Custos insumos'!$D$22,))))))))))) -> 0
B54: Fitecom | C54: Felpagem | E54: 1 | G54: 0.77 | H54: metro linear | I54: =G54/E54 -> 0.77 | L54: =G54-M54-N54 -> 0.77 | M54: =IF(B54="Texion Textil",0,IF(C54="Malha",'Custos insumos'!$B$24,IF(C54="Dublagem Cretone",'Custos insumos'!$D$7,IF(C54="Dublagem Spun",'Custos insumos'!$D$4,IF(C54="Espelhamento",'Custos insumos'!$B$11,IF(C54="Espelhamento 2x",2*'Custos insumos'!$B$11,IF(C54="Esp. + Pel.",'Custos insumos'!$B$11,IF(C54="Pel. + Spun",'Custos insumos'!$D$4,IF(C54="Dublagem Cretone PES",'Custos insumos'!$D$7,IF(C54="Dublagem Barreira",'Custos insumos'!$D$11,IF(C54="Dublagem - MO + Filme",'Custos insumos'!$D$4,IF(C54="Dublagem Cretone HM50",'Custos insumos'!$D$26,IF(C54="Dublagem Cretone HM70",'Custos insumos'!$F$10,))))))))))))) -> 0 | N54: =IF(B54="Texion Textil",0,IF(B54="Três Elos",0,IF(C54="Malha",0,IF(C54="Dublagem Cretone",'Custos insumos'!$D$23,IF(C54="Dublagem Spun",'Custos insumos'!$D$19,IF(C54="Espelhamento",0,IF(C54="Espelhamento 2x",0,IF(C54="Esp. + Pel.",0,IF(C54="Pel. + Spun",'Custos insumos'!$D$19,IF(C54="Dublagem Cretone PES",'Custos insumos'!$F$25,IF(C54="Dublagem Barreira",'Custos insumos'!$D$22,))))))))))) -> 0
B55: Iberfios | C55: Peletização | E55: 1 | F55: 0.6 | G55: 0.6 | H55: metro linear | I55: =G55/E55 -> 0.6 | J55: 45301 | L55: =G55-M55-N55 -> 0.6 | M55: =IF(B55="Texion Textil",0,IF(C55="Malha",'Custos insumos'!$B$24,IF(C55="Dublagem Cretone",'Custos insumos'!$D$7,IF(C55="Dublagem Spun",'Custos insumos'!$D$4,IF(C55="Espelhamento",'Custos insumos'!$B$11,IF(C55="Espelhamento 2x",2*'Custos insumos'!$B$11,IF(C55="Esp. + Pel.",'Custos insumos'!$B$11,IF(C55="Pel. + Spun",'Custos insumos'!$D$4,IF(C55="Dublagem Cretone PES",'Custos insumos'!$D$7,IF(C55="Dublagem Barreira",'Custos insumos'!$D$11,IF(C55="Dublagem - MO + Filme",'Custos insumos'!$D$4,IF(C55="Dublagem Cretone HM50",'Custos insumos'!$D$26,IF(C55="Dublagem Cretone HM70",'Custos insumos'!$F$10,))))))))))))) -> 0 | N55: =IF(B55="Texion Textil",0,IF(B55="Três Elos",0,IF(C55="Malha",0,IF(C55="Dublagem Cretone",'Custos insumos'!$D$23,IF(C55="Dublagem Spun",'Custos insumos'!$D$19,IF(C55="Espelhamento",0,IF(C55="Espelhamento 2x",0,IF(C55="Esp. + Pel.",0,IF(C55="Pel. + Spun",'Custos insumos'!$D$19,IF(C55="Dublagem Cretone PES",'Custos insumos'!$F$25,IF(C55="Dublagem Barreira",'Custos insumos'!$D$22,))))))))))) -> 0
A56: ok | B56: Ibirapuera Textil | C56: Felpagem | E56: 2 | F56: 1.2 | G56: 1.2 | H56: metro linear | I56: =G56/E56 -> 0.6 | J56: 45301 | L56: =G56-M56-N56 -> 1.2 | M56: =IF(B56="Texion Textil",0,IF(C56="Malha",'Custos insumos'!$B$24,IF(C56="Dublagem Cretone",'Custos insumos'!$D$7,IF(C56="Dublagem Spun",'Custos insumos'!$D$4,IF(C56="Espelhamento",'Custos insumos'!$B$11,IF(C56="Espelhamento 2x",2*'Custos insumos'!$B$11,IF(C56="Esp. + Pel.",'Custos insumos'!$B$11,IF(C56="Pel. + Spun",'Custos insumos'!$D$4,IF(C56="Dublagem Cretone PES",'Custos insumos'!$D$7,IF(C56="Dublagem Barreira",'Custos insumos'!$D$11,IF(C56="Dublagem - MO + Filme",'Custos insumos'!$D$4,IF(C56="Dublagem Cretone HM50",'Custos insumos'!$D$26,IF(C56="Dublagem Cretone HM70",'Custos insumos'!$F$10,))))))))))))) -> 0 | N56: =IF(B56="Texion Textil",0,IF(B56="Três Elos",0,IF(C56="Malha",0,IF(C56="Dublagem Cretone",'Custos insumos'!$D$23,IF(C56="Dublagem Spun",'Custos insumos'!$D$19,IF(C56="Espelhamento",0,IF(C56="Espelhamento 2x",0,IF(C56="Esp. + Pel.",0,IF(C56="Pel. + Spun",'Custos insumos'!$D$19,IF(C56="Dublagem Cretone PES",'Custos insumos'!$F$25,IF(C56="Dublagem Barreira",'Custos insumos'!$D$22,))))))))))) -> 0
A57: ok | B57: Innovativ Ind. | C57: Esp. + Pel. | E57: 1 | F57: 3.2 | G57: 3.5 | H57: metro linear | I57: =G57/E57 -> 3.5 | J57: 45301 | L57: =G57-M57-N57 -> 2.4414997 | M57: =IF(B57="Texion Textil",0,IF(C57="Malha",'Custos insumos'!$B$24,IF(C57="Dublagem Cretone",'Custos insumos'!$D$7,IF(C57="Dublagem Spun",'Custos insumos'!$D$4,IF(C57="Espelhamento",'Custos insumos'!$B$11,IF(C57="Espelhamento 2x",2*'Custos insumos'!$B$11,IF(C57="Esp. + Pel.",'Custos insumos'!$B$11,IF(C57="Pel. + Spun",'Custos insumos'!$D$4,IF(C57="Dublagem Cretone PES",'Custos insumos'!$D$7,IF(C57="Dublagem Barreira",'Custos insumos'!$D$11,IF(C57="Dublagem - MO + Filme",'Custos insumos'!$D$4,IF(C57="Dublagem Cretone HM50",'Custos insumos'!$D$26,IF(C57="Dublagem Cretone HM70",'Custos insumos'!$F$10,))))))))))))) -> 1.0585003 | N57: =IF(B57="Texion Textil",0,IF(B57="Três Elos",0,IF(C57="Malha",0,IF(C57="Dublagem Cretone",'Custos insumos'!$D$23,IF(C57="Dublagem Spun",'Custos insumos'!$D$19,IF(C57="Espelhamento",0,IF(C57="Espelhamento 2x",0,IF(C57="Esp. + Pel.",0,IF(C57="Pel. + Spun",'Custos insumos'!$D$19,IF(C57="Dublagem Cretone PES",'Custos insumos'!$F$25,IF(C57="Dublagem Barreira",'Custos insumos'!$D$22,))))))))))) -> 0
A58: ok | B58: Innovativ Ind. | C58: Espelhamento | E58: 1 | G58: 2.75 | H58: metro linear | I58: =G58/E58 -> 2.75 | J58: 45301 | L58: =G58-M58-N58 -> 1.6914997 | M58: =IF(B58="Texion Textil",0,IF(C58="Malha",'Custos insumos'!$B$24,IF(C58="Dublagem Cretone",'Custos insumos'!$D$7,IF(C58="Dublagem Spun",'Custos insumos'!$D$4,IF(C58="Espelhamento",'Custos insumos'!$B$11,IF(C58="Espelhamento 2x",2*'Custos insumos'!$B$11,IF(C58="Esp. + Pel.",'Custos insumos'!$B$11,IF(C58="Pel. + Spun",'Custos insumos'!$D$4,IF(C58="Dublagem Cretone PES",'Custos insumos'!$D$7,IF(C58="Dublagem Barreira",'Custos insumos'!$D$11,IF(C58="Dublagem - MO + Filme",'Custos insumos'!$D$4,IF(C58="Dublagem Cretone HM50",'Custos insumos'!$D$26,IF(C58="Dublagem Cretone HM70",'Custos insumos'!$F$10,))))))))))))) -> 1.0585003 | N58: =IF(B58="Texion Textil",0,IF(B58="Três Elos",0,IF(C58="Malha",0,IF(C58="Dublagem Cretone",'Custos insumos'!$D$23,IF(C58="Dublagem Spun",'Custos insumos'!$D$19,IF(C58="Espelhamento",0,IF(C58="Espelhamento 2x",0,IF(C58="Esp. + Pel.",0,IF(C58="Pel. + Spun",'Custos insumos'!$D$19,IF(C58="Dublagem Cretone PES",'Custos insumos'!$F$25,IF(C58="Dublagem Barreira",'Custos insumos'!$D$22,))))))))))) -> 0
A59: ok | B59: Innovativ Ind. | C59: Espelhamento 2x | E59: 1 | G59: =(2*1.17)+(2*1.15)+0.36 -> 5 | H59: metro linear | I59: =G59/E59 -> 5 | J59: 45301 | L59: =G59-M59-N59 -> 2.8829994 | M59: =IF(B59="Texion Textil",0,IF(C59="Malha",'Custos insumos'!$B$24,IF(C59="Dublagem Cretone",'Custos insumos'!$D$7,IF(C59="Dublagem Spun",'Custos insumos'!$D$4,IF(C59="Espelhamento",'Custos insumos'!$B$11,IF(C59="Espelhamento 2x",2*'Custos insumos'!$B$11,IF(C59="Esp. + Pel.",'Custos insumos'!$B$11,IF(C59="Pel. + Spun",'Custos insumos'!$D$4,IF(C59="Dublagem Cretone PES",'Custos insumos'!$D$7,IF(C59="Dublagem Barreira",'Custos insumos'!$D$11,IF(C59="Dublagem - MO + Filme",'Custos insumos'!$D$4,IF(C59="Dublagem Cretone HM50",'Custos insumos'!$D$26,IF(C59="Dublagem Cretone HM70",'Custos insumos'!$F$10,))))))))))))) -> 2.1170006 | N59: =IF(B59="Texion Textil",0,IF(B59="Três Elos",0,IF(C59="Malha",0,IF(C59="Dublagem Cretone",'Custos insumos'!$D$23,IF(C59="Dublagem Spun",'Custos insumos'!$D$19,IF(C59="Espelhamento",0,IF(C59="Espelhamento 2x",0,IF(C59="Esp. + Pel.",0,IF(C59="Pel. + Spun",'Custos insumos'!$D$19,IF(C59="Dublagem Cretone PES",'Custos insumos'!$F$25,IF(C59="Dublagem Barreira",'Custos insumos'!$D$22,))))))))))) -> 0
A60: ok | B60: Innovativ Ind. | C60: Peletização | E60: 1 | F60: 0.57 | G60: 0.65 | H60: metro linear | I60: =G60/E60 -> 0.65 | J60: 45301 | L60: =G60-M60-N60 -> 0.65 | M60: =IF(B60="Texion Textil",0,IF(C60="Malha",'Custos insumos'!$B$24,IF(C60="Dublagem Cretone",'Custos insumos'!$D$7,IF(C60="Dublagem Spun",'Custos insumos'!$D$4,IF(C60="Espelhamento",'Custos insumos'!$B$11,IF(C60="Espelhamento 2x",2*'Custos insumos'!$B$11,IF(C60="Esp. + Pel.",'Custos insumos'!$B$11,IF(C60="Pel. + Spun",'Custos insumos'!$D$4,IF(C60="Dublagem Cretone PES",'Custos insumos'!$D$7,IF(C60="Dublagem Barreira",'Custos insumos'!$D$11,IF(C60="Dublagem - MO + Filme",'Custos insumos'!$D$4,IF(C60="Dublagem Cretone HM50",'Custos insumos'!$D$26,IF(C60="Dublagem Cretone HM70",'Custos insumos'!$F$10,))))))))))))) -> 0 | N60: =IF(B60="Texion Textil",0,IF(B60="Três Elos",0,IF(C60="Malha",0,IF(C60="Dublagem Cretone",'Custos insumos'!$D$23,IF(C60="Dublagem Spun",'Custos insumos'!$D$19,IF(C60="Espelhamento",0,IF(C60="Espelhamento 2x",0,IF(C60="Esp. + Pel.",0,IF(C60="Pel. + Spun",'Custos insumos'!$D$19,IF(C60="Dublagem Cretone PES",'Custos insumos'!$F$25,IF(C60="Dublagem Barreira",'Custos insumos'!$D$22,))))))))))) -> 0
A61: ok | B61: Innovativ Ind. | C61: Felpagem | D61: Diversos | E61: 2 | F61: 1.1 | G61: 1.25 | H61: metro linear | I61: =G61/E61 -> 0.625 | J61: 45301 | L61: =G61-M61-N61 -> 1.25 | M61: =IF(B61="Texion Textil",0,IF(C61="Malha",'Custos insumos'!$B$24,IF(C61="Dublagem Cretone",'Custos insumos'!$D$7,IF(C61="Dublagem Spun",'Custos insumos'!$D$4,IF(C61="Espelhamento",'Custos insumos'!$B$11,IF(C61="Espelhamento 2x",2*'Custos insumos'!$B$11,IF(C61="Esp. + Pel.",'Custos insumos'!$B$11,IF(C61="Pel. + Spun",'Custos insumos'!$D$4,IF(C61="Dublagem Cretone PES",'Custos insumos'!$D$7,IF(C61="Dublagem Barreira",'Custos insumos'!$D$11,IF(C61="Dublagem - MO + Filme",'Custos insumos'!$D$4,IF(C61="Dublagem Cretone HM50",'Custos insumos'!$D$26,IF(C61="Dublagem Cretone HM70",'Custos insumos'!$F$10,))))))))))))) -> 0 | N61: =IF(B61="Texion Textil",0,IF(B61="Três Elos",0,IF(C61="Malha",0,IF(C61="Dublagem Cretone",'Custos insumos'!$D$23,IF(C61="Dublagem Spun",'Custos insumos'!$D$19,IF(C61="Espelhamento",0,IF(C61="Espelhamento 2x",0,IF(C61="Esp. + Pel.",0,IF(C61="Pel. + Spun",'Custos insumos'!$D$19,IF(C61="Dublagem Cretone PES",'Custos insumos'!$F$25,IF(C61="Dublagem Barreira",'Custos insumos'!$D$22,))))))))))) -> 0
A62: ok | B62: Innovativ Ind. | C62: Felpagem | D62: Lona | E62: 1 | F62: 0.98 | G62: 1.15 | H62: metro linear | I62: =G62/E62 -> 1.15 | J62: 45301 | L62: =G62-M62-N62 -> 1.15 | M62: =IF(B62="Texion Textil",0,IF(C62="Malha",'Custos insumos'!$B$24,IF(C62="Dublagem Cretone",'Custos insumos'!$D$7,IF(C62="Dublagem Spun",'Custos insumos'!$D$4,IF(C62="Espelhamento",'Custos insumos'!$B$11,IF(C62="Espelhamento 2x",2*'Custos insumos'!$B$11,IF(C62="Esp. + Pel.",'Custos insumos'!$B$11,IF(C62="Pel. + Spun",'Custos insumos'!$D$4,IF(C62="Dublagem Cretone PES",'Custos insumos'!$D$7,IF(C62="Dublagem Barreira",'Custos insumos'!$D$11,IF(C62="Dublagem - MO + Filme",'Custos insumos'!$D$4,IF(C62="Dublagem Cretone HM50",'Custos insumos'!$D$26,IF(C62="Dublagem Cretone HM70",'Custos insumos'!$F$10,))))))))))))) -> 0 | N62: =IF(B62="Texion Textil",0,IF(B62="Três Elos",0,IF(C62="Malha",0,IF(C62="Dublagem Cretone",'Custos insumos'!$D$23,IF(C62="Dublagem Spun",'Custos insumos'!$D$19,IF(C62="Espelhamento",0,IF(C62="Espelhamento 2x",0,IF(C62="Esp. + Pel.",0,IF(C62="Pel. + Spun",'Custos insumos'!$D$19,IF(C62="Dublagem Cretone PES",'Custos insumos'!$F$25,IF(C62="Dublagem Barreira",'Custos insumos'!$D$22,))))))))))) -> 0
A63: ok | B63: Innovativ Ind. | C63: Felpagem | D63: Lolla | E63: 3 | F63: 1.71 | G63: 2.15 | H63: metro linear | I63: =G63/E63 -> 0.71666667 | J63: 45301 | L63: =G63-M63-N63 -> 2.15 | M63: =IF(B63="Texion Textil",0,IF(C63="Malha",'Custos insumos'!$B$24,IF(C63="Dublagem Cretone",'Custos insumos'!$D$7,IF(C63="Dublagem Spun",'Custos insumos'!$D$4,IF(C63="Espelhamento",'Custos insumos'!$B$11,IF(C63="Espelhamento 2x",2*'Custos insumos'!$B$11,IF(C63="Esp. + Pel.",'Custos insumos'!$B$11,IF(C63="Pel. + Spun",'Custos insumos'!$D$4,IF(C63="Dublagem Cretone PES",'Custos insumos'!$D$7,IF(C63="Dublagem Barreira",'Custos insumos'!$D$11,IF(C63="Dublagem - MO + Filme",'Custos insumos'!$D$4,IF(C63="Dublagem Cretone HM50",'Custos insumos'!$D$26,IF(C63="Dublagem Cretone HM70",'Custos insumos'!$F$10,))))))))))))) -> 0 | N63: =IF(B63="Texion Textil",0,IF(B63="Três Elos",0,IF(C63="Malha",0,IF(C63="Dublagem Cretone",'Custos insumos'!$D$23,IF(C63="Dublagem Spun",'Custos insumos'!$D$19,IF(C63="Espelhamento",0,IF(C63="Espelhamento 2x",0,IF(C63="Esp. + Pel.",0,IF(C63="Pel. + Spun",'Custos insumos'!$D$19,IF(C63="Dublagem Cretone PES",'Custos insumos'!$F$25,IF(C63="Dublagem Barreira",'Custos insumos'!$D$22,))))))))))) -> 0
A64: ok | B64: Innovativ Ind. | C64: Malha | E64: 1 | F64: 18.9 | G64: 20.9 | H64: kg | I64: =G64/E64 -> 20.9 | J64: 45301 | L64: =G64-M64-N64 -> 8.4 | M64: =IF(B64="Texion Textil",0,IF(C64="Malha",'Custos insumos'!$B$24,IF(C64="Dublagem Cretone",'Custos insumos'!$D$7,IF(C64="Dublagem Spun",'Custos insumos'!$D$4,IF(C64="Espelhamento",'Custos insumos'!$B$11,IF(C64="Espelhamento 2x",2*'Custos insumos'!$B$11,IF(C64="Esp. + Pel.",'Custos insumos'!$B$11,IF(C64="Pel. + Spun",'Custos insumos'!$D$4,IF(C64="Dublagem Cretone PES",'Custos insumos'!$D$7,IF(C64="Dublagem Barreira",'Custos insumos'!$D$11,IF(C64="Dublagem - MO + Filme",'Custos insumos'!$D$4,IF(C64="Dublagem Cretone HM50",'Custos insumos'!$D$26,IF(C64="Dublagem Cretone HM70",'Custos insumos'!$F$10,))))))))))))) -> 12.5 | N64: =IF(B64="Texion Textil",0,IF(B64="Três Elos",0,IF(C64="Malha",0,IF(C64="Dublagem Cretone",'Custos insumos'!$D$23,IF(C64="Dublagem Spun",'Custos insumos'!$D$19,IF(C64="Espelhamento",0,IF(C64="Espelhamento 2x",0,IF(C64="Esp. + Pel.",0,IF(C64="Pel. + Spun",'Custos insumos'!$D$19,IF(C64="Dublagem Cretone PES",'Custos insumos'!$F$25,IF(C64="Dublagem Barreira",'Custos insumos'!$D$22,))))))))))) -> 0
A65: ok | B65: Irineu Meneghel | C65: Felpagem | E65: 1 | F65: 2.39 | G65: 2.39 | H65: metro linear | I65: =G65/E65 -> 2.39 | J65: 45301 | L65: =G65-M65-N65 -> 2.39 | M65: =IF(B65="Texion Textil",0,IF(C65="Malha",'Custos insumos'!$B$24,IF(C65="Dublagem Cretone",'Custos insumos'!$D$7,IF(C65="Dublagem Spun",'Custos insumos'!$D$4,IF(C65="Espelhamento",'Custos insumos'!$B$11,IF(C65="Espelhamento 2x",2*'Custos insumos'!$B$11,IF(C65="Esp. + Pel.",'Custos insumos'!$B$11,IF(C65="Pel. + Spun",'Custos insumos'!$D$4,IF(C65="Dublagem Cretone PES",'Custos insumos'!$D$7,IF(C65="Dublagem Barreira",'Custos insumos'!$D$11,IF(C65="Dublagem - MO + Filme",'Custos insumos'!$D$4,IF(C65="Dublagem Cretone HM50",'Custos insumos'!$D$26,IF(C65="Dublagem Cretone HM70",'Custos insumos'!$F$10,))))))))))))) -> 0 | N65: =IF(B65="Texion Textil",0,IF(B65="Três Elos",0,IF(C65="Malha",0,IF(C65="Dublagem Cretone",'Custos insumos'!$D$23,IF(C65="Dublagem Spun",'Custos insumos'!$D$19,IF(C65="Espelhamento",0,IF(C65="Espelhamento 2x",0,IF(C65="Esp. + Pel.",0,IF(C65="Pel. + Spun",'Custos insumos'!$D$19,IF(C65="Dublagem Cretone PES",'Custos insumos'!$F$25,IF(C65="Dublagem Barreira",'Custos insumos'!$D$22,))))))))))) -> 0
B66: Irmãos Jurgensen | C66: Peletização | E66: 1 | F66: 0.34 | G66: 0.6 | H66: metro linear | I66: =G66/E66 -> 0.6 | J66: 45301 | L66: =G66-M66-N66 -> 0.6 | M66: =IF(B66="Texion Textil",0,IF(C66="Malha",'Custos insumos'!$B$24,IF(C66="Dublagem Cretone",'Custos insumos'!$D$7,IF(C66="Dublagem Spun",'Custos insumos'!$D$4,IF(C66="Espelhamento",'Custos insumos'!$B$11,IF(C66="Espelhamento 2x",2*'Custos insumos'!$B$11,IF(C66="Esp. + Pel.",'Custos insumos'!$B$11,IF(C66="Pel. + Spun",'Custos insumos'!$D$4,IF(C66="Dublagem Cretone PES",'Custos insumos'!$D$7,IF(C66="Dublagem Barreira",'Custos insumos'!$D$11,IF(C66="Dublagem - MO + Filme",'Custos insumos'!$D$4,IF(C66="Dublagem Cretone HM50",'Custos insumos'!$D$26,IF(C66="Dublagem Cretone HM70",'Custos insumos'!$F$10,))))))))))))) -> 0 | N66: =IF(B66="Texion Textil",0,IF(B66="Três Elos",0,IF(C66="Malha",0,IF(C66="Dublagem Cretone",'Custos insumos'!$D$23,IF(C66="Dublagem Spun",'Custos insumos'!$D$19,IF(C66="Espelhamento",0,IF(C66="Espelhamento 2x",0,IF(C66="Esp. + Pel.",0,IF(C66="Pel. + Spun",'Custos insumos'!$D$19,IF(C66="Dublagem Cretone PES",'Custos insumos'!$F$25,IF(C66="Dublagem Barreira",'Custos insumos'!$D$22,))))))))))) -> 0
B67: Italytex Textil | C67: Calandra | E67: 1 | F67: 0.34 | G67: 0.65 | H67: metro linear | I67: =G67/E67 -> 0.65 | J67: 45301 | L67: =G67-M67-N67 -> 0.65 | M67: =IF(B67="Texion Textil",0,IF(C67="Malha",'Custos insumos'!$B$24,IF(C67="Dublagem Cretone",'Custos insumos'!$D$7,IF(C67="Dublagem Spun",'Custos insumos'!$D$4,IF(C67="Espelhamento",'Custos insumos'!$B$11,IF(C67="Espelhamento 2x",2*'Custos insumos'!$B$11,IF(C67="Esp. + Pel.",'Custos insumos'!$B$11,IF(C67="Pel. + Spun",'Custos insumos'!$D$4,IF(C67="Dublagem Cretone PES",'Custos insumos'!$D$7,IF(C67="Dublagem Barreira",'Custos insumos'!$D$11,IF(C67="Dublagem - MO + Filme",'Custos insumos'!$D$4,IF(C67="Dublagem Cretone HM50",'Custos insumos'!$D$26,IF(C67="Dublagem Cretone HM70",'Custos insumos'!$F$10,))))))))))))) -> 0 | N67: =IF(B67="Texion Textil",0,IF(B67="Três Elos",0,IF(C67="Malha",0,IF(C67="Dublagem Cretone",'Custos insumos'!$D$23,IF(C67="Dublagem Spun",'Custos insumos'!$D$19,IF(C67="Espelhamento",0,IF(C67="Espelhamento 2x",0,IF(C67="Esp. + Pel.",0,IF(C67="Pel. + Spun",'Custos insumos'!$D$19,IF(C67="Dublagem Cretone PES",'Custos insumos'!$F$25,IF(C67="Dublagem Barreira",'Custos insumos'!$D$22,))))))))))) -> 0
B68: Italytex Textil | C68: Peletização | E68: 1 | G68: 0.6 | H68: metro linear | I68: =G68/E68 -> 0.6 | M68: =IF(B68="Texion Textil",0,IF(C68="Malha",'Custos insumos'!$B$24,IF(C68="Dublagem Cretone",'Custos insumos'!$D$7,IF(C68="Dublagem Spun",'Custos insumos'!$D$4,IF(C68="Espelhamento",'Custos insumos'!$B$11,IF(C68="Espelhamento 2x",2*'Custos insumos'!$B$11,IF(C68="Esp. + Pel.",'Custos insumos'!$B$11,IF(C68="Pel. + Spun",'Custos insumos'!$D$4,IF(C68="Dublagem Cretone PES",'Custos insumos'!$D$7,IF(C68="Dublagem Barreira",'Custos insumos'!$D$11,IF(C68="Dublagem - MO + Filme",'Custos insumos'!$D$4,IF(C68="Dublagem Cretone HM50",'Custos insumos'!$D$26,IF(C68="Dublagem Cretone HM70",'Custos insumos'!$F$10,))))))))))))) -> 0
B69: J. Besan Comercial | C69: Felpagem | E69: 1 | F69: 0.34 | G69: 0.4 | H69: metro linear | I69: =G69/E69 -> 0.4 | J69: 45301 | L69: =G69-M69-N69 -> 0.4 | M69: =IF(B69="Texion Textil",0,IF(C69="Malha",'Custos insumos'!$B$24,IF(C69="Dublagem Cretone",'Custos insumos'!$D$7,IF(C69="Dublagem Spun",'Custos insumos'!$D$4,IF(C69="Espelhamento",'Custos insumos'!$B$11,IF(C69="Espelhamento 2x",2*'Custos insumos'!$B$11,IF(C69="Esp. + Pel.",'Custos insumos'!$B$11,IF(C69="Pel. + Spun",'Custos insumos'!$D$4,IF(C69="Dublagem Cretone PES",'Custos insumos'!$D$7,IF(C69="Dublagem Barreira",'Custos insumos'!$D$11,IF(C69="Dublagem - MO + Filme",'Custos insumos'!$D$4,IF(C69="Dublagem Cretone HM50",'Custos insumos'!$D$26,IF(C69="Dublagem Cretone HM70",'Custos insumos'!$F$10,))))))))))))) -> 0 | N69: =IF(B69="Texion Textil",0,IF(B69="Três Elos",0,IF(C69="Malha",0,IF(C69="Dublagem Cretone",'Custos insumos'!$D$23,IF(C69="Dublagem Spun",'Custos insumos'!$D$16,IF(C69="Espelhamento",0,IF(C69="Espelhamento 2x",0,IF(C69="Esp. + Pel.",0,IF(C69="Pel. + Spun",'Custos insumos'!$D$16,IF(C69="Dublagem Cretone PES",'Custos insumos'!$F$25,IF(C69="Dublagem Barreira",'Custos insumos'!$D$22,))))))))))) -> 0
B70: J. Besan Comercial | C70: Dublagem Spun | E70: 1 | G70: 6.1 | H70: metro linear | I70: =G70/E70 -> 6.1 | J70: 45301 | K70: Insumos fornecidos por Tapajos | L70: =G70-M70-N70 -> 4.25908 | M70: =IF(B70="Texion Textil",0,IF(C70="Malha",'Custos insumos'!$B$24,IF(C70="Dublagem Cretone",'Custos insumos'!$D$7,IF(C70="Dublagem Spun",'Custos insumos'!$D$4,IF(C70="Espelhamento",'Custos insumos'!$B$11,IF(C70="Espelhamento 2x",2*'Custos insumos'!$B$11,IF(C70="Esp. + Pel.",'Custos insumos'!$B$11,IF(C70="Pel. + Spun",'Custos insumos'!$D$4,IF(C70="Dublagem Cretone PES",'Custos insumos'!$D$7,IF(C70="Dublagem Barreira",'Custos insumos'!$D$11,IF(C70="Dublagem - MO + Filme",'Custos insumos'!$D$4,IF(C70="Dublagem Cretone HM50",'Custos insumos'!$D$26,IF(C70="Dublagem Cretone HM70",'Custos insumos'!$F$10,))))))))))))) -> 1.1232 | N70: =IF(B70="Texion Textil",0,IF(B70="Três Elos",0,IF(C70="Malha",0,IF(C70="Dublagem Cretone",'Custos insumos'!$D$23,IF(C70="Dublagem Spun",'Custos insumos'!$D$16,IF(C70="Espelhamento",0,IF(C70="Espelhamento 2x",0,IF(C70="Esp. + Pel.",0,IF(C70="Pel. + Spun",'Custos insumos'!$D$16,IF(C70="Dublagem Cretone PES",'Custos insumos'!$F$25,IF(C70="Dublagem Barreira",'Custos insumos'!$D$22,))))))))))) -> 0.71772
B71: J. Besan Comercial | C71: Calandra | E71: 2 | F71: 0.6 | G71: 0.65 | H71: metro linear | I71: =G71/E71 -> 0.325 | J71: 45301 | L71: =G71-M71-N71 -> 0.65 | M71: =IF(B71="Texion Textil",0,IF(C71="Malha",'Custos insumos'!$B$24,IF(C71="Dublagem Cretone",'Custos insumos'!$D$7,IF(C71="Dublagem Spun",'Custos insumos'!$D$4,IF(C71="Espelhamento",'Custos insumos'!$B$11,IF(C71="Espelhamento 2x",2*'Custos insumos'!$B$11,IF(C71="Esp. + Pel.",'Custos insumos'!$B$11,IF(C71="Pel. + Spun",'Custos insumos'!$D$4,IF(C71="Dublagem Cretone PES",'Custos insumos'!$D$7,IF(C71="Dublagem Barreira",'Custos insumos'!$D$11,IF(C71="Dublagem - MO + Filme",'Custos insumos'!$D$4,IF(C71="Dublagem Cretone HM50",'Custos insumos'!$D$26,IF(C71="Dublagem Cretone HM70",'Custos insumos'!$F$10,))))))))))))) -> 0 | N71: =IF(B71="Texion Textil",0,IF(B71="Três Elos",0,IF(C71="Malha",0,IF(C71="Dublagem Cretone",'Custos insumos'!$D$23,IF(C71="Dublagem Spun",'Custos insumos'!$D$16,IF(C71="Espelhamento",0,IF(C71="Espelhamento 2x",0,IF(C71="Esp. + Pel.",0,IF(C71="Pel. + Spun",'Custos insumos'!$D$16,IF(C71="Dublagem Cretone PES",'Custos insumos'!$F$25,IF(C71="Dublagem Barreira",'Custos insumos'!$D$22,))))))))))) -> 0
B72: JRJ | C72: Dublagem Cretone - Cola 50 | E72: 1 | F72: 6.1 | G72: 7.1 | H72: metro linear | I72: =G72/E72 -> 7.1 | J72: 45301 | L72: =G72-M72-N72 -> 2.54 | M72: ='Custos insumos'!F9 -> 2.232 | N72: ='Custos insumos'!D23 -> 2.328
A73: ok | B73: JRJ | C73: Dublagem Cretone | E73: 1 | F73: 6.1 | G73: 6.1 | H73: metro linear | I73: =G73/E73 -> 6.1 | J73: 45301 | L73: =G73-M73-N73 -> 1.81 | M73: =IF(B73="Texion Textil",0,IF(C73="Malha",'Custos insumos'!$B$24,IF(C73="Dublagem Cretone",'Custos insumos'!$D$7,IF(C73="Dublagem Spun",'Custos insumos'!$D$4,IF(C73="Espelhamento",'Custos insumos'!$B$11,IF(C73="Espelhamento 2x",2*'Custos insumos'!$B$11,IF(C73="Esp. + Pel.",'Custos insumos'!$B$11,IF(C73="Pel. + Spun",'Custos insumos'!$D$4,IF(C73="Dublagem Cretone PES",'Custos insumos'!$D$7,IF(C73="Dublagem Barreira",'Custos insumos'!$D$11,IF(C73="Dublagem - MO + Filme",'Custos insumos'!$D$4,IF(C73="Dublagem Cretone HM50",'Custos insumos'!$D$26,IF(C73="Dublagem Cretone HM70",'Custos insumos'!$F$10,))))))))))))) -> 1.962 | N73: =IF(B73="Texion Textil",0,IF(B73="Três Elos",0,IF(C73="Malha",0,IF(C73="Dublagem Cretone",'Custos insumos'!$D$23,IF(C73="Dublagem Spun",'Custos insumos'!$D$16,IF(C73="Espelhamento",0,IF(C73="Espelhamento 2x",0,IF(C73="Esp. + Pel.",0,IF(C73="Pel. + Spun",'Custos insumos'!$D$16,IF(C73="Dublagem Cretone PES",'Custos insumos'!$F$25,IF(C73="Dublagem Barreira",'Custos insumos'!$D$22,))))))))))) -> 2.328
A74: ok | B74: JRJ | C74: Dublagem Spun | E74: 1 | F74: 6.1 | G74: 6.1 | H74: metro linear | I74: =G74/E74 -> 6.1 | J74: 45301 | L74: =G74-M74-N74 -> 4.25908 | M74: =IF(B74="Texion Textil",0,IF(C74="Malha",'Custos insumos'!$B$24,IF(C74="Dublagem Cretone",'Custos insumos'!$D$7,IF(C74="Dublagem Spun",'Custos insumos'!$D$4,IF(C74="Espelhamento",'Custos insumos'!$B$11,IF(C74="Espelhamento 2x",2*'Custos insumos'!$B$11,IF(C74="Esp. + Pel.",'Custos insumos'!$B$11,IF(C74="Pel. + Spun",'Custos insumos'!$D$4,IF(C74="Dublagem Cretone PES",'Custos insumos'!$D$7,IF(C74="Dublagem Barreira",'Custos insumos'!$D$11,IF(C74="Dublagem - MO + Filme",'Custos insumos'!$D$4,IF(C74="Dublagem Cretone HM50",'Custos insumos'!$D$26,IF(C74="Dublagem Cretone HM70",'Custos insumos'!$F$10,))))))))))))) -> 1.1232 | N74: =IF(B74="Texion Textil",0,IF(B74="Três Elos",0,IF(C74="Malha",0,IF(C74="Dublagem Cretone",'Custos insumos'!$D$23,IF(C74="Dublagem Spun",'Custos insumos'!$D$16,IF(C74="Espelhamento",0,IF(C74="Espelhamento 2x",0,IF(C74="Esp. + Pel.",0,IF(C74="Pel. + Spun",'Custos insumos'!$D$16,IF(C74="Dublagem Cretone PES",'Custos insumos'!$F$25,IF(C74="Dublagem Barreira",'Custos insumos'!$D$22,))))))))))) -> 0.71772
A75: ok | B75: JRJ | C75: Peletização | E75: 1 | F75: 0.66 | G75: 0.66 | H75: metro linear | I75: =G75/E75 -> 0.66 | J75: 45301 | L75: =G75-M75-N75 -> 0.66 | M75: =IF(B75="Texion Textil",0,IF(C75="Malha",'Custos insumos'!$B$24,IF(C75="Dublagem Cretone",'Custos insumos'!$D$7,IF(C75="Dublagem Spun",'Custos insumos'!$D$4,IF(C75="Espelhamento",'Custos insumos'!$B$11,IF(C75="Espelhamento 2x",2*'Custos insumos'!$B$11,IF(C75="Esp. + Pel.",'Custos insumos'!$B$11,IF(C75="Pel. + Spun",'Custos insumos'!$D$4,IF(C75="Dublagem Cretone PES",'Custos insumos'!$D$7,IF(C75="Dublagem Barreira",'Custos insumos'!$D$11,IF(C75="Dublagem - MO + Filme",'Custos insumos'!$D$4,IF(C75="Dublagem Cretone HM50",'Custos insumos'!$D$26,IF(C75="Dublagem Cretone HM70",'Custos insumos'!$F$10,))))))))))))) -> 0 | N75: =IF(B75="Texion Textil",0,IF(B75="Três Elos",0,IF(C75="Malha",0,IF(C75="Dublagem Cretone",'Custos insumos'!$D$23,IF(C75="Dublagem Spun",'Custos insumos'!$D$16,IF(C75="Espelhamento",0,IF(C75="Espelhamento 2x",0,IF(C75="Esp. + Pel.",0,IF(C75="Pel. + Spun",'Custos insumos'!$D$16,IF(C75="Dublagem Cretone PES",'Custos insumos'!$F$25,IF(C75="Dublagem Barreira",'Custos insumos'!$D$22,))))))))))) -> 0
A76: ok | B76: JRJ | C76: Pel. + Cal. | E76: 1 | F76: 1.2 | G76: 1.2 | H76: metro linear | I76: =G76/E76 -> 1.2 | J76: 45301 | L76: =G76-M76-N76 -> 1.2 | M76: =IF(B76="Texion Textil",0,IF(C76="Malha",'Custos insumos'!$B$24,IF(C76="Dublagem Cretone",'Custos insumos'!$D$7,IF(C76="Dublagem Spun",'Custos insumos'!$D$4,IF(C76="Espelhamento",'Custos insumos'!$B$11,IF(C76="Espelhamento 2x",2*'Custos insumos'!$B$11,IF(C76="Esp. + Pel.",'Custos insumos'!$B$11,IF(C76="Pel. + Spun",'Custos insumos'!$D$4,IF(C76="Dublagem Cretone PES",'Custos insumos'!$D$7,IF(C76="Dublagem Barreira",'Custos insumos'!$D$11,IF(C76="Dublagem - MO + Filme",'Custos insumos'!$D$4,IF(C76="Dublagem Cretone HM50",'Custos insumos'!$D$26,IF(C76="Dublagem Cretone HM70",'Custos insumos'!$F$10,))))))))))))) -> 0 | N76: =IF(B76="Texion Textil",0,IF(B76="Três Elos",0,IF(C76="Malha",0,IF(C76="Dublagem Cretone",'Custos insumos'!$D$23,IF(C76="Dublagem Spun",'Custos insumos'!$D$16,IF(C76="Espelhamento",0,IF(C76="Espelhamento 2x",0,IF(C76="Esp. + Pel.",0,IF(C76="Pel. + Spun",'Custos insumos'!$D$16,IF(C76="Dublagem Cretone PES",'Custos insumos'!$F$25,IF(C76="Dublagem Barreira",'Custos insumos'!$D$22,))))))))))) -> 0
A77: ok | B77: Jumirim Malhas | C77: Peletização | E77: 1 | F77: 1.34 | G77: 1.34 | H77: metro linear | I77: =G77/E77 -> 1.34 | J77: 45301 | L77: =G77-M77-N77 -> 1.34 | M77: =IF(B77="Texion Textil",0,IF(C77="Malha",'Custos insumos'!$B$24,IF(C77="Dublagem Cretone",'Custos insumos'!$D$7,IF(C77="Dublagem Spun",'Custos insumos'!$D$4,IF(C77="Espelhamento",'Custos insumos'!$B$11,IF(C77="Espelhamento 2x",2*'Custos insumos'!$B$11,IF(C77="Esp. + Pel.",'Custos insumos'!$B$11,IF(C77="Pel. + Spun",'Custos insumos'!$D$4,IF(C77="Dublagem Cretone PES",'Custos insumos'!$D$7,IF(C77="Dublagem Barreira",'Custos insumos'!$D$11,IF(C77="Dublagem - MO + Filme",'Custos insumos'!$D$4,IF(C77="Dublagem Cretone HM50",'Custos insumos'!$D$26,IF(C77="Dublagem Cretone HM70",'Custos insumos'!$F$10,))))))))))))) -> 0 | N77: =IF(B77="Texion Textil",0,IF(B77="Três Elos",0,IF(C77="Malha",0,IF(C77="Dublagem Cretone",'Custos insumos'!$D$23,IF(C77="Dublagem Spun",'Custos insumos'!$D$16,IF(C77="Espelhamento",0,IF(C77="Espelhamento 2x",0,IF(C77="Esp. + Pel.",0,IF(C77="Pel. + Spun",'Custos insumos'!$D$16,IF(C77="Dublagem Cretone PES",'Custos insumos'!$F$25,IF(C77="Dublagem Barreira",'Custos insumos'!$D$22,))))))))))) -> 0
A78: ok | B78: LAJU | C78: Peletização | E78: 1 | G78: 0.6 | H78: metro linear | I78: =G78/E78 -> 0.6 | L78: =G78-M78-N78 -> 0.6 | M78: =IF(B78="Texion Textil",0,IF(C78="Malha",'Custos insumos'!$B$24,IF(C78="Dublagem Cretone",'Custos insumos'!$D$7,IF(C78="Dublagem Spun",'Custos insumos'!$D$4,IF(C78="Espelhamento",'Custos insumos'!$B$11,IF(C78="Espelhamento 2x",2*'Custos insumos'!$B$11,IF(C78="Esp. + Pel.",'Custos insumos'!$B$11,IF(C78="Pel. + Spun",'Custos insumos'!$D$4,IF(C78="Dublagem Cretone PES",'Custos insumos'!$D$7,IF(C78="Dublagem Barreira",'Custos insumos'!$D$11,IF(C78="Dublagem - MO + Filme",'Custos insumos'!$D$4,IF(C78="Dublagem Cretone HM50",'Custos insumos'!$D$26,IF(C78="Dublagem Cretone HM70",'Custos insumos'!$F$10,))))))))))))) -> 0 | N78: =IF(B78="Texion Textil",0,IF(B78="Três Elos",0,IF(C78="Malha",0,IF(C78="Dublagem Cretone",'Custos insumos'!$D$23,IF(C78="Dublagem Spun",'Custos insumos'!$D$16,IF(C78="Espelhamento",0,IF(C78="Espelhamento 2x",0,IF(C78="Esp. + Pel.",0,IF(C78="Pel. + Spun",'Custos insumos'!$D$16,IF(C78="Dublagem Cretone PES",'Custos insumos'!$F$25,IF(C78="Dublagem Barreira",'Custos insumos'!$D$22,))))))))))) -> 0
B79: LAJU | C79: Felpagem | E79: 1 | G79: 0.6 | H79: metro linear | I79: =G79/E79 -> 0.6 | L79: =G79-M79-N79 -> 0.6 | M79: =IF(B79="Texion Textil",0,IF(C79="Malha",'Custos insumos'!$B$24,IF(C79="Dublagem Cretone",'Custos insumos'!$D$7,IF(C79="Dublagem Spun",'Custos insumos'!$D$4,IF(C79="Espelhamento",'Custos insumos'!$B$11,IF(C79="Espelhamento 2x",2*'Custos insumos'!$B$11,IF(C79="Esp. + Pel.",'Custos insumos'!$B$11,IF(C79="Pel. + Spun",'Custos insumos'!$D$4,IF(C79="Dublagem Cretone PES",'Custos insumos'!$D$7,IF(C79="Dublagem Barreira",'Custos insumos'!$D$11,IF(C79="Dublagem - MO + Filme",'Custos insumos'!$D$4,IF(C79="Dublagem Cretone HM50",'Custos insumos'!$D$26,IF(C79="Dublagem Cretone HM70",'Custos insumos'!$F$10,))))))))))))) -> 0 | N79: =IF(B79="Texion Textil",0,IF(B79="Três Elos",0,IF(C79="Malha",0,IF(C79="Dublagem Cretone",'Custos insumos'!$D$23,IF(C79="Dublagem Spun",'Custos insumos'!$D$16,IF(C79="Espelhamento",0,IF(C79="Espelhamento 2x",0,IF(C79="Esp. + Pel.",0,IF(C79="Pel. + Spun",'Custos insumos'!$D$16,IF(C79="Dublagem Cretone PES",'Custos insumos'!$F$25,IF(C79="Dublagem Barreira",'Custos insumos'!$D$22,))))))))))) -> 0
B80: Lamatex | C80: Felpagem | E80: 1 | F80: 1.1 | G80: 1.1 | H80: metro linear | I80: =G80/E80 -> 1.1 | J80: 45301 | L80: =G80-M80-N80 -> 1.1 | M80: =IF(B80="Texion Textil",0,IF(C80="Malha",'Custos insumos'!$B$24,IF(C80="Dublagem Cretone",'Custos insumos'!$D$7,IF(C80="Dublagem Spun",'Custos insumos'!$D$4,IF(C80="Espelhamento",'Custos insumos'!$B$11,IF(C80="Espelhamento 2x",2*'Custos insumos'!$B$11,IF(C80="Esp. + Pel.",'Custos insumos'!$B$11,IF(C80="Pel. + Spun",'Custos insumos'!$D$4,IF(C80="Dublagem Cretone PES",'Custos insumos'!$D$7,IF(C80="Dublagem Barreira",'Custos insumos'!$D$11,IF(C80="Dublagem - MO + Filme",'Custos insumos'!$D$4,IF(C80="Dublagem Cretone HM50",'Custos insumos'!$D$26,IF(C80="Dublagem Cretone HM70",'Custos insumos'!$F$10,))))))))))))) -> 0 | N80: =IF(B80="Texion Textil",0,IF(B80="Três Elos",0,IF(C80="Malha",0,IF(C80="Dublagem Cretone",'Custos insumos'!$D$23,IF(C80="Dublagem Spun",'Custos insumos'!$D$16,IF(C80="Espelhamento",0,IF(C80="Espelhamento 2x",0,IF(C80="Esp. + Pel.",0,IF(C80="Pel. + Spun",'Custos insumos'!$D$16,IF(C80="Dublagem Cretone PES",'Custos insumos'!$F$25,IF(C80="Dublagem Barreira",'Custos insumos'!$D$22,))))))))))) -> 0
A81: ok | B81: Lartex/Sunfabrics | C81: Espelhamento | E81: 1 | F81: 2.15 | G81: 2.35 | H81: metro linear | I81: =G81/E81 -> 2.35 | J81: 45301 | K81: Insumo + MO | L81: =G81-M81-N81 -> 1.2914997 | M81: =IF(B81="Texion Textil",0,IF(C81="Malha",'Custos insumos'!$B$24,IF(C81="Dublagem Cretone",'Custos insumos'!$D$7,IF(C81="Dublagem Spun",'Custos insumos'!$D$4,IF(C81="Espelhamento",'Custos insumos'!$B$11,IF(C81="Espelhamento 2x",2*'Custos insumos'!$B$11,IF(C81="Esp. + Pel.",'Custos insumos'!$B$11,IF(C81="Pel. + Spun",'Custos insumos'!$D$4,IF(C81="Dublagem Cretone PES",'Custos insumos'!$D$7,IF(C81="Dublagem Barreira",'Custos insumos'!$D$11,IF(C81="Dublagem - MO + Filme",'Custos insumos'!$D$4,IF(C81="Dublagem Cretone HM50",'Custos insumos'!$D$26,IF(C81="Dublagem Cretone HM70",'Custos insumos'!$F$10,))))))))))))) -> 1.0585003 | N81: =IF(B81="Texion Textil",0,IF(B81="Três Elos",0,IF(C81="Malha",0,IF(C81="Dublagem Cretone",'Custos insumos'!$D$23,IF(C81="Dublagem Spun",'Custos insumos'!$D$16,IF(C81="Espelhamento",0,IF(C81="Espelhamento 2x",0,IF(C81="Esp. + Pel.",0,IF(C81="Pel. + Spun",'Custos insumos'!$D$16,IF(C81="Dublagem Cretone PES",'Custos insumos'!$F$25,IF(C81="Dublagem Barreira",'Custos insumos'!$D$22,))))))))))) -> 0
B82: Lartex/Sunfabrics | C82: Dublagem Cretone PES | E82: 1 | G82: 5.1 | H82: metro linear | I82: =G82/E82 -> 5.1 | K82: Insumos + MO | L82: =G82-M82-N82 -> 1.988 | M82: =IF(B82="Texion Textil",0,IF(C82="Malha",'Custos insumos'!$B$24,IF(C82="Dublagem Cretone",'Custos insumos'!$D$7,IF(C82="Dublagem Spun",'Custos insumos'!$D$4,IF(C82="Espelhamento",'Custos insumos'!$B$11,IF(C82="Espelhamento 2x",2*'Custos insumos'!$B$11,IF(C82="Esp. + Pel.",'Custos insumos'!$B$11,IF(C82="Pel. + Spun",'Custos insumos'!$D$4,IF(C82="Dublagem Cretone PES",'Custos insumos'!$D$7,IF(C82="Dublagem Barreira",'Custos insumos'!$D$11,IF(C82="Dublagem - MO + Filme",'Custos insumos'!$D$4,IF(C82="Dublagem Cretone HM50",'Custos insumos'!$D$26,IF(C82="Dublagem Cretone HM70",'Custos insumos'!$F$10,))))))))))))) -> 1.962 | N82: =IF(B82="Texion Textil",0,IF(B82="Três Elos",0,IF(C82="Malha",0,IF(C82="Dublagem Cretone",'Custos insumos'!$D$23,IF(C82="Dublagem Spun",'Custos insumos'!$D$16,IF(C82="Espelhamento",0,IF(C82="Espelhamento 2x",0,IF(C82="Esp. + Pel.",0,IF(C82="Pel. + Spun",'Custos insumos'!$D$16,IF(C82="Dublagem Cretone PES",'Custos insumos'!$D$25,IF(C82="Dublagem Barreira",'Custos insumos'!$D$22,))))))))))) -> 1.15
B83: Lartex/Sunfabrics | C83: Dublagem Spun | E83: 1 | F83: 4.5 | G83: 4.5 | H83: metro linear | I83: =G83/E83 -> 4.5 | J83: 45301 | K83: Insumo + MO | L83: =G83-M83-N83 -> 2.65908 | M83: =IF(B83="Texion Textil",0,IF(C83="Malha",'Custos insumos'!$B$24,IF(C83="Dublagem Cretone",'Custos insumos'!$D$7,IF(C83="Dublagem Spun",'Custos insumos'!$D$4,IF(C83="Espelhamento",'Custos insumos'!$B$11,IF(C83="Espelhamento 2x",2*'Custos insumos'!$B$11,IF(C83="Esp. + Pel.",'Custos insumos'!$B$11,IF(C83="Pel. + Spun",'Custos insumos'!$D$4,IF(C83="Dublagem Cretone PES",'Custos insumos'!$D$7,IF(C83="Dublagem Barreira",'Custos insumos'!$D$11,IF(C83="Dublagem - MO + Filme",'Custos insumos'!$D$4,IF(C83="Dublagem Cretone HM50",'Custos insumos'!$D$26,IF(C83="Dublagem Cretone HM70",'Custos insumos'!$F$10,))))))))))))) -> 1.1232 | N83: =IF(B83="Texion Textil",0,IF(B83="Três Elos",0,IF(C83="Malha",0,IF(C83="Dublagem Cretone",'Custos insumos'!$D$23,IF(C83="Dublagem Spun",'Custos insumos'!$D$16,IF(C83="Espelhamento",0,IF(C83="Espelhamento 2x",0,IF(C83="Esp. + Pel.",0,IF(C83="Pel. + Spun",'Custos insumos'!$D$16,IF(C83="Dublagem Cretone PES",'Custos insumos'!$F$25,IF(C83="Dublagem Barreira",'Custos insumos'!$D$22,))))))))))) -> 0.71772
B84: Lartex/Sunfabrics | C84: Calandra | E84: 1 | F84: 0.65 | G84: 0.65 | H84: metro linear | I84: =G84/E84 -> 0.65 | L84: =G84-M84-N84 -> 0.65 | M84: =IF(B84="Texion Textil",0,IF(C84="Malha",'Custos insumos'!$B$24,IF(C84="Dublagem Cretone",'Custos insumos'!$D$7,IF(C84="Dublagem Spun",'Custos insumos'!$D$4,IF(C84="Espelhamento",'Custos insumos'!$B$11,IF(C84="Espelhamento 2x",2*'Custos insumos'!$B$11,IF(C84="Esp. + Pel.",'Custos insumos'!$B$11,IF(C84="Pel. + Spun",'Custos insumos'!$D$4,IF(C84="Dublagem Cretone PES",'Custos insumos'!$D$7,IF(C84="Dublagem Barreira",'Custos insumos'!$D$11,IF(C84="Dublagem - MO + Filme",'Custos insumos'!$D$4,IF(C84="Dublagem Cretone HM50",'Custos insumos'!$D$26,IF(C84="Dublagem Cretone HM70",'Custos insumos'!$F$10,))))))))))))) -> 0 | N84: =IF(B84="Texion Textil",0,IF(B84="Três Elos",0,IF(C84="Malha",0,IF(C84="Dublagem Cretone",'Custos insumos'!$D$23,IF(C84="Dublagem Spun",'Custos insumos'!$D$16,IF(C84="Espelhamento",0,IF(C84="Espelhamento 2x",0,IF(C84="Esp. + Pel.",0,IF(C84="Pel. + Spun",'Custos insumos'!$D$16,IF(C84="Dublagem Cretone PES",'Custos insumos'!$F$25,IF(C84="Dublagem Barreira",'Custos insumos'!$D$22,))))))))))) -> 0
B85: Limpanos | C85: Felpagem | E85: 3 | F85: 1.04 | G85: 1.14 | H85: metro linear | I85: =G85/E85 -> 0.38 | J85: 45301 | L85: =G85-M85-N85 -> 1.14 | M85: =IF(B85="Texion Textil",0,IF(C85="Malha",'Custos insumos'!$B$24,IF(C85="Dublagem Cretone",'Custos insumos'!$D$7,IF(C85="Dublagem Spun",'Custos insumos'!$D$4,IF(C85="Espelhamento",'Custos insumos'!$B$11,IF(C85="Espelhamento 2x",2*'Custos insumos'!$B$11,IF(C85="Esp. + Pel.",'Custos insumos'!$B$11,IF(C85="Pel. + Spun",'Custos insumos'!$D$4,IF(C85="Dublagem Cretone PES",'Custos insumos'!$D$7,IF(C85="Dublagem Barreira",'Custos insumos'!$D$11,IF(C85="Dublagem - MO + Filme",'Custos insumos'!$D$4,IF(C85="Dublagem Cretone HM50",'Custos insumos'!$D$26,IF(C85="Dublagem Cretone HM70",'Custos insumos'!$F$10,))))))))))))) -> 0 | N85: =IF(B85="Texion Textil",0,IF(B85="Três Elos",0,IF(C85="Malha",0,IF(C85="Dublagem Cretone",'Custos insumos'!$D$23,IF(C85="Dublagem Spun",'Custos insumos'!$D$16,IF(C85="Espelhamento",0,IF(C85="Espelhamento 2x",0,IF(C85="Esp. + Pel.",0,IF(C85="Pel. + Spun",'Custos insumos'!$D$16,IF(C85="Dublagem Cretone PES",'Custos insumos'!$F$25,IF(C85="Dublagem Barreira",'Custos insumos'!$D$22,))))))))))) -> 0
B86: Mesa Belém | C86: Dublagem Cretone | G86: 5.45 | L86: =G86-M86-N86 -> 1.16 | M86: =IF(B86="Texion Textil",0,IF(C86="Malha",'Custos insumos'!$B$24,IF(C86="Dublagem Cretone",'Custos insumos'!$D$7,IF(C86="Dublagem Spun",'Custos insumos'!$D$4,IF(C86="Espelhamento",'Custos insumos'!$B$11,IF(C86="Espelhamento 2x",2*'Custos insumos'!$B$11,IF(C86="Esp. + Pel.",'Custos insumos'!$B$11,IF(C86="Pel. + Spun",'Custos insumos'!$D$4,IF(C86="Dublagem Cretone PES",'Custos insumos'!$D$7,IF(C86="Dublagem Barreira",'Custos insumos'!$D$11,IF(C86="Dublagem - MO + Filme",'Custos insumos'!$D$4,IF(C86="Dublagem Cretone HM50",'Custos insumos'!$D$26,IF(C86="Dublagem Cretone HM70",'Custos insumos'!$F$10,))))))))))))) -> 1.962 | N86: =IF(B86="Texion Textil",0,IF(B86="Três Elos",0,IF(C86="Malha",0,IF(C86="Dublagem Cretone",'Custos insumos'!$D$23,IF(C86="Dublagem Spun",'Custos insumos'!$D$19,IF(C86="Espelhamento",0,IF(C86="Espelhamento 2x",0,IF(C86="Esp. + Pel.",0,IF(C86="Pel. + Spun",'Custos insumos'!$D$19,IF(C86="Dublagem Cretone PES",'Custos insumos'!$F$25,IF(C86="Dublagem Barreira",'Custos insumos'!$D$22,))))))))))) -> 2.328
B87: Microtex | C87: Felpagem | G87: 0.75 | H87: metro linear | L87: =G87-M87-N87 -> 0.75 | M87: =IF(B87="Texion Textil",0,IF(C87="Malha",'Custos insumos'!$B$24,IF(C87="Dublagem Cretone",'Custos insumos'!$D$7,IF(C87="Dublagem Spun",'Custos insumos'!$D$4,IF(C87="Espelhamento",'Custos insumos'!$B$11,IF(C87="Espelhamento 2x",2*'Custos insumos'!$B$11,IF(C87="Esp. + Pel.",'Custos insumos'!$B$11,IF(C87="Pel. + Spun",'Custos insumos'!$D$4,IF(C87="Dublagem Cretone PES",'Custos insumos'!$D$7,IF(C87="Dublagem Barreira",'Custos insumos'!$D$11,IF(C87="Dublagem - MO + Filme",'Custos insumos'!$D$4,IF(C87="Dublagem Cretone HM50",'Custos insumos'!$D$26,IF(C87="Dublagem Cretone HM70",'Custos insumos'!$F$10,))))))))))))) -> 0 | N87: =IF(B87="Texion Textil",0,IF(B87="Três Elos",0,IF(C87="Malha",0,IF(C87="Dublagem Cretone",'Custos insumos'!$D$23,IF(C87="Dublagem Spun",'Custos insumos'!$D$16,IF(C87="Espelhamento",0,IF(C87="Espelhamento 2x",0,IF(C87="Esp. + Pel.",0,IF(C87="Pel. + Spun",'Custos insumos'!$D$16,IF(C87="Dublagem Cretone PES",'Custos insumos'!$F$25,IF(C87="Dublagem Barreira",'Custos insumos'!$D$22,))))))))))) -> 0
A88: ok | B88: MN | C88: Peletização | E88: 1 | G88: 0.6 | H88: metro linear | I88: =G88/E88 -> 0.6 | J88: 45301 | K88: Mão de obra e insumos | L88: =G88-M88-N88 -> 0.6 | M88: =IF(B88="Texion Textil",0,IF(C88="Malha",'Custos insumos'!$B$24,IF(C88="Dublagem Cretone",'Custos insumos'!$D$7,IF(C88="Dublagem Spun",'Custos insumos'!$D$4,IF(C88="Espelhamento",'Custos insumos'!$B$11,IF(C88="Espelhamento 2x",2*'Custos insumos'!$B$11,IF(C88="Esp. + Pel.",'Custos insumos'!$B$11,IF(C88="Pel. + Spun",'Custos insumos'!$D$4,IF(C88="Dublagem Cretone PES",'Custos insumos'!$D$7,IF(C88="Dublagem Barreira",'Custos insumos'!$D$11,IF(C88="Dublagem - MO + Filme",'Custos insumos'!$D$4,IF(C88="Dublagem Cretone HM50",'Custos insumos'!$D$26,IF(C88="Dublagem Cretone HM70",'Custos insumos'!$F$10,))))))))))))) -> 0 | N88: =IF(B88="Texion Textil",0,IF(B88="Três Elos",0,IF(C88="Malha",0,IF(C88="Dublagem Cretone",'Custos insumos'!$D$23,IF(C88="Dublagem Spun",'Custos insumos'!$D$16,IF(C88="Espelhamento",0,IF(C88="Espelhamento 2x",0,IF(C88="Esp. + Pel.",0,IF(C88="Pel. + Spun",'Custos insumos'!$D$16,IF(C88="Dublagem Cretone PES",'Custos insumos'!$F$25,IF(C88="Dublagem Barreira",'Custos insumos'!$D$22,))))))))))) -> 0
A89: ok | B89: NM | C89: Espelhamento | E89: 1 | F89: 2.29 | G89: 2.35 | H89: metro linear | I89: =G89/E89 -> 2.35 | J89: 45301 | K89: Mão de obra e insumos | L89: =G89-M89-N89 -> 1.2914997 | M89: =IF(B89="Texion Textil",0,IF(C89="Malha",'Custos insumos'!$B$24,IF(C89="Dublagem Cretone",'Custos insumos'!$D$7,IF(C89="Dublagem Spun",'Custos insumos'!$D$4,IF(C89="Espelhamento",'Custos insumos'!$B$11,IF(C89="Espelhamento 2x",2*'Custos insumos'!$B$11,IF(C89="Esp. + Pel.",'Custos insumos'!$B$11,IF(C89="Pel. + Spun",'Custos insumos'!$D$4,IF(C89="Dublagem Cretone PES",'Custos insumos'!$D$7,IF(C89="Dublagem Barreira",'Custos insumos'!$D$11,IF(C89="Dublagem - MO + Filme",'Custos insumos'!$D$4,IF(C89="Dublagem Cretone HM50",'Custos insumos'!$D$26,IF(C89="Dublagem Cretone HM70",'Custos insumos'!$F$10,))))))))))))) -> 1.0585003 | N89: =IF(B89="Texion Textil",0,IF(B89="Três Elos",0,IF(C89="Malha",0,IF(C89="Dublagem Cretone",'Custos insumos'!$D$23,IF(C89="Dublagem Spun",'Custos insumos'!$D$16,IF(C89="Espelhamento",0,IF(C89="Espelhamento 2x",0,IF(C89="Esp. + Pel.",0,IF(C89="Pel. + Spun",'Custos insumos'!$D$16,IF(C89="Dublagem Cretone PES",'Custos insumos'!$F$25,IF(C89="Dublagem Barreira",'Custos insumos'!$D$22,))))))))))) -> 0
A90: ok | B90: NM | C90: Dublagem Spun | E90: 1 | F90: 4.47 | G90: 4.47 | H90: metro linear | I90: =G90/E90 -> 4.47 | J90: 45301 | K90: Mão de obra e insumos | L90: =G90-M90-N90 -> 2.62908 | M90: =IF(B90="Texion Textil",0,IF(C90="Malha",'Custos insumos'!$B$24,IF(C90="Dublagem Cretone",'Custos insumos'!$D$7,IF(C90="Dublagem Spun",'Custos insumos'!$D$4,IF(C90="Espelhamento",'Custos insumos'!$B$11,IF(C90="Espelhamento 2x",2*'Custos insumos'!$B$11,IF(C90="Esp. + Pel.",'Custos insumos'!$B$11,IF(C90="Pel. + Spun",'Custos insumos'!$D$4,IF(C90="Dublagem Cretone PES",'Custos insumos'!$D$7,IF(C90="Dublagem Barreira",'Custos insumos'!$D$11,IF(C90="Dublagem - MO + Filme",'Custos insumos'!$D$4,IF(C90="Dublagem Cretone HM50",'Custos insumos'!$D$26,IF(C90="Dublagem Cretone HM70",'Custos insumos'!$F$10,))))))))))))) -> 1.1232 | N90: =IF(B90="Texion Textil",0,IF(B90="Três Elos",0,IF(C90="Malha",0,IF(C90="Dublagem Cretone",'Custos insumos'!$D$23,IF(C90="Dublagem Spun",'Custos insumos'!$D$16,IF(C90="Espelhamento",0,IF(C90="Espelhamento 2x",0,IF(C90="Esp. + Pel.",0,IF(C90="Pel. + Spun",'Custos insumos'!$D$16,IF(C90="Dublagem Cretone PES",'Custos insumos'!$F$25,IF(C90="Dublagem Barreira",'Custos insumos'!$D$22,))))))))))) -> 0.71772
B91: Nossa Sra. Do Belém | C91: Peletização | E91: 1 | F91: 0.57 | G91: 0.65 | H91: metro linear | I91: =G91/E91 -> 0.65 | J91: 45301 | L91: =G91-M91-N91 -> 0.65 | M91: =IF(B91="Texion Textil",0,IF(C91="Malha",'Custos insumos'!$B$24,IF(C91="Dublagem Cretone",'Custos insumos'!$D$7,IF(C91="Dublagem Spun",'Custos insumos'!$D$4,IF(C91="Espelhamento",'Custos insumos'!$B$11,IF(C91="Espelhamento 2x",2*'Custos insumos'!$B$11,IF(C91="Esp. + Pel.",'Custos insumos'!$B$11,IF(C91="Pel. + Spun",'Custos insumos'!$D$4,IF(C91="Dublagem Cretone PES",'Custos insumos'!$D$7,IF(C91="Dublagem Barreira",'Custos insumos'!$D$11,IF(C91="Dublagem - MO + Filme",'Custos insumos'!$D$4,IF(C91="Dublagem Cretone HM50",'Custos insumos'!$D$26,IF(C91="Dublagem Cretone HM70",'Custos insumos'!$F$10,))))))))))))) -> 0 | N91: =IF(B91="Texion Textil",0,IF(B91="Três Elos",0,IF(C91="Malha",0,IF(C91="Dublagem Cretone",'Custos insumos'!$D$23,IF(C91="Dublagem Spun",'Custos insumos'!$D$16,IF(C91="Espelhamento",0,IF(C91="Espelhamento 2x",0,IF(C91="Esp. + Pel.",0,IF(C91="Pel. + Spun",'Custos insumos'!$D$16,IF(C91="Dublagem Cretone PES",'Custos insumos'!$F$25,IF(C91="Dublagem Barreira",'Custos insumos'!$D$22,))))))))))) -> 0
B92: Nossa Sra. Do Belém | C92: Dublagem | E92: 1 | G92: 5.9 | H92: metro linear | I92: =G92/E92 -> 5.9 | M92: =IF(B92="Texion Textil",0,IF(C92="Malha",'Custos insumos'!$B$24,IF(C92="Dublagem Cretone",'Custos insumos'!$D$7,IF(C92="Dublagem Spun",'Custos insumos'!$D$4,IF(C92="Espelhamento",'Custos insumos'!$B$11,IF(C92="Espelhamento 2x",2*'Custos insumos'!$B$11,IF(C92="Esp. + Pel.",'Custos insumos'!$B$11,IF(C92="Pel. + Spun",'Custos insumos'!$D$4,IF(C92="Dublagem Cretone PES",'Custos insumos'!$D$7,IF(C92="Dublagem Barreira",'Custos insumos'!$D$11,IF(C92="Dublagem - MO + Filme",'Custos insumos'!$D$4,IF(C92="Dublagem Cretone HM50",'Custos insumos'!$D$26,IF(C92="Dublagem Cretone HM70",'Custos insumos'!$F$10,))))))))))))) -> 0
B93: PBS | C93: Dublagem | E93: 1 | F93: 1 | G93: 1 | H93: metro linear | I93: =G93/E93 -> 1 | J93: 45301 | K93: MO | L93: =G93-M93-N93 -> 1 | M93: =IF(B93="Texion Textil",0,IF(C93="Malha",'Custos insumos'!$B$24,IF(C93="Dublagem Cretone",'Custos insumos'!$D$7,IF(C93="Dublagem Spun",'Custos insumos'!$D$4,IF(C93="Espelhamento",'Custos insumos'!$B$11,IF(C93="Espelhamento 2x",2*'Custos insumos'!$B$11,IF(C93="Esp. + Pel.",'Custos insumos'!$B$11,IF(C93="Pel. + Spun",'Custos insumos'!$D$4,IF(C93="Dublagem Cretone PES",'Custos insumos'!$D$7,IF(C93="Dublagem Barreira",'Custos insumos'!$D$11,IF(C93="Dublagem - MO + Filme",'Custos insumos'!$D$4,IF(C93="Dublagem Cretone HM50",'Custos insumos'!$D$26,IF(C93="Dublagem Cretone HM70",'Custos insumos'!$F$10,))))))))))))) -> 0 | N93: =IF(B93="Texion Textil",0,IF(B93="Três Elos",0,IF(C93="Malha",0,IF(C93="Dublagem Cretone",'Custos insumos'!$D$23,IF(C93="Dublagem Spun",'Custos insumos'!$D$16,IF(C93="Espelhamento",0,IF(C93="Espelhamento 2x",0,IF(C93="Esp. + Pel.",0,IF(C93="Pel. + Spun",'Custos insumos'!$D$16,IF(C93="Dublagem Cretone PES",'Custos insumos'!$F$25,IF(C93="Dublagem Barreira",'Custos insumos'!$D$22,))))))))))) -> 0
A94: ok | B94: Porcher do Brasil | C94: Fel. + Pel. | E94: 1 | F94: 1.7 | G94: 1.8 | H94: metro linear | I94: =G94/E94 -> 1.8 | J94: 45301 | L94: =G94-M94-N94 -> 1.8 | M94: =IF(B94="Texion Textil",0,IF(C94="Malha",'Custos insumos'!$B$24,IF(C94="Dublagem Cretone",'Custos insumos'!$D$7,IF(C94="Dublagem Spun",'Custos insumos'!$D$4,IF(C94="Espelhamento",'Custos insumos'!$B$11,IF(C94="Espelhamento 2x",2*'Custos insumos'!$B$11,IF(C94="Esp. + Pel.",'Custos insumos'!$B$11,IF(C94="Pel. + Spun",'Custos insumos'!$D$4,IF(C94="Dublagem Cretone PES",'Custos insumos'!$D$7,IF(C94="Dublagem Barreira",'Custos insumos'!$D$11,IF(C94="Dublagem - MO + Filme",'Custos insumos'!$D$4,IF(C94="Dublagem Cretone HM50",'Custos insumos'!$D$26,IF(C94="Dublagem Cretone HM70",'Custos insumos'!$F$10,))))))))))))) -> 0 | N94: =IF(B94="Texion Textil",0,IF(B94="Três Elos",0,IF(C94="Malha",0,IF(C94="Dublagem Cretone",'Custos insumos'!$D$23,IF(C94="Dublagem Spun",'Custos insumos'!$D$16,IF(C94="Espelhamento",0,IF(C94="Espelhamento 2x",0,IF(C94="Esp. + Pel.",0,IF(C94="Pel. + Spun",'Custos insumos'!$D$16,IF(C94="Dublagem Cretone PES",'Custos insumos'!$F$25,IF(C94="Dublagem Barreira",'Custos insumos'!$D$22,))))))))))) -> 0
B95: Protextil | C95: Espelhamento | E95: 1 | F95: 2.39 | G95: 2.45 | H95: metro linear | I95: =G95/E95 -> 2.45 | J95: 45301 | K95: HM 20 = 1,07 + M.O = 1,10 | L95: =G95-M95-N95 -> 1.3914997 | M95: =IF(B95="Texion Textil",0,IF(C95="Malha",'Custos insumos'!$B$24,IF(C95="Dublagem Cretone",'Custos insumos'!$D$7,IF(C95="Dublagem Spun",'Custos insumos'!$D$4,IF(C95="Espelhamento",'Custos insumos'!$B$11,IF(C95="Espelhamento 2x",2*'Custos insumos'!$B$11,IF(C95="Esp. + Pel.",'Custos insumos'!$B$11,IF(C95="Pel. + Spun",'Custos insumos'!$D$4,IF(C95="Dublagem Cretone PES",'Custos insumos'!$D$7,IF(C95="Dublagem Barreira",'Custos insumos'!$D$11,IF(C95="Dublagem - MO + Filme",'Custos insumos'!$D$4,IF(C95="Dublagem Cretone HM50",'Custos insumos'!$D$26,IF(C95="Dublagem Cretone HM70",'Custos insumos'!$F$10,))))))))))))) -> 1.0585003 | N95: =IF(B95="Texion Textil",0,IF(B95="Três Elos",0,IF(C95="Malha",0,IF(C95="Dublagem Cretone",'Custos insumos'!$D$23,IF(C95="Dublagem Spun",'Custos insumos'!$D$16,IF(C95="Espelhamento",0,IF(C95="Espelhamento 2x",0,IF(C95="Esp. + Pel.",0,IF(C95="Pel. + Spun",'Custos insumos'!$D$16,IF(C95="Dublagem Cretone PES",'Custos insumos'!$F$25,IF(C95="Dublagem Barreira",'Custos insumos'!$D$22,))))))))))) -> 0
B96: Protextil | C96: Espelhamento | E96: 1 | F96: 2.44 | G96: 2.5 | H96: metro linear | I96: =G96/E96 -> 2.5 | J96: 45301 | K96: TPU PX= 1,12 + M.O = 1,10 | L96: =G96-M96-N96 -> 1.4414997 | M96: =IF(B96="Texion Textil",0,IF(C96="Malha",'Custos insumos'!$B$24,IF(C96="Dublagem Cretone",'Custos insumos'!$D$7,IF(C96="Dublagem Spun",'Custos insumos'!$D$4,IF(C96="Espelhamento",'Custos insumos'!$B$11,IF(C96="Espelhamento 2x",2*'Custos insumos'!$B$11,IF(C96="Esp. + Pel.",'Custos insumos'!$B$11,IF(C96="Pel. + Spun",'Custos insumos'!$D$4,IF(C96="Dublagem Cretone PES",'Custos insumos'!$D$7,IF(C96="Dublagem Barreira",'Custos insumos'!$D$11,IF(C96="Dublagem - MO + Filme",'Custos insumos'!$D$4,IF(C96="Dublagem Cretone HM50",'Custos insumos'!$D$26,IF(C96="Dublagem Cretone HM70",'Custos insumos'!$F$10,))))))))))))) -> 1.0585003 | N96: =IF(B96="Texion Textil",0,IF(B96="Três Elos",0,IF(C96="Malha",0,IF(C96="Dublagem Cretone",'Custos insumos'!$D$23,IF(C96="Dublagem Spun",'Custos insumos'!$D$16,IF(C96="Espelhamento",0,IF(C96="Espelhamento 2x",0,IF(C96="Esp. + Pel.",0,IF(C96="Pel. + Spun",'Custos insumos'!$D$16,IF(C96="Dublagem Cretone PES",'Custos insumos'!$F$25,IF(C96="Dublagem Barreira",'Custos insumos'!$D$22,))))))))))) -> 0
B97: Protextil | C97: Dublagem Spun | E97: 1 | F97: 4.53 | G97: 4.6 | H97: metro linear | I97: =G97/E97 -> 4.6 | J97: 45301 | K97: TNT 1,95 / HM 20 1,07 / M.O 1,10 | L97: =G97-M97-N97 -> 2.75908 | M97: =IF(B97="Texion Textil",0,IF(C97="Malha",'Custos insumos'!$B$24,IF(C97="Dublagem Cretone",'Custos insumos'!$D$7,IF(C97="Dublagem Spun",'Custos insumos'!$D$4,IF(C97="Espelhamento",'Custos insumos'!$B$11,IF(C97="Espelhamento 2x",2*'Custos insumos'!$B$11,IF(C97="Esp. + Pel.",'Custos insumos'!$B$11,IF(C97="Pel. + Spun",'Custos insumos'!$D$4,IF(C97="Dublagem Cretone PES",'Custos insumos'!$D$7,IF(C97="Dublagem Barreira",'Custos insumos'!$D$11,IF(C97="Dublagem - MO + Filme",'Custos insumos'!$D$4,IF(C97="Dublagem Cretone HM50",'Custos insumos'!$D$26,IF(C97="Dublagem Cretone HM70",'Custos insumos'!$F$10,))))))))))))) -> 1.1232 | N97: =IF(B97="Texion Textil",0,IF(B97="Três Elos",0,IF(C97="Malha",0,IF(C97="Dublagem Cretone",'Custos insumos'!$D$23,IF(C97="Dublagem Spun",'Custos insumos'!$D$16,IF(C97="Espelhamento",0,IF(C97="Espelhamento 2x",0,IF(C97="Esp. + Pel.",0,IF(C97="Pel. + Spun",'Custos insumos'!$D$16,IF(C97="Dublagem Cretone PES",'Custos insumos'!$F$25,IF(C97="Dublagem Barreira",'Custos insumos'!$D$22,))))))))))) -> 0.71772
A98: ok | B98: RC | C98: Felpagem | E98: 3 | F98: 0.7 | G98: 0.77 | H98: metro linear | I98: =G98/E98 -> 0.25666667 | J98: 45313 | K98: Tres passadas devido desgaste das guarnições | L98: =G98-M98-N98 -> 0.77 | M98: =IF(B98="Texion Textil",0,IF(C98="Malha",'Custos insumos'!$B$24,IF(C98="Dublagem Cretone",'Custos insumos'!$D$7,IF(C98="Dublagem Spun",'Custos insumos'!$D$4,IF(C98="Espelhamento",'Custos insumos'!$B$11,IF(C98="Espelhamento 2x",2*'Custos insumos'!$B$11,IF(C98="Esp. + Pel.",'Custos insumos'!$B$11,IF(C98="Pel. + Spun",'Custos insumos'!$D$4,IF(C98="Dublagem Cretone PES",'Custos insumos'!$D$7,IF(C98="Dublagem Barreira",'Custos insumos'!$D$11,IF(C98="Dublagem - MO + Filme",'Custos insumos'!$D$4,IF(C98="Dublagem Cretone HM50",'Custos insumos'!$D$26,IF(C98="Dublagem Cretone HM70",'Custos insumos'!$F$10,))))))))))))) -> 0 | N98: =IF(B98="Texion Textil",0,IF(B98="Três Elos",0,IF(C98="Malha",0,IF(C98="Dublagem Cretone",'Custos insumos'!$D$23,IF(C98="Dublagem Spun",'Custos insumos'!$D$16,IF(C98="Espelhamento",0,IF(C98="Espelhamento 2x",0,IF(C98="Esp. + Pel.",0,IF(C98="Pel. + Spun",'Custos insumos'!$D$16,IF(C98="Dublagem Cretone PES",'Custos insumos'!$F$25,IF(C98="Dublagem Barreira",'Custos insumos'!$D$22,))))))))))) -> 0
A99: ok | B99: Reia textil | C99: Peletização | E99: 1 | G99: 0.65 | H99: metro linear | I99: =G99/E99 -> 0.65 | L99: =G99-M99-N99 -> 0.65 | M99: =IF(B99="Texion Textil",0,IF(C99="Malha",'Custos insumos'!$B$24,IF(C99="Dublagem Cretone",'Custos insumos'!$D$7,IF(C99="Dublagem Spun",'Custos insumos'!$D$4,IF(C99="Espelhamento",'Custos insumos'!$B$11,IF(C99="Espelhamento 2x",2*'Custos insumos'!$B$11,IF(C99="Esp. + Pel.",'Custos insumos'!$B$11,IF(C99="Pel. + Spun",'Custos insumos'!$D$4,IF(C99="Dublagem Cretone PES",'Custos insumos'!$D$7,IF(C99="Dublagem Barreira",'Custos insumos'!$D$11,IF(C99="Dublagem - MO + Filme",'Custos insumos'!$D$4,IF(C99="Dublagem Cretone HM50",'Custos insumos'!$D$26,IF(C99="Dublagem Cretone HM70",'Custos insumos'!$F$10,))))))))))))) -> 0 | N99: =IF(B99="Texion Textil",0,IF(B99="Três Elos",0,IF(C99="Malha",0,IF(C99="Dublagem Cretone",'Custos insumos'!$D$23,IF(C99="Dublagem Spun",'Custos insumos'!$D$16,IF(C99="Espelhamento",0,IF(C99="Espelhamento 2x",0,IF(C99="Esp. + Pel.",0,IF(C99="Pel. + Spun",'Custos insumos'!$D$16,IF(C99="Dublagem Cretone PES",'Custos insumos'!$F$25,IF(C99="Dublagem Barreira",'Custos insumos'!$D$22,))))))))))) -> 0
A100: ok | B100: Reia textil | C100: Dublagem Spun | E100: 1 | G100: 4.63 | H100: metro linear | I100: =G100/E100 -> 4.63 | L100: =G100-M100-N100 -> 2.78908 | M100: =IF(B100="Texion Textil",0,IF(C100="Malha",'Custos insumos'!$B$24,IF(C100="Dublagem Cretone",'Custos insumos'!$D$7,IF(C100="Dublagem Spun",'Custos insumos'!$D$4,IF(C100="Espelhamento",'Custos insumos'!$B$11,IF(C100="Espelhamento 2x",2*'Custos insumos'!$B$11,IF(C100="Esp. + Pel.",'Custos insumos'!$B$11,IF(C100="Pel. + Spun",'Custos insumos'!$D$4,IF(C100="Dublagem Cretone PES",'Custos insumos'!$D$7,IF(C100="Dublagem Barreira",'Custos insumos'!$D$11,IF(C100="Dublagem - MO + Filme",'Custos insumos'!$D$4,IF(C100="Dublagem Cretone HM50",'Custos insumos'!$D$26,IF(C100="Dublagem Cretone HM70",'Custos insumos'!$F$10,))))))))))))) -> 1.1232 | N100: =IF(B100="Texion Textil",0,IF(B100="Três Elos",0,IF(C100="Malha",0,IF(C100="Dublagem Cretone",'Custos insumos'!$D$23,IF(C100="Dublagem Spun",'Custos insumos'!$D$16,IF(C100="Espelhamento",0,IF(C100="Espelhamento 2x",0,IF(C100="Esp. + Pel.",0,IF(C100="Pel. + Spun",'Custos insumos'!$D$16,IF(C100="Dublagem Cretone PES",'Custos insumos'!$F$25,IF(C100="Dublagem Barreira",'Custos insumos'!$D$22,))))))))))) -> 0.71772
...

Sheet 2025
B1: Cliente | C1: Processo | D1: Artigo | E1: Passadas | F1: Valor anterior | G1: Valor atual | H1: Unid | I1: Preço/metro | J1: Data de atualização | K1: Obs | L1: MO | M1: Colas | N1: Forro | P1: Margem | Q1: Valor de venda por hora | R1: Produtividade m/por hora | S1: Custo de produção por hora | T1: CHH | U1: CMH | V1: CA | X1: CHH | Y1: CMH | Z1: CA
B2: Ademir Maceti | C2: Calandra | E2: 1 | F2: 0.65 | G2: =F2 -> 0.65 | H2: metro linear | J2: 45663 | L2: =G2-M2-N2 -> 0.65 | P2: =(Q2-S2)/Q2 -> 0.24765714 | Q2: =G2*R2 -> 227.5 | R2: {=_xlfn.IFS(C2="Calandra",(350),C2="Peletização",(421),C2="Dublagem Spun",(250),C2="Dublagem Cretone PES",(180),C2="Felpagem",(270/E2),C2="Emborrachamento",(200),C2="Espelhamento",(250),C2="Malha",(1),C2="Dublagem Cretone",(180),C2="Malha",(1),C2="Dublagem Spun - MO",250,C2="Dublagem Cretone - MO",180,C2="Dublagem Cretone PES - MO",180,C2="Espelhamento - MO",250,C2="Emborrachamento",100,C2="Malha",0,C2="Dublagem Barreira",100,C2="Pel. + Cal.",350,C2="Fel. + Pel. + Cal.",270,C2="Pel. + Spun",250,C2="Espelhamento - L: 1,45m",200,C2="Espelhamento - L: 1,65m",200,C2="Estampagem",100,C2="Fel. + Cal.",270,C2="Dublagem Juta",180,C2="Dublagem Cretone - MO (Juta)",180,C2="Dublagem Tapete",150,C2="Esp. + Pel.",200,C2="Espelhamento 2x",100)} -> 350 | S2: =(T2*X2)+(U2*Y2)+(V2*Z2)+((M2+N2)*(R2)) -> 171.158 | T2: {=_xlfn.IFS(C2="Calandra",0.4,C2="Felpagem",0.3,C2="Dublagem Spun",0.8,C2="Dublagem Cretone",0.8,C2="Dublagem Cretone PES",0.8,C2="Espelhamento",0.8,C2="Peletização",0.5,C2="Dublagem Spun - MO",0.8,C2="Dublagem Cretone - MO",0.8,C2="Dublagem Cretone PES - MO",0.8,C2="Espelhamento - MO",0.8,C2="Emborrachamento",1,C2="Malha",0,C2="Dublagem Barreira",1,C2="Pel. + Cal.",0.4,C2="Fel. + Pel. + Cal.",0.5,C2="Pel. + Spun",0.8,C2="Espelhamento - L: 1,45m",0.8,C2="Espelhamento - L: 1,65m",0.8,C2="Estampagem",1,C2="Fel. + Cal.",0.4,C2="Dublagem Juta",0.8,C2="Dublagem Cretone - MO (Juta)",0.8,C2="Dublagem Tapete",0.8,C2="Esp. + Pel.",0.8,C2="Espelhamento 2x",0.8)} -> 0.4 | U2: 1 | V2: 1 | X2: 39.67 | Y2: 38.51 | Z2: 116.78
B3: Ademir Maceti | C3: Emborrachamento | E3: 1 | F3: =4.1+1.5 -> 5.6 | G3: =F3 -> 5.6 | H3: metro linear | J3: 45663 | L3: =G3-M3-N3 -> 2.1 | M3: 3.5 | P3: =(Q3-S3)/Q3 -> 0.20092857 | Q3: =G3*R3 -> 1120 | R3: {=_xlfn.IFS(C3="Calandra",(350),C3="Peletização",(421),C3="Dublagem Spun",(250),C3="Dublagem Cretone PES",(180),C3="Felpagem",(270/E3),C3="Emborrachamento",(200),C3="Espelhamento",(250),C3="Malha",(1),C3="Dublagem Cretone",(180),C3="Malha",(1),C3="Dublagem Spun - MO",250,C3="Dublagem Cretone - MO",180,C3="Dublagem Cretone PES - MO",180,C3="Espelhamento - MO",250,C3="Emborrachamento",100,C3="Malha",0,C3="Dublagem Barreira",100,C3="Pel. + Cal.",350,C3="Fel. + Pel. + Cal.",270,C3="Pel. + Spun",250,C3="Espelhamento - L: 1,45m",200,C3="Espelhamento - L: 1,65m",200,C3="Estampagem",100,C3="Fel. + Cal.",270,C3="Dublagem Juta",180,C3="Dublagem Cretone - MO (Juta)",180,C3="Dublagem Tapete",150,C3="Esp. + Pel.",200,C3="Espelhamento 2x",100)} -> 200 | S3: =(T3*X3)+(U3*Y3)+(V3*Z3)+((M3+N3)*(R3)) -> 894.96 | T3: {=_xlfn.IFS(C3="Calandra",0.4,C3="Felpagem",0.3,C3="Dublagem Spun",0.8,C3="Dublagem Cretone",0.8,C3="Dublagem Cretone PES",0.8,C3="Espelhamento",0.8,C3="Peletização",0.5,C3="Dublagem Spun - MO",0.8,C3="Dublagem Cretone - MO",0.8,C3="Dublagem Cretone PES - MO",0.8,C3="Espelhamento - MO",0.8,C3="Emborrachamento",1,C3="Malha",0,C3="Dublagem Barreira",1,C3="Pel. + Cal.",0.4,C3="Fel. + Pel. + Cal.",0.5,C3="Pel. + Spun",0.8,C3="Espelhamento - L: 1,45m",0.8,C3="Espelhamento - L: 1,65m",0.8,C3="Estampagem",1,C3="Fel. + Cal.",0.4,C3="Dublagem Juta",0.8,C3="Dublagem Cretone - MO (Juta)",0.8,C3="Dublagem Tapete",0.8,C3="Esp. + Pel.",0.8,C3="Espelhamento 2x",0.8)} -> 1 | U3: 1 | V3: 1 | X3: 39.67 | Y3: 38.51 | Z3: 116.78
B4: AG Textil Eireli | C4: Peletização | E4: 1 | F4: 0.65 | G4: =F4 -> 0.65 | H4: metro linear | I4: =G4/E4 -> 0.65 | J4: 45663 | L4: =G4-M4-N4 -> 0.65 | M4: =IF(B4="Texion Textil",0,IF(C4="Malha",'Custos insumos'!$B$24,IF(C4="Dublagem Cretone",'Custos insumos'!$D$7,IF(C4="Dublagem Spun",'Custos insumos'!$D$4,IF(C4="Espelhamento",'Custos insumos'!$B$11,IF(C4="Espelhamento 2x",2*'Custos insumos'!$B$11,IF(C4="Esp. + Pel.",'Custos insumos'!$B$11,IF(C4="Pel. + Spun",'Custos insumos'!$D$4,IF(C4="Dublagem Cretone PES",'Custos insumos'!$D$7,IF(C4="Dublagem Barreira",'Custos insumos'!$D$11,IF(C4="Dublagem - MO + Filme",'Custos insumos'!$D$4,))))))))))) -> 0 | N4: =IF(B4="Texion Textil",0,IF(B4="Três Elos",0,IF(C4="Malha",0,IF(C4="Dublagem Cretone",'Custos insumos'!$D$23,IF(C4="Dublagem Spun",'Custos insumos'!$D$19,IF(C4="Espelhamento",0,IF(C4="Espelhamento 2x",0,IF(C4="Esp. + Pel.",0,IF(C4="Pel. + Spun",'Custos insumos'!$D$19,IF(C4="Dublagem Cretone PES",'Custos insumos'!$F$25,IF(C4="Dublagem Barreira",'Custos insumos'!$D$22,))))))))))) -> 0 | P4: =(Q4-S4)/Q4 -> 0.3600402 | Q4: =G4*R4 -> 273.65 | R4: {=_xlfn.IFS(C4="Calandra",(350),C4="Peletização",(421),C4="Dublagem Spun",(250),C4="Dublagem Cretone PES",(180),C4="Felpagem",(270/E4),C4="Emborrachamento",(200),C4="Espelhamento",(250),C4="Malha",(1),C4="Dublagem Cretone",(180),C4="Malha",(1),C4="Dublagem Spun - MO",250,C4="Dublagem Cretone - MO",180,C4="Dublagem Cretone PES - MO",180,C4="Espelhamento - MO",250,C4="Emborrachamento",100,C4="Malha",0,C4="Dublagem Barreira",100,C4="Pel. + Cal.",350,C4="Fel. + Pel. + Cal.",270,C4="Pel. + Spun",250,C4="Espelhamento - L: 1,45m",200,C4="Espelhamento - L: 1,65m",200,C4="Estampagem",100,C4="Fel. + Cal.",270,C4="Dublagem Juta",180,C4="Dublagem Cretone - MO (Juta)",180,C4="Dublagem Tapete",150,C4="Esp. + Pel.",200,C4="Espelhamento 2x",100)} -> 421 | S4: =(T4*X4)+(U4*Y4)+(V4*Z4)+((M4+N4)*(R4)) -> 175.125 | T4: {=_xlfn.IFS(C4="Calandra",0.4,C4="Felpagem",0.3,C4="Dublagem Spun",0.8,C4="Dublagem Cretone",0.8,C4="Dublagem Cretone PES",0.8,C4="Espelhamento",0.8,C4="Peletização",0.5,C4="Dublagem Spun - MO",0.8,C4="Dublagem Cretone - MO",0.8,C4="Dublagem Cretone PES - MO",0.8,C4="Espelhamento - MO",0.8,C4="Emborrachamento",1,C4="Malha",0,C4="Dublagem Barreira",1,C4="Pel. + Cal.",0.4,C4="Fel. + Pel. + Cal.",0.5,C4="Pel. + Spun",0.8,C4="Espelhamento - L: 1,45m",0.8,C4="Espelhamento - L: 1,65m",0.8,C4="Estampagem",1,C4="Fel. + Cal.",0.4,C4="Dublagem Juta",0.8,C4="Dublagem Cretone - MO (Juta)",0.8,C4="Dublagem Tapete",0.8,C4="Esp. + Pel.",0.8,C4="Espelhamento 2x",0.8)} -> 0.5 | U4: 1 | V4: 1 | X4: 39.67 | Y4: 38.51 | Z4: 116.78
B5: Air Slaid | C5: Malha | E5: 1 | F5: 20.9 | G5: 22.9 | H5: kg | I5: =G5/E5 -> 22.9 | J5: 45663 | L5: =G5-M5-N5 -> 10.4 | M5: =IF(B5="Texion Textil",0,IF(C5="Malha",'Custos insumos'!$B$24,IF(C5="Dublagem Cretone",'Custos insumos'!$D$7,IF(C5="Dublagem Spun",'Custos insumos'!$D$4,IF(C5="Espelhamento",'Custos insumos'!$B$11,IF(C5="Espelhamento 2x",2*'Custos insumos'!$B$11,IF(C5="Esp. + Pel.",'Custos insumos'!$B$11,IF(C5="Pel. + Spun",'Custos insumos'!$D$4,IF(C5="Dublagem Cretone PES",'Custos insumos'!$D$7,IF(C5="Dublagem Barreira",'Custos insumos'!$D$11,IF(C5="Dublagem - MO + Filme",'Custos insumos'!$D$4,))))))))))) -> 12.5 | N5: =IF(B5="Texion Textil",0,IF(B5="Três Elos",0,IF(C5="Malha",0,IF(C5="Dublagem Cretone",'Custos insumos'!$D$23,IF(C5="Dublagem Spun",'Custos insumos'!$D$19,IF(C5="Espelhamento",0,IF(C5="Espelhamento 2x",0,IF(C5="Esp. + Pel.",0,IF(C5="Pel. + Spun",'Custos insumos'!$D$19,IF(C5="Dublagem Cretone PES",'Custos insumos'!$F$25,IF(C5="Dublagem Barreira",'Custos insumos'!$D$22,))))))))))) -> 0 | P5: =(Q5-S5)/Q5 -> -6.3270742 | Q5: =G5*R5 -> 22.9 | R5: {=_xlfn.IFS(C5="Calandra",(350),C5="Peletização",(421),C5="Dublagem Spun",(250),C5="Dublagem Cretone PES",(180),C5="Felpagem",(270/E5),C5="Emborrachamento",(200),C5="Espelhamento",(250),C5="Malha",(1),C5="Dublagem Cretone",(180),C5="Malha",(1),C5="Dublagem Spun - MO",250,C5="Dublagem Cretone - MO",180,C5="Dublagem Cretone PES - MO",180,C5="Espelhamento - MO",250,C5="Emborrachamento",100,C5="Malha",0,C5="Dublagem Barreira",100,C5="Pel. + Cal.",350,C5="Fel. + Pel. + Cal.",270,C5="Pel. + Spun",250,C5="Espelhamento - L: 1,45m",200,C5="Espelhamento - L: 1,65m",200,C5="Estampagem",100,C5="Fel. + Cal.",270,C5="Dublagem Juta",180,C5="Dublagem Cretone - MO (Juta)",180,C5="Dublagem Tapete",150,C5="Esp. + Pel.",200,C5="Espelhamento 2x",100)} -> 1 | S5: =(T5*X5)+(U5*Y5)+(V5*Z5)+((M5+N5)*(R5)) -> 167.79 | T5: {=_xlfn.IFS(C5="Calandra",0.4,C5="Felpagem",0.3,C5="Dublagem Spun",0.8,C5="Dublagem Cretone",0.8,C5="Dublagem Cretone PES",0.8,C5="Espelhamento",0.8,C5="Peletização",0.5,C5="Dublagem Spun - MO",0.8,C5="Dublagem Cretone - MO",0.8,C5="Dublagem Cretone PES - MO",0.8,C5="Espelhamento - MO",0.8,C5="Emborrachamento",1,C5="Malha",0,C5="Dublagem Barreira",1,C5="Pel. + Cal.",0.4,C5="Fel. + Pel. + Cal.",0.5,C5="Pel. + Spun",0.8,C5="Espelhamento - L: 1,45m",0.8,C5="Espelhamento - L: 1,65m",0.8,C5="Estampagem",1,C5="Fel. + Cal.",0.4,C5="Dublagem Juta",0.8,C5="Dublagem Cretone - MO (Juta)",0.8,C5="Dublagem Tapete",0.8,C5="Esp. + Pel.",0.8,C5="Espelhamento 2x",0.8)} -> 0 | U5: 1 | V5: 1 | X5: 39.67 | Y5: 38.51 | Z5: 116.78
B6: Aparatos | C6: Dublagem Cretone PES | E6: 1 | F6: 6.5 | G6: =F6 -> 6.5 | H6: metro linear | I6: =G6/E6 -> 6.5 | J6: 45663 | K6: Insumos fornecidos por Tapajos | L6: =G6-M6-N6 -> 2.21 | M6: =IF(B6="Texion Textil",0,IF(C6="Malha",'Custos insumos'!$B$24,IF(C6="Dublagem Cretone",'Custos insumos'!$D$7,IF(C6="Dublagem Spun",'Custos insumos'!$D$4,IF(C6="Espelhamento",'Custos insumos'!$B$11,IF(C6="Espelhamento 2x",2*'Custos insumos'!$B$11,IF(C6="Esp. + Pel.",'Custos insumos'!$B$11,IF(C6="Pel. + Spun",'Custos insumos'!$D$4,IF(C6="Dublagem Cretone PES",'Custos insumos'!$D$7,IF(C6="Dublagem Barreira",'Custos insumos'!$D$11,IF(C6="Dublagem - MO + Filme",'Custos insumos'!$D$4,IF(C6="Dublagem Cretone HM50",'Custos insumos'!$D$26,IF(C6="Dublagem Cretone HM70",'Custos insumos'!$F$10,))))))))))))) -> 1.962 | N6: =IF(B6="Texion Textil",0,IF(B6="Três Elos",0,IF(C6="Malha",0,IF(C6="Dublagem Cretone",'Custos insumos'!$D$23,IF(C6="Dublagem Spun",'Custos insumos'!$D$19,IF(C6="Espelhamento",0,IF(C6="Espelhamento 2x",0,IF(C6="Esp. + Pel.",0,IF(C6="Pel. + Spun",'Custos insumos'!$D$19,IF(C6="Dublagem Cretone PES",'Custos insumos'!$F$25,IF(C6="Dublagem Barreira",'Custos insumos'!$D$22,))))))))))) -> 2.328 | P6: =(Q6-S6)/Q6 -> 0.18014872 | Q6: =G6*R6 -> 1170 | R6: {=_xlfn.IFS(C6="Calandra",(350),C6="Peletização",(421),C6="Dublagem Spun",(250),C6="Dublagem Cretone PES",(180),C6="Felpagem",(270/E6),C6="Emborrachamento",(200),C6="Espelhamento",(250),C6="Malha",(1),C6="Dublagem Cretone",(180),C6="Malha",(1),C6="Dublagem Spun - MO",250,C6="Dublagem Cretone - MO",180,C6="Dublagem Cretone PES - MO",180,C6="Espelhamento - MO",250,C6="Emborrachamento",100,C6="Malha",0,C6="Dublagem Barreira",100,C6="Pel. + Cal.",350,C6="Fel. + Pel. + Cal.",270,C6="Pel. + Spun",250,C6="Espelhamento - L: 1,45m",200,C6="Espelhamento - L: 1,65m",200,C6="Estampagem",100,C6="Fel. + Cal.",270,C6="Dublagem Juta",180,C6="Dublagem Cretone - MO (Juta)",180,C6="Dublagem Tapete",150,C6="Esp. + Pel.",200,C6="Espelhamento 2x",100)} -> 180 | S6: =(T6*X6)+(U6*Y6)+(V6*Z6)+((M6+N6)*(R6)) -> 959.226 | T6: {=_xlfn.IFS(C6="Calandra",0.4,C6="Felpagem",0.3,C6="Dublagem Spun",0.8,C6="Dublagem Cretone",0.8,C6="Dublagem Cretone PES",0.8,C6="Espelhamento",0.8,C6="Peletização",0.5,C6="Dublagem Spun - MO",0.8,C6="Dublagem Cretone - MO",0.8,C6="Dublagem Cretone PES - MO",0.8,C6="Espelhamento - MO",0.8,C6="Emborrachamento",1,C6="Malha",0,C6="Dublagem Barreira",1,C6="Pel. + Cal.",0.4,C6="Fel. + Pel. + Cal.",0.5,C6="Pel. + Spun",0.8,C6="Espelhamento - L: 1,45m",0.8,C6="Espelhamento - L: 1,65m",0.8,C6="Estampagem",1,C6="Fel. + Cal.",0.4,C6="Dublagem Juta",0.8,C6="Dublagem Cretone - MO (Juta)",0.8,C6="Dublagem Tapete",0.8,C6="Esp. + Pel.",0.8,C6="Espelhamento 2x",0.8)} -> 0.8 | U6: 1 | V6: 1 | X6: 39.67 | Y6: 38.51 | Z6: 116.78
B7: Aparatos | C7: Dublagem Spun | D7: Novo | E7: 1 | F7: 6.5 | G7: =F7 -> 6.5 | H7: metro linear | I7: =G7/E7 -> 6.5 | J7: 45663 | K7: Insumos fornecidos por Tapajos | L7: =G7-M7-N7 -> 4.4858 | M7: =IF(B7="Texion Textil",0,IF(C7="Malha",'Custos insumos'!$B$24,IF(C7="Dublagem Cretone",'Custos insumos'!$D$7,IF(C7="Dublagem Spun",'Custos insumos'!$D$4,IF(C7="Espelhamento",'Custos insumos'!$B$11,IF(C7="Espelhamento 2x",2*'Custos insumos'!$B$11,IF(C7="Esp. + Pel.",'Custos insumos'!$B$11,IF(C7="Pel. + Spun",'Custos insumos'!$D$4,IF(C7="Dublagem Cretone PES",'Custos insumos'!$D$7,IF(C7="Dublagem Barreira",'Custos insumos'!$D$11,IF(C7="Dublagem - MO + Filme",'Custos insumos'!$D$4,IF(C7="Dublagem Cretone HM50",'Custos insumos'!$D$26,IF(C7="Dublagem Cretone HM70",'Custos insumos'!$F$10,))))))))))))) -> 1.1232 | N7: =IF(B7="Texion Textil",0,IF(B7="Três Elos",0,IF(C7="Malha",0,IF(C7="Dublagem Cretone",'Custos insumos'!$D$23,IF(C7="Dublagem Spun",'Custos insumos'!$D$19,IF(C7="Espelhamento",0,IF(C7="Espelhamento 2x",0,IF(C7="Esp. + Pel.",0,IF(C7="Pel. + Spun",'Custos insumos'!$D$19,IF(C7="Dublagem Cretone PES",'Custos insumos'!$F$25,IF(C7="Dublagem Barreira",'Custos insumos'!$D$22,))))))))))) -> 0.891 | P7: =(Q7-S7)/Q7 -> 0.57503015 | Q7: =G7*R7 -> 1625 | R7: {=_xlfn.IFS(C7="Calandra",(350),C7="Peletização",(421),C7="Dublagem Spun",(250),C7="Dublagem Cretone PES",(180),C7="Felpagem",(270/E7),C7="Emborrachamento",(200),C7="Espelhamento",(250),C7="Malha",(1),C7="Dublagem Cretone",(180),C7="Malha",(1),C7="Dublagem Spun - MO",250,C7="Dublagem Cretone - MO",180,C7="Dublagem Cretone PES - MO",180,C7="Espelhamento - MO",250,C7="Emborrachamento",100,C7="Malha",0,C7="Dublagem Barreira",100,C7="Pel. + Cal.",350,C7="Fel. + Pel. + Cal.",270,C7="Pel. + Spun",250,C7="Espelhamento - L: 1,45m",200,C7="Espelhamento - L: 1,65m",200,C7="Estampagem",100,C7="Fel. + Cal.",270,C7="Dublagem Juta",180,C7="Dublagem Cretone - MO (Juta)",180,C7="Dublagem Tapete",150,C7="Esp. + Pel.",200,C7="Espelhamento 2x",100)} -> 250 | S7: =(T7*X7)+(U7*Y7)+(V7*Z7)+((M7+N7)*(R7)) -> 690.576 | T7: {=_xlfn.IFS(C7="Calandra",0.4,C7="Felpagem",0.3,C7="Dublagem Spun",0.8,C7="Dublagem Cretone",0.8,C7="Dublagem Cretone PES",0.8,C7="Espelhamento",0.8,C7="Peletização",0.5,C7="Dublagem Spun - MO",0.8,C7="Dublagem Cretone - MO",0.8,C7="Dublagem Cretone PES - MO",0.8,C7="Espelhamento - MO",0.8,C7="Emborrachamento",1,C7="Malha",0,C7="Dublagem Barreira",1,C7="Pel. + Cal.",0.4,C7="Fel. + Pel. + Cal.",0.5,C7="Pel. + Spun",0.8,C7="Espelhamento - L: 1,45m",0.8,C7="Espelhamento - L: 1,65m",0.8,C7="Estampagem",1,C7="Fel. + Cal.",0.4,C7="Dublagem Juta",0.8,C7="Dublagem Cretone - MO (Juta)",0.8,C7="Dublagem Tapete",0.8,C7="Esp. + Pel.",0.8,C7="Espelhamento 2x",0.8)} -> 0.8 | U7: 1 | V7: 1 | X7: 39.67 | Y7: 38.51 | Z7: 116.78
B8: Aparatos | C8: Dublagem Cretone - MO | E8: 1 | F8: =E8+(E8*0.1) -> 1.1 | G8: =F8 -> 1.1 | H8: metro linear | I8: =G8/E8 -> 1.1 | J8: 45663 | K8: Insumos fornecidos por Tapajos; TNT= R$ 1,42 + Filme HM20/35 = R$ 1,1 | L8: =G8-M8-N8 -> 1.1 | M8: =IF(B8="Texion Textil",0,IF(C8="Malha",'Custos insumos'!$B$24,IF(C8="Dublagem Cretone",'Custos insumos'!$D$7,IF(C8="Dublagem Spun",'Custos insumos'!$D$4,IF(C8="Espelhamento",'Custos insumos'!$B$11,IF(C8="Espelhamento 2x",2*'Custos insumos'!$B$11,IF(C8="Esp. + Pel.",'Custos insumos'!$B$11,IF(C8="Pel. + Spun",'Custos insumos'!$D$4,IF(C8="Dublagem Cretone PES",'Custos insumos'!$D$7,IF(C8="Dublagem Barreira",'Custos insumos'!$D$11,IF(C8="Dublagem - MO + Filme",'Custos insumos'!$D$4,IF(C8="Dublagem Cretone HM50",'Custos insumos'!$D$26,IF(C8="Dublagem Cretone HM70",'Custos insumos'!$F$10,))))))))))))) -> 0 | N8: =IF(B8="Texion Textil",0,IF(B8="Três Elos",0,IF(C8="Malha",0,IF(C8="Dublagem Cretone",'Custos insumos'!$D$23,IF(C8="Dublagem Spun",'Custos insumos'!$D$19,IF(C8="Espelhamento",0,IF(C8="Espelhamento 2x",0,IF(C8="Esp. + Pel.",0,IF(C8="Pel. + Spun",'Custos insumos'!$D$19,IF(C8="Dublagem Cretone PES",'Custos insumos'!$F$25,IF(C8="Dublagem Barreira",'Custos insumos'!$D$22,))))))))))) -> 0 | P8: =(Q8-S8)/Q8 -> 0.055424242 | Q8: =G8*R8 -> 198 | R8: {=_xlfn.IFS(C8="Calandra",(350),C8="Peletização",(421),C8="Dublagem Spun",(250),C8="Dublagem Cretone PES",(180),C8="Felpagem",(270/E8),C8="Emborrachamento",(200),C8="Espelhamento",(250),C8="Malha",(1),C8="Dublagem Cretone",(180),C8="Malha",(1),C8="Dublagem Spun - MO",250,C8="Dublagem Cretone - MO",180,C8="Dublagem Cretone PES - MO",180,C8="Espelhamento - MO",250,C8="Emborrachamento",100,C8="Malha",0,C8="Dublagem Barreira",100,C8="Pel. + Cal.",350,C8="Fel. + Pel. + Cal.",270,C8="Pel. + Spun",250,C8="Espelhamento - L: 1,45m",200,C8="Espelhamento - L: 1,65m",200,C8="Estampagem",100,C8="Fel. + Cal.",270,C8="Dublagem Juta",180,C8="Dublagem Cretone - MO (Juta)",180,C8="Dublagem Tapete",150,C8="Esp. + Pel.",200,C8="Espelhamento 2x",100)} -> 180 | S8: =(T8*X8)+(U8*Y8)+(V8*Z8)+((M8+N8)*(R8)) -> 187.026 | T8: {=_xlfn.IFS(C8="Calandra",0.4,C8="Felpagem",0.3,C8="Dublagem Spun",0.8,C8="Dublagem Cretone",0.8,C8="Dublagem Cretone PES",0.8,C8="Espelhamento",0.8,C8="Peletização",0.5,C8="Dublagem Spun - MO",0.8,C8="Dublagem Cretone - MO",0.8,C8="Dublagem Cretone PES - MO",0.8,C8="Espelhamento - MO",0.8,C8="Emborrachamento",1,C8="Malha",0,C8="Dublagem Barreira",1,C8="Pel. + Cal.",0.4,C8="Fel. + Pel. + Cal.",0.5,C8="Pel. + Spun",0.8,C8="Espelhamento - L: 1,45m",0.8,C8="Espelhamento - L: 1,65m",0.8,C8="Estampagem",1,C8="Fel. + Cal.",0.4,C8="Dublagem Juta",0.8,C8="Dublagem Cretone - MO (Juta)",0.8,C8="Dublagem Tapete",0.8,C8="Esp. + Pel.",0.8,C8="Espelhamento 2x",0.8)} -> 0.8 | U8: 1 | V8: 1 | X8: 39.67 | Y8: 38.51 | Z8: 116.78
B9: Aparatos | C9: Dublagem Spun - MO | E9: 1 | F9: =E9+(E9*0.1) -> 1.1 | G9: =F9 -> 1.1 | H9: metro linear | I9: =G9/E9 -> 1.1 | J9: 45663 | K9: Insumos fornecidos por Tapajos | L9: =G9-M9-N9 -> 1.1 | M9: =IF(B9="Texion Textil",0,IF(C9="Malha",'Custos insumos'!$B$24,IF(C9="Dublagem Cretone",'Custos insumos'!$D$7,IF(C9="Dublagem Spun",'Custos insumos'!$D$4,IF(C9="Espelhamento",'Custos insumos'!$B$11,IF(C9="Espelhamento 2x",2*'Custos insumos'!$B$11,IF(C9="Esp. + Pel.",'Custos insumos'!$B$11,IF(C9="Pel. + Spun",'Custos insumos'!$D$4,IF(C9="Dublagem Cretone PES",'Custos insumos'!$D$7,IF(C9="Dublagem Barreira",'Custos insumos'!$D$11,IF(C9="Dublagem - MO + Filme",'Custos insumos'!$D$4,IF(C9="Dublagem Cretone HM50",'Custos insumos'!$D$26,IF(C9="Dublagem Cretone HM70",'Custos insumos'!$F$10,))))))))))))) -> 0 | N9: =IF(B9="Texion Textil",0,IF(B9="Três Elos",0,IF(C9="Malha",0,IF(C9="Dublagem Cretone",'Custos insumos'!$D$23,IF(C9="Dublagem Spun",'Custos insumos'!$D$19,IF(C9="Espelhamento",0,IF(C9="Espelhamento 2x",0,IF(C9="Esp. + Pel.",0,IF(C9="Pel. + Spun",'Custos insumos'!$D$19,IF(C9="Dublagem Cretone PES",'Custos insumos'!$F$25,IF(C9="Dublagem Barreira",'Custos insumos'!$D$22,))))))))))) -> 0 | P9: =(Q9-S9)/Q9 -> 0.31990545 | Q9: =G9*R9 -> 275 | R9: {=_xlfn.IFS(C9="Calandra",(350),C9="Peletização",(421),C9="Dublagem Spun",(250),C9="Dublagem Cretone PES",(180),C9="Felpagem",(270/E9),C9="Emborrachamento",(200),C9="Espelhamento",(250),C9="Malha",(1),C9="Dublagem Cretone",(180),C9="Malha",(1),C9="Dublagem Spun - MO",250,C9="Dublagem Cretone - MO",180,C9="Dublagem Cretone PES - MO",180,C9="Espelhamento - MO",250,C9="Emborrachamento",100,C9="Malha",0,C9="Dublagem Barreira",100,C9="Pel. + Cal.",350,C9="Fel. + Pel. + Cal.",270,C9="Pel. + Spun",250,C9="Espelhamento - L: 1,45m",200,C9="Espelhamento - L: 1,65m",200,C9="Estampagem",100,C9="Fel. + Cal.",270,C9="Dublagem Juta",180,C9="Dublagem Cretone - MO (Juta)",180,C9="Dublagem Tapete",150,C9="Esp. + Pel.",200,C9="Espelhamento 2x",100)} -> 250 | S9: =(T9*X9)+(U9*Y9)+(V9*Z9)+((M9+N9)*(R9)) -> 187.026 | T9: {=_xlfn.IFS(C9="Calandra",0.4,C9="Felpagem",0.3,C9="Dublagem Spun",0.8,C9="Dublagem Cretone",0.8,C9="Dublagem Cretone PES",0.8,C9="Espelhamento",0.8,C9="Peletização",0.5,C9="Dublagem Spun - MO",0.8,C9="Dublagem Cretone - MO",0.8,C9="Dublagem Cretone PES - MO",0.8,C9="Espelhamento - MO",0.8,C9="Emborrachamento",1,C9="Malha",0,C9="Dublagem Barreira",1,C9="Pel. + Cal.",0.4,C9="Fel. + Pel. + Cal.",0.5,C9="Pel. + Spun",0.8,C9="Espelhamento - L: 1,45m",0.8,C9="Espelhamento - L: 1,65m",0.8,C9="Estampagem",1,C9="Fel. + Cal.",0.4,C9="Dublagem Juta",0.8,C9="Dublagem Cretone - MO (Juta)",0.8,C9="Dublagem Tapete",0.8,C9="Esp. + Pel.",0.8,C9="Espelhamento 2x",0.8)} -> 0.8 | U9: 1 | V9: 1 | X9: 39.67 | Y9: 38.51 | Z9: 116.78
B10: Aparatos | C10: Espelhamento | E10: 1 | F10: =E10+(E10*0.1) -> 1.1 | G10: =F10 -> 1.1 | H10: metro linear | I10: =G10/E10 -> 1.1 | J10: 45663 | K10: Insumos fornecidos por Tapajos | L10: =G10-M10-N10 -> 0.04149971 | M10: =IF(B10="Texion Textil",0,IF(C10="Malha",'Custos insumos'!$B$24,IF(C10="Dublagem Cretone",'Custos insumos'!$D$7,IF(C10="Dublagem Spun",'Custos insumos'!$D$4,IF(C10="Espelhamento",'Custos insumos'!$B$11,IF(C10="Espelhamento 2x",2*'Custos insumos'!$B$11,IF(C10="Esp. + Pel.",'Custos insumos'!$B$11,IF(C10="Pel. + Spun",'Custos insumos'!$D$4,IF(C10="Dublagem Cretone PES",'Custos insumos'!$D$7,IF(C10="Dublagem Barreira",'Custos insumos'!$D$11,IF(C10="Dublagem - MO + Filme",'Custos insumos'!$D$4,IF(C10="Dublagem Cretone HM50",'Custos insumos'!$D$26,IF(C10="Dublagem Cretone HM70",'Custos insumos'!$F$10,))))))))))))) -> 1.0585003 | N10: =IF(B10="Texion Textil",0,IF(B10="Três Elos",0,IF(C10="Malha",0,IF(C10="Dublagem Cretone",'Custos insumos'!$D$23,IF(C10="Dublagem Spun",'Custos insumos'!$D$19,IF(C10="Espelhamento",0,IF(C10="Espelhamento 2x",0,IF(C10="Esp. + Pel.",0,IF(C10="Pel. + Spun",'Custos insumos'!$D$19,IF(C10="Dublagem Cretone PES",'Custos insumos'!$F$25,IF(C10="Dublagem Barreira",'Custos insumos'!$D$22,))))))))))) -> 0 | P10: =(Q10-S10)/Q10 -> -0.64236754 | Q10: =G10*R10 -> 275 | R10: {=_xlfn.IFS(C10="Calandra",(350),C10="Peletização",(421),C10="Dublagem Spun",(250),C10="Dublagem Cretone PES",(180),C10="Felpagem",(270/E10),C10="Emborrachamento",(200),C10="Espelhamento",(250),C10="Malha",(1),C10="Dublagem Cretone",(180),C10="Malha",(1),C10="Dublagem Spun - MO",250,C10="Dublagem Cretone - MO",180,C10="Dublagem Cretone PES - MO",180,C10="Espelhamento - MO",250,C10="Emborrachamento",100,C10="Malha",0,C10="Dublagem Barreira",100,C10="Pel. + Cal.",350,C10="Fel. + Pel. + Cal.",270,C10="Pel. + Spun",250,C10="Espelhamento - L: 1,45m",200,C10="Espelhamento - L: 1,65m",200,C10="Estampagem",100,C10="Fel. + Cal.",270,C10="Dublagem Juta",180,C10="Dublagem Cretone - MO (Juta)",180,C10="Dublagem Tapete",150,C10="Esp. + Pel.",200,C10="Espelhamento 2x",100)} -> 250 | S10: =(T10*X10)+(U10*Y10)+(V10*Z10)+((M10+N10)*(R10)) -> 451.65107 | T10: {=_xlfn.IFS(C10="Calandra",0.4,C10="Felpagem",0.3,C10="Dublagem Spun",0.8,C10="Dublagem Cretone",0.8,C10="Dublagem Cretone PES",0.8,C10="Espelhamento",0.8,C10="Peletização",0.5,C10="Dublagem Spun - MO",0.8,C10="Dublagem Cretone - MO",0.8,C10="Dublagem Cretone PES - MO",0.8,C10="Espelhamento - MO",0.8,C10="Emborrachamento",1,C10="Malha",0,C10="Dublagem Barreira",1,C10="Pel. + Cal.",0.4,C10="Fel. + Pel. + Cal.",0.5,C10="Pel. + Spun",0.8,C10="Espelhamento - L: 1,45m",0.8,C10="Espelhamento - L: 1,65m",0.8,C10="Estampagem",1,C10="Fel. + Cal.",0.4,C10="Dublagem Juta",0.8,C10="Dublagem Cretone - MO (Juta)",0.8,C10="Dublagem Tapete",0.8,C10="Esp. + Pel.",0.8,C10="Espelhamento 2x",0.8)} -> 0.8 | U10: 1 | V10: 1 | X10: 39.67 | Y10: 38.51 | Z10: 116.78
B11: Bergon | C11: Felpagem - FRETE- R$70,00 | D11: 12221 e 12179 | E11: 2 | F11: 0.5 | G11: 0.45 | H11: metro linear | I11: =G11/E11 -> 0.225 | J11: 45663 | L11: =G11-M11-N11 -> 0.45 | M11: =IF(B11="Texion Textil",0,IF(C11="Malha",'Custos insumos'!$B$24,IF(C11="Dublagem Cretone",'Custos insumos'!$D$7,IF(C11="Dublagem Spun",'Custos insumos'!$D$4,IF(C11="Espelhamento",'Custos insumos'!$B$11,IF(C11="Espelhamento 2x",2*'Custos insumos'!$B$11,IF(C11="Esp. + Pel.",'Custos insumos'!$B$11,IF(C11="Pel. + Spun",'Custos insumos'!$D$4,IF(C11="Dublagem Cretone PES",'Custos insumos'!$D$7,IF(C11="Dublagem Barreira",'Custos insumos'!$D$11,IF(C11="Dublagem - MO + Filme",'Custos insumos'!$D$4,IF(C11="Dublagem Cretone HM50",'Custos insumos'!$D$26,IF(C11="Dublagem Cretone HM70",'Custos insumos'!$F$10,))))))))))))) -> 0 | N11: =IF(B11="Texion Textil",0,IF(B11="Três Elos",0,IF(C11="Malha",0,IF(C11="Dublagem Cretone",'Custos insumos'!$D$23,IF(C11="Dublagem Spun",'Custos insumos'!$D$19,IF(C11="Espelhamento",0,IF(C11="Espelhamento 2x",0,IF(C11="Esp. + Pel.",0,IF(C11="Pel. + Spun",'Custos insumos'!$D$19,IF(C11="Dublagem Cretone PES",'Custos insumos'!$F$25,IF(C11="Dublagem Barreira",'Custos insumos'!$D$22,))))))))))) -> 0 | P11: =(Q11-S11)/Q11 -> #N/A | Q11: =G11*R11 -> #N/A | R11: {=_xlfn.IFS(C11="Calandra",(350),C11="Peletização",(421),C11="Dublagem Spun",(250),C11="Dublagem Cretone PES",(180),C11="Felpagem",(270/E11),C11="Emborrachamento",(200),C11="Espelhamento",(250),C11="Malha",(1),C11="Dublagem Cretone",(180),C11="Malha",(1),C11="Dublagem Spun - MO",250,C11="Dublagem Cretone - MO",180,C11="Dublagem Cretone PES - MO",180,C11="Espelhamento - MO",250,C11="Emborrachamento",100,C11="Malha",0,C11="Dublagem Barreira",100,C11="Pel. + Cal.",350,C11="Fel. + Pel. + Cal.",270,C11="Pel. + Spun",250,C11="Espelhamento - L: 1,45m",200,C11="Espelhamento - L: 1,65m",200,C11="Estampagem",100,C11="Fel. + Cal.",270,C11="Dublagem Juta",180,C11="Dublagem Cretone - MO (Juta)",180,C11="Dublagem Tapete",150,C11="Esp. + Pel.",200,C11="Espelhamento 2x",100)} -> #N/A | S11: =(T11*X11)+(U11*Y11)+(V11*Z11)+((M11+N11)*(R11)) -> #N/A | T11: {=_xlfn.IFS(C11="Calandra",0.4,C11="Felpagem",0.3,C11="Dublagem Spun",0.8,C11="Dublagem Cretone",0.8,C11="Dublagem Cretone PES",0.8,C11="Espelhamento",0.8,C11="Peletização",0.5,C11="Dublagem Spun - MO",0.8,C11="Dublagem Cretone - MO",0.8,C11="Dublagem Cretone PES - MO",0.8,C11="Espelhamento - MO",0.8,C11="Emborrachamento",1,C11="Malha",0,C11="Dublagem Barreira",1,C11="Pel. + Cal.",0.4,C11="Fel. + Pel. + Cal.",0.5,C11="Pel. + Spun",0.8,C11="Espelhamento - L: 1,45m",0.8,C11="Espelhamento - L: 1,65m",0.8,C11="Estampagem",1,C11="Fel. + Cal.",0.4,C11="Dublagem Juta",0.8,C11="Dublagem Cretone - MO (Juta)",0.8,C11="Dublagem Tapete",0.8,C11="Esp. + Pel.",0.8,C11="Espelhamento 2x",0.8)} -> #N/A | U11: 1 | V11: 1 | X11: 39.67 | Y11: 38.51 | Z11: 116.78
B12: Bergon | C12: Felpagem | D12: 12142 | E12: 2 | F12: 0.35 | G12: =F12 -> 0.35 | H12: metro linear | I12: =G12/E12 -> 0.175 | J12: 45663 | L12: =G12-M12-N12 -> 0.35 | M12: =IF(B12="Texion Textil",0,IF(C12="Malha",'Custos insumos'!$B$24,IF(C12="Dublagem Cretone",'Custos insumos'!$D$7,IF(C12="Dublagem Spun",'Custos insumos'!$D$4,IF(C12="Espelhamento",'Custos insumos'!$B$11,IF(C12="Espelhamento 2x",2*'Custos insumos'!$B$11,IF(C12="Esp. + Pel.",'Custos insumos'!$B$11,IF(C12="Pel. + Spun",'Custos insumos'!$D$4,IF(C12="Dublagem Cretone PES",'Custos insumos'!$D$7,IF(C12="Dublagem Barreira",'Custos insumos'!$D$11,IF(C12="Dublagem - MO + Filme",'Custos insumos'!$D$4,IF(C12="Dublagem Cretone HM50",'Custos insumos'!$D$26,IF(C12="Dublagem Cretone HM70",'Custos insumos'!$F$10,))))))))))))) -> 0 | N12: =IF(B12="Texion Textil",0,IF(B12="Três Elos",0,IF(C12="Malha",0,IF(C12="Dublagem Cretone",'Custos insumos'!$D$23,IF(C12="Dublagem Spun",'Custos insumos'!$D$19,IF(C12="Espelhamento",0,IF(C12="Espelhamento 2x",0,IF(C12="Esp. + Pel.",0,IF(C12="Pel. + Spun",'Custos insumos'!$D$19,IF(C12="Dublagem Cretone PES",'Custos insumos'!$F$25,IF(C12="Dublagem Barreira",'Custos insumos'!$D$22,))))))))))) -> 0 | P12: =(Q12-S12)/Q12 -> #N/A | Q12: =G12*R12 -> #N/A | R12: {=_xlfn.IFS(C12="Calandra",(350),C12="Peletização",(421),C12="Dublagem Spun",(250),C12="Dublagem Cretone PES",(180),C12="Felpagem",(270/E12),C12="Emborrachamento",(200),C12="Espelhamento",(250),C12="Malha",(1),C12="Dublagem Cretone",(180),C12="Malha",(1),C12="Dublagem Spun - MO",250,C12="Dublagem Cretone - MO",180,C12="Dublagem Cretone PES - MO",180,C12="Espelhamento - MO",250,C12="Emborrachamento",100,C12="Malha",0,C12="Dublagem Barreira",100,C12="Pel. + Cal.",350,C12="Fel. + Pel. + Cal.",270,C12="Pel. + Spun",250,C12="Espelhamento - L: 1,45m",200,C12="Espelhamento - L: 1,65m",200,C12="Estampagem",100,C12="Fel. + Cal.",270,C12="Dublagem Juta",180,C12="Dublagem Cretone - MO (Juta)",180,C12="Dublagem Tapete",150,C12="Esp. + Pel.",200,C12="Espelhamento 2x",100)} -> #N/A | S12: =(T12*X12)+(U12*Y12)+(V12*Z12)+((M12+N12)*(R12)) -> #N/A | T12: {=_xlfn.IFS(C12="Calandra",0.4,C12="Felpagem",0.3,C12="Dublagem Spun",0.8,C12="Dublagem Cretone",0.8,C12="Dublagem Cretone PES",0.8,C12="Espelhamento",0.8,C12="Peletização",0.5,C12="Dublagem Spun - MO",0.8,C12="Dublagem Cretone - MO",0.8,C12="Dublagem Cretone PES - MO",0.8,C12="Espelhamento - MO",0.8,C12="Emborrachamento",1,C12="Malha",0,C12="Dublagem Barreira",1,C12="Pel. + Cal.",0.4,C12="Fel. + Pel. + Cal.",0.5,C12="Pel. + Spun",0.8,C12="Espelhamento - L: 1,45m",0.8,C12="Espelhamento - L: 1,65m",0.8,C12="Estampagem",1,C12="Fel. + Cal.",0.4,C12="Dublagem Juta",0.8,C12="Dublagem Cretone - MO (Juta)",0.8,C12="Dublagem Tapete",0.8,C12="Esp. + Pel.",0.8,C12="Espelhamento 2x",0.8)} -> #N/A | U12: 1 | V12: 1 | X12: 39.67 | Y12: 38.51 | Z12: 116.78
B13: Bergon | C13: Peletização | E13: 1 | F13: 0.45 | G13: 0.65 | H13: metro linear | I13: =G13/E13 -> 0.65 | J13: 45663 | L13: =G13-M13-N13 -> 0.65 | M13: =IF(B13="Texion Textil",0,IF(C13="Malha",'Custos insumos'!$B$24,IF(C13="Dublagem Cretone",'Custos insumos'!$D$7,IF(C13="Dublagem Spun",'Custos insumos'!$D$4,IF(C13="Espelhamento",'Custos insumos'!$B$11,IF(C13="Espelhamento 2x",2*'Custos insumos'!$B$11,IF(C13="Esp. + Pel.",'Custos insumos'!$B$11,IF(C13="Pel. + Spun",'Custos insumos'!$D$4,IF(C13="Dublagem Cretone PES",'Custos insumos'!$D$7,IF(C13="Dublagem Barreira",'Custos insumos'!$D$11,IF(C13="Dublagem - MO + Filme",'Custos insumos'!$D$4,IF(C13="Dublagem Cretone HM50",'Custos insumos'!$D$26,IF(C13="Dublagem Cretone HM70",'Custos insumos'!$F$10,))))))))))))) -> 0 | N13: =IF(B13="Texion Textil",0,IF(B13="Três Elos",0,IF(C13="Malha",0,IF(C13="Dublagem Cretone",'Custos insumos'!$D$23,IF(C13="Dublagem Spun",'Custos insumos'!$D$19,IF(C13="Espelhamento",0,IF(C13="Espelhamento 2x",0,IF(C13="Esp. + Pel.",0,IF(C13="Pel. + Spun",'Custos insumos'!$D$19,IF(C13="Dublagem Cretone PES",'Custos insumos'!$F$25,IF(C13="Dublagem Barreira",'Custos insumos'!$D$22,))))))))))) -> 0 | P13: =(Q13-S13)/Q13 -> 0.3600402 | Q13: =G13*R13 -> 273.65 | R13: {=_xlfn.IFS(C13="Calandra",(350),C13="Peletização",(421),C13="Dublagem Spun",(250),C13="Dublagem Cretone PES",(180),C13="Felpagem",(270/E13),C13="Emborrachamento",(200),C13="Espelhamento",(250),C13="Malha",(1),C13="Dublagem Cretone",(180),C13="Malha",(1),C13="Dublagem Spun - MO",250,C13="Dublagem Cretone - MO",180,C13="Dublagem Cretone PES - MO",180,C13="Espelhamento - MO",250,C13="Emborrachamento",100,C13="Malha",0,C13="Dublagem Barreira",100,C13="Pel. + Cal.",350,C13="Fel. + Pel. + Cal.",270,C13="Pel. + Spun",250,C13="Espelhamento - L: 1,45m",200,C13="Espelhamento - L: 1,65m",200,C13="Estampagem",100,C13="Fel. + Cal.",270,C13="Dublagem Juta",180,C13="Dublagem Cretone - MO (Juta)",180,C13="Dublagem Tapete",150,C13="Esp. + Pel.",200,C13="Espelhamento 2x",100)} -> 421 | S13: =(T13*X13)+(U13*Y13)+(V13*Z13)+((M13+N13)*(R13)) -> 175.125 | T13: {=_xlfn.IFS(C13="Calandra",0.4,C13="Felpagem",0.3,C13="Dublagem Spun",0.8,C13="Dublagem Cretone",0.8,C13="Dublagem Cretone PES",0.8,C13="Espelhamento",0.8,C13="Peletização",0.5,C13="Dublagem Spun - MO",0.8,C13="Dublagem Cretone - MO",0.8,C13="Dublagem Cretone PES - MO",0.8,C13="Espelhamento - MO",0.8,C13="Emborrachamento",1,C13="Malha",0,C13="Dublagem Barreira",1,C13="Pel. + Cal.",0.4,C13="Fel. + Pel. + Cal.",0.5,C13="Pel. + Spun",0.8,C13="Espelhamento - L: 1,45m",0.8,C13="Espelhamento - L: 1,65m",0.8,C13="Estampagem",1,C13="Fel. + Cal.",0.4,C13="Dublagem Juta",0.8,C13="Dublagem Cretone - MO (Juta)",0.8,C13="Dublagem Tapete",0.8,C13="Esp. + Pel.",0.8,C13="Espelhamento 2x",0.8)} -> 0.5 | U13: 1 | V13: 1 | X13: 39.67 | Y13: 38.51 | Z13: 116.78
B14: Bergon | C14: Calandra | E14: 1 | F14: 0.65 | G14: =F14 -> 0.65 | H14: metro linear | I14: =G14/E14 -> 0.65 | J14: 45663 | L14: =G14-M14-N14 -> 0.65 | M14: =IF(B14="Texion Textil",0,IF(C14="Malha",'Custos insumos'!$B$24,IF(C14="Dublagem Cretone",'Custos insumos'!$D$7,IF(C14="Dublagem Spun",'Custos insumos'!$D$4,IF(C14="Espelhamento",'Custos insumos'!$B$11,IF(C14="Espelhamento 2x",2*'Custos insumos'!$B$11,IF(C14="Esp. + Pel.",'Custos insumos'!$B$11,IF(C14="Pel. + Spun",'Custos insumos'!$D$4,IF(C14="Dublagem Cretone PES",'Custos insumos'!$D$7,IF(C14="Dublagem Barreira",'Custos insumos'!$D$11,IF(C14="Dublagem - MO + Filme",'Custos insumos'!$D$4,IF(C14="Dublagem Cretone HM50",'Custos insumos'!$D$26,IF(C14="Dublagem Cretone HM70",'Custos insumos'!$F$10,))))))))))))) -> 0 | N14: =IF(B14="Texion Textil",0,IF(B14="Três Elos",0,IF(C14="Malha",0,IF(C14="Dublagem Cretone",'Custos insumos'!$D$23,IF(C14="Dublagem Spun",'Custos insumos'!$D$19,IF(C14="Espelhamento",0,IF(C14="Espelhamento 2x",0,IF(C14="Esp. + Pel.",0,IF(C14="Pel. + Spun",'Custos insumos'!$D$19,IF(C14="Dublagem Cretone PES",'Custos insumos'!$F$25,IF(C14="Dublagem Barreira",'Custos insumos'!$D$22,))))))))))) -> 0 | P14: =(Q14-S14)/Q14 -> 0.24765714 | Q14: =G14*R14 -> 227.5 | R14: {=_xlfn.IFS(C14="Calandra",(350),C14="Peletização",(421),C14="Dublagem Spun",(250),C14="Dublagem Cretone PES",(180),C14="Felpagem",(270/E14),C14="Emborrachamento",(200),C14="Espelhamento",(250),C14="Malha",(1),C14="Dublagem Cretone",(180),C14="Malha",(1),C14="Dublagem Spun - MO",250,C14="Dublagem Cretone - MO",180,C14="Dublagem Cretone PES - MO",180,C14="Espelhamento - MO",250,C14="Emborrachamento",100,C14="Malha",0,C14="Dublagem Barreira",100,C14="Pel. + Cal.",350,C14="Fel. + Pel. + Cal.",270,C14="Pel. + Spun",250,C14="Espelhamento - L: 1,45m",200,C14="Espelhamento - L: 1,65m",200,C14="Estampagem",100,C14="Fel. + Cal.",270,C14="Dublagem Juta",180,C14="Dublagem Cretone - MO (Juta)",180,C14="Dublagem Tapete",150,C14="Esp. + Pel.",200,C14="Espelhamento 2x",100)} -> 350 | S14: =(T14*X14)+(U14*Y14)+(V14*Z14)+((M14+N14)*(R14)) -> 171.158 | T14: {=_xlfn.IFS(C14="Calandra",0.4,C14="Felpagem",0.3,C14="Dublagem Spun",0.8,C14="Dublagem Cretone",0.8,C14="Dublagem Cretone PES",0.8,C14="Espelhamento",0.8,C14="Peletização",0.5,C14="Dublagem Spun - MO",0.8,C14="Dublagem Cretone - MO",0.8,C14="Dublagem Cretone PES - MO",0.8,C14="Espelhamento - MO",0.8,C14="Emborrachamento",1,C14="Malha",0,C14="Dublagem Barreira",1,C14="Pel. + Cal.",0.4,C14="Fel. + Pel. + Cal.",0.5,C14="Pel. + Spun",0.8,C14="Espelhamento - L: 1,45m",0.8,C14="Espelhamento - L: 1,65m",0.8,C14="Estampagem",1,C14="Fel. + Cal.",0.4,C14="Dublagem Juta",0.8,C14="Dublagem Cretone - MO (Juta)",0.8,C14="Dublagem Tapete",0.8,C14="Esp. + Pel.",0.8,C14="Espelhamento 2x",0.8)} -> 0.4 | U14: 1 | V14: 1 | X14: 39.67 | Y14: 38.51 | Z14: 116.78
B15: Bergon | C15: Espelhamento - MO | E15: 1 | F15: 1.15 | G15: =F15 -> 1.15 | H15: metro linear | I15: =G15/E15 -> 1.15 | J15: 45663 | K15: Mão de obra | L15: =G15-M15-N15 -> 1.15 | M15: =IF(B15="Texion Textil",0,IF(C15="Malha",'Custos insumos'!$B$24,IF(C15="Dublagem Cretone",'Custos insumos'!$D$7,IF(C15="Dublagem Spun",'Custos insumos'!$D$4,IF(C15="Espelhamento",'Custos insumos'!$B$11,IF(C15="Espelhamento 2x",2*'Custos insumos'!$B$11,IF(C15="Esp. + Pel.",'Custos insumos'!$B$11,IF(C15="Pel. + Spun",'Custos insumos'!$D$4,IF(C15="Dublagem Cretone PES",'Custos insumos'!$D$7,IF(C15="Dublagem Barreira",'Custos insumos'!$D$11,IF(C15="Dublagem - MO + Filme",'Custos insumos'!$D$4,IF(C15="Dublagem Cretone HM50",'Custos insumos'!$D$26,IF(C15="Dublagem Cretone HM70",'Custos insumos'!$F$10,))))))))))))) -> 0 | N15: =IF(B15="Texion Textil",0,IF(B15="Três Elos",0,IF(C15="Malha",0,IF(C15="Dublagem Cretone",'Custos insumos'!$D$23,IF(C15="Dublagem Spun",'Custos insumos'!$D$19,IF(C15="Espelhamento",0,IF(C15="Espelhamento 2x",0,IF(C15="Esp. + Pel.",0,IF(C15="Pel. + Spun",'Custos insumos'!$D$19,IF(C15="Dublagem Cretone PES",'Custos insumos'!$F$25,IF(C15="Dublagem Barreira",'Custos insumos'!$D$22,))))))))))) -> 0 | P15: =(Q15-S15)/Q15 -> 0.34947478 | Q15: =G15*R15 -> 287.5 | R15: {=_xlfn.IFS(C15="Calandra",(350),C15="Peletização",(421),C15="Dublagem Spun",(250),C15="Dublagem Cretone PES",(180),C15="Felpagem",(270/E15),C15="Emborrachamento",(200),C15="Espelhamento",(250),C15="Malha",(1),C15="Dublagem Cretone",(180),C15="Malha",(1),C15="Dublagem Spun - MO",250,C15="Dublagem Cretone - MO",180,C15="Dublagem Cretone PES - MO",180,C15="Espelhamento - MO",250,C15="Emborrachamento",100,C15="Malha",0,C15="Dublagem Barreira",100,C15="Pel. + Cal.",350,C15="Fel. + Pel. + Cal.",270,C15="Pel. + Spun",250,C15="Espelhamento - L: 1,45m",200,C15="Espelhamento - L: 1,65m",200,C15="Estampagem",100,C15="Fel. + Cal.",270,C15="Dublagem Juta",180,C15="Dublagem Cretone - MO (Juta)",180,C15="Dublagem Tapete",150,C15="Esp. + Pel.",200,C15="Espelhamento 2x",100)} -> 250 | S15: =(T15*X15)+(U15*Y15)+(V15*Z15)+((M15+N15)*(R15)) -> 187.026 | T15: {=_xlfn.IFS(C15="Calandra",0.4,C15="Felpagem",0.3,C15="Dublagem Spun",0.8,C15="Dublagem Cretone",0.8,C15="Dublagem Cretone PES",0.8,C15="Espelhamento",0.8,C15="Peletização",0.5,C15="Dublagem Spun - MO",0.8,C15="Dublagem Cretone - MO",0.8,C15="Dublagem Cretone PES - MO",0.8,C15="Espelhamento - MO",0.8,C15="Emborrachamento",1,C15="Malha",0,C15="Dublagem Barreira",1,C15="Pel. + Cal.",0.4,C15="Fel. + Pel. + Cal.",0.5,C15="Pel. + Spun",0.8,C15="Espelhamento - L: 1,45m",0.8,C15="Espelhamento - L: 1,65m",0.8,C15="Estampagem",1,C15="Fel. + Cal.",0.4,C15="Dublagem Juta",0.8,C15="Dublagem Cretone - MO (Juta)",0.8,C15="Dublagem Tapete",0.8,C15="Esp. + Pel.",0.8,C15="Espelhamento 2x",0.8)} -> 0.8 | U15: 1 | V15: 1 | X15: 39.67 | Y15: 38.51 | Z15: 116.78
B16: Bergon | C16: Espelhamento | E16: 1 | F16: 2.35 | G16: =F16 -> 2.35 | H16: metro linear | I16: =G16/E16 -> 2.35 | J16: 45663 | K16: Mão de obra e insumos | L16: =G16-M16-N16 -> 1.2914997 | M16: =IF(B16="Texion Textil",0,IF(C16="Malha",'Custos insumos'!$B$24,IF(C16="Dublagem Cretone",'Custos insumos'!$D$7,IF(C16="Dublagem Spun",'Custos insumos'!$D$4,IF(C16="Espelhamento",'Custos insumos'!$B$11,IF(C16="Espelhamento 2x",2*'Custos insumos'!$B$11,IF(C16="Esp. + Pel.",'Custos insumos'!$B$11,IF(C16="Pel. + Spun",'Custos insumos'!$D$4,IF(C16="Dublagem Cretone PES",'Custos insumos'!$D$7,IF(C16="Dublagem Barreira",'Custos insumos'!$D$11,IF(C16="Dublagem - MO + Filme",'Custos insumos'!$D$4,IF(C16="Dublagem Cretone HM50",'Custos insumos'!$D$26,IF(C16="Dublagem Cretone HM70",'Custos insumos'!$F$10,))))))))))))) -> 1.0585003 | N16: =IF(B16="Texion Textil",0,IF(B16="Três Elos",0,IF(C16="Malha",0,IF(C16="Dublagem Cretone",'Custos insumos'!$D$23,IF(C16="Dublagem Spun",'Custos insumos'!$D$19,IF(C16="Espelhamento",0,IF(C16="Espelhamento 2x",0,IF(C16="Esp. + Pel.",0,IF(C16="Pel. + Spun",'Custos insumos'!$D$19,IF(C16="Dublagem Cretone PES",'Custos insumos'!$F$25,IF(C16="Dublagem Barreira",'Custos insumos'!$D$22,))))))))))) -> 0 | P16: =(Q16-S16)/Q16 -> 0.23123222 | Q16: =G16*R16 -> 587.5 | R16: {=_xlfn.IFS(C16="Calandra",(350),C16="Peletização",(421),C16="Dublagem Spun",(250),C16="Dublagem Cretone PES",(180),C16="Felpagem",(270/E16),C16="Emborrachamento",(200),C16="Espelhamento",(250),C16="Malha",(1),C16="Dublagem Cretone",(180),C16="Malha",(1),C16="Dublagem Spun - MO",250,C16="Dublagem Cretone - MO",180,C16="Dublagem Cretone PES - MO",180,C16="Espelhamento - MO",250,C16="Emborrachamento",100,C16="Malha",0,C16="Dublagem Barreira",100,C16="Pel. + Cal.",350,C16="Fel. + Pel. + Cal.",270,C16="Pel. + Spun",250,C16="Espelhamento - L: 1,45m",200,C16="Espelhamento - L: 1,65m",200,C16="Estampagem",100,C16="Fel. + Cal.",270,C16="Dublagem Juta",180,C16="Dublagem Cretone - MO (Juta)",180,C16="Dublagem Tapete",150,C16="Esp. + Pel.",200,C16="Espelhamento 2x",100)} -> 250 | S16: =(T16*X16)+(U16*Y16)+(V16*Z16)+((M16+N16)*(R16)) -> 451.65107 | T16: {=_xlfn.IFS(C16="Calandra",0.4,C16="Felpagem",0.3,C16="Dublagem Spun",0.8,C16="Dublagem Cretone",0.8,C16="Dublagem Cretone PES",0.8,C16="Espelhamento",0.8,C16="Peletização",0.5,C16="Dublagem Spun - MO",0.8,C16="Dublagem Cretone - MO",0.8,C16="Dublagem Cretone PES - MO",0.8,C16="Espelhamento - MO",0.8,C16="Emborrachamento",1,C16="Malha",0,C16="Dublagem Barreira",1,C16="Pel. + Cal.",0.4,C16="Fel. + Pel. + Cal.",0.5,C16="Pel. + Spun",0.8,C16="Espelhamento - L: 1,45m",0.8,C16="Espelhamento - L: 1,65m",0.8,C16="Estampagem",1,C16="Fel. + Cal.",0.4,C16="Dublagem Juta",0.8,C16="Dublagem Cretone - MO (Juta)",0.8,C16="Dublagem Tapete",0.8,C16="Esp. + Pel.",0.8,C16="Espelhamento 2x",0.8)} -> 0.8 | U16: 1 | V16: 1 | X16: 39.67 | Y16: 38.51 | Z16: 116.78
B17: Bergon | C17: Dublagem Spun - MO | E17: 1 | F17: 1.15 | G17: =F17 -> 1.15 | H17: metro linear | I17: =G17/E17 -> 1.15 | J17: 45663 | K17: Mão de obra | L17: =G17-M17-N17 -> 1.15 | M17: =IF(B17="Texion Textil",0,IF(C17="Malha",'Custos insumos'!$B$24,IF(C17="Dublagem Cretone",'Custos insumos'!$D$7,IF(C17="Dublagem Spun",'Custos insumos'!$D$4,IF(C17="Espelhamento",'Custos insumos'!$B$11,IF(C17="Espelhamento 2x",2*'Custos insumos'!$B$11,IF(C17="Esp. + Pel.",'Custos insumos'!$B$11,IF(C17="Pel. + Spun",'Custos insumos'!$D$4,IF(C17="Dublagem Cretone PES",'Custos insumos'!$D$7,IF(C17="Dublagem Barreira",'Custos insumos'!$D$11,IF(C17="Dublagem - MO + Filme",'Custos insumos'!$D$4,IF(C17="Dublagem Cretone HM50",'Custos insumos'!$D$26,IF(C17="Dublagem Cretone HM70",'Custos insumos'!$F$10,))))))))))))) -> 0 | N17: =IF(B17="Texion Textil",0,IF(B17="Três Elos",0,IF(C17="Malha",0,IF(C17="Dublagem Cretone",'Custos insumos'!$D$23,IF(C17="Dublagem Spun",'Custos insumos'!$D$19,IF(C17="Espelhamento",0,IF(C17="Espelhamento 2x",0,IF(C17="Esp. + Pel.",0,IF(C17="Pel. + Spun",'Custos insumos'!$D$19,IF(C17="Dublagem Cretone PES",'Custos insumos'!$F$25,IF(C17="Dublagem Barreira",'Custos insumos'!$D$22,))))))))))) -> 0 | P17: =(Q17-S17)/Q17 -> 0.34947478 | Q17: =G17*R17 -> 287.5 | R17: {=_xlfn.IFS(C17="Calandra",(350),C17="Peletização",(421),C17="Dublagem Spun",(250),C17="Dublagem Cretone PES",(180),C17="Felpagem",(270/E17),C17="Emborrachamento",(200),C17="Espelhamento",(250),C17="Malha",(1),C17="Dublagem Cretone",(180),C17="Malha",(1),C17="Dublagem Spun - MO",250,C17="Dublagem Cretone - MO",180,C17="Dublagem Cretone PES - MO",180,C17="Espelhamento - MO",250,C17="Emborrachamento",100,C17="Malha",0,C17="Dublagem Barreira",100,C17="Pel. + Cal.",350,C17="Fel. + Pel. + Cal.",270,C17="Pel. + Spun",250,C17="Espelhamento - L: 1,45m",200,C17="Espelhamento - L: 1,65m",200,C17="Estampagem",100,C17="Fel. + Cal.",270,C17="Dublagem Juta",180,C17="Dublagem Cretone - MO (Juta)",180,C17="Dublagem Tapete",150,C17="Esp. + Pel.",200,C17="Espelhamento 2x",100)} -> 250 | S17: =(T17*X17)+(U17*Y17)+(V17*Z17)+((M17+N17)*(R17)) -> 187.026 | T17: {=_xlfn.IFS(C17="Calandra",0.4,C17="Felpagem",0.3,C17="Dublagem Spun",0.8,C17="Dublagem Cretone",0.8,C17="Dublagem Cretone PES",0.8,C17="Espelhamento",0.8,C17="Peletização",0.5,C17="Dublagem Spun - MO",0.8,C17="Dublagem Cretone - MO",0.8,C17="Dublagem Cretone PES - MO",0.8,C17="Espelhamento - MO",0.8,C17="Emborrachamento",1,C17="Malha",0,C17="Dublagem Barreira",1,C17="Pel. + Cal.",0.4,C17="Fel. + Pel. + Cal.",0.5,C17="Pel. + Spun",0.8,C17="Espelhamento - L: 1,45m",0.8,C17="Espelhamento - L: 1,65m",0.8,C17="Estampagem",1,C17="Fel. + Cal.",0.4,C17="Dublagem Juta",0.8,C17="Dublagem Cretone - MO (Juta)",0.8,C17="Dublagem Tapete",0.8,C17="Esp. + Pel.",0.8,C17="Espelhamento 2x",0.8)} -> 0.8 | U17: 1 | V17: 1 | X17: 39.67 | Y17: 38.51 | Z17: 116.78
B18: Bergon | C18: Dublagem Spun | E18: 1 | F18: 4.5 | G18: =F18 -> 4.5 | H18: metro linear | I18: =G18/E18 -> 4.5 | J18: 45663 | K18: Mão de obra e insumos | L18: =G18-M18-N18 -> 2.4858 | M18: =IF(B18="Texion Textil",0,IF(C18="Malha",'Custos insumos'!$B$24,IF(C18="Dublagem Cretone",'Custos insumos'!$D$7,IF(C18="Dublagem Spun",'Custos insumos'!$D$4,IF(C18="Espelhamento",'Custos insumos'!$B$11,IF(C18="Espelhamento 2x",2*'Custos insumos'!$B$11,IF(C18="Esp. + Pel.",'Custos insumos'!$B$11,IF(C18="Pel. + Spun",'Custos insumos'!$D$4,IF(C18="Dublagem Cretone PES",'Custos insumos'!$D$7,IF(C18="Dublagem Barreira",'Custos insumos'!$D$11,IF(C18="Dublagem - MO + Filme",'Custos insumos'!$D$4,IF(C18="Dublagem Cretone HM50",'Custos insumos'!$D$26,IF(C18="Dublagem Cretone HM70",'Custos insumos'!$F$10,))))))))))))) -> 1.1232 | N18: =IF(B18="Texion Textil",0,IF(B18="Três Elos",0,IF(C18="Malha",0,IF(C18="Dublagem Cretone",'Custos insumos'!$D$23,IF(C18="Dublagem Spun",'Custos insumos'!$D$19,IF(C18="Espelhamento",0,IF(C18="Espelhamento 2x",0,IF(C18="Esp. + Pel.",0,IF(C18="Pel. + Spun",'Custos insumos'!$D$19,IF(C18="Dublagem Cretone PES",'Custos insumos'!$F$25,IF(C18="Dublagem Barreira",'Custos insumos'!$D$22,))))))))))) -> 0.891 | P18: =(Q18-S18)/Q18 -> 0.38615467 | Q18: =G18*R18 -> 1125 | R18: {=_xlfn.IFS(C18="Calandra",(350),C18="Peletização",(421),C18="Dublagem Spun",(250),C18="Dublagem Cretone PES",(180),C18="Felpagem",(270/E18),C18="Emborrachamento",(200),C18="Espelhamento",(250),C18="Malha",(1),C18="Dublagem Cretone",(180),C18="Malha",(1),C18="Dublagem Spun - MO",250,C18="Dublagem Cretone - MO",180,C18="Dublagem Cretone PES - MO",180,C18="Espelhamento - MO",250,C18="Emborrachamento",100,C18="Malha",0,C18="Dublagem Barreira",100,C18="Pel. + Cal.",350,C18="Fel. + Pel. + Cal.",270,C18="Pel. + Spun",250,C18="Espelhamento - L: 1,45m",200,C18="Espelhamento - L: 1,65m",200,C18="Estampagem",100,C18="Fel. + Cal.",270,C18="Dublagem Juta",180,C18="Dublagem Cretone - MO (Juta)",180,C18="Dublagem Tapete",150,C18="Esp. + Pel.",200,C18="Espelhamento 2x",100)} -> 250 | S18: =(T18*X18)+(U18*Y18)+(V18*Z18)+((M18+N18)*(R18)) -> 690.576 | T18: {=_xlfn.IFS(C18="Calandra",0.4,C18="Felpagem",0.3,C18="Dublagem Spun",0.8,C18="Dublagem Cretone",0.8,C18="Dublagem Cretone PES",0.8,C18="Espelhamento",0.8,C18="Peletização",0.5,C18="Dublagem Spun - MO",0.8,C18="Dublagem Cretone - MO",0.8,C18="Dublagem Cretone PES - MO",0.8,C18="Espelhamento - MO",0.8,C18="Emborrachamento",1,C18="Malha",0,C18="Dublagem Barreira",1,C18="Pel. + Cal.",0.4,C18="Fel. + Pel. + Cal.",0.5,C18="Pel. + Spun",0.8,C18="Espelhamento - L: 1,45m",0.8,C18="Espelhamento - L: 1,65m",0.8,C18="Estampagem",1,C18="Fel. + Cal.",0.4,C18="Dublagem Juta",0.8,C18="Dublagem Cretone - MO (Juta)",0.8,C18="Dublagem Tapete",0.8,C18="Esp. + Pel.",0.8,C18="Espelhamento 2x",0.8)} -> 0.8 | U18: 1 | V18: 1 | X18: 39.67 | Y18: 38.51 | Z18: 116.78
B19: Bergon | C19: Dublagem Cretone - MO | E19: 1 | F19: 1.15 | G19: =F19 -> 1.15 | H19: metro linear | I19: =G19/E19 -> 1.15 | J19: 45663 | K19: Mão de obra | L19: =G19-M19-N19 -> 1.15 | M19: =IF(B19="Texion Textil",0,IF(C19="Malha",'Custos insumos'!$B$24,IF(C19="Dublagem Cretone",'Custos insumos'!$D$7,IF(C19="Dublagem Spun",'Custos insumos'!$D$4,IF(C19="Espelhamento",'Custos insumos'!$B$11,IF(C19="Espelhamento 2x",2*'Custos insumos'!$B$11,IF(C19="Esp. + Pel.",'Custos insumos'!$B$11,IF(C19="Pel. + Spun",'Custos insumos'!$D$4,IF(C19="Dublagem Cretone PES",'Custos insumos'!$D$7,IF(C19="Dublagem Barreira",'Custos insumos'!$D$11,IF(C19="Dublagem - MO + Filme",'Custos insumos'!$D$4,IF(C19="Dublagem Cretone HM50",'Custos insumos'!$D$26,IF(C19="Dublagem Cretone HM70",'Custos insumos'!$F$10,))))))))))))) -> 0 | N19: =IF(B19="Texion Textil",0,IF(B19="Três Elos",0,IF(C19="Malha",0,IF(C19="Dublagem Cretone",'Custos insumos'!$D$23,IF(C19="Dublagem Spun",'Custos insumos'!$D$19,IF(C19="Espelhamento",0,IF(C19="Espelhamento 2x",0,IF(C19="Esp. + Pel.",0,IF(C19="Pel. + Spun",'Custos insumos'!$D$19,IF(C19="Dublagem Cretone PES",'Custos insumos'!$F$25,IF(C19="Dublagem Barreira",'Custos insumos'!$D$22,))))))))))) -> 0 | P19: =(Q19-S19)/Q19 -> 0.096492754 | Q19: =G19*R19 -> 207 | R19: {=_xlfn.IFS(C19="Calandra",(350),C19="Peletização",(421),C19="Dublagem Spun",(250),C19="Dublagem Cretone PES",(180),C19="Felpagem",(270/E19),C19="Emborrachamento",(200),C19="Espelhamento",(250),C19="Malha",(1),C19="Dublagem Cretone",(180),C19="Malha",(1),C19="Dublagem Spun - MO",250,C19="Dublagem Cretone - MO",180,C19="Dublagem Cretone PES - MO",180,C19="Espelhamento - MO",250,C19="Emborrachamento",100,C19="Malha",0,C19="Dublagem Barreira",100,C19="Pel. + Cal.",350,C19="Fel. + Pel. + Cal.",270,C19="Pel. + Spun",250,C19="Espelhamento - L: 1,45m",200,C19="Espelhamento - L: 1,65m",200,C19="Estampagem",100,C19="Fel. + Cal.",270,C19="Dublagem Juta",180,C19="Dublagem Cretone - MO (Juta)",180,C19="Dublagem Tapete",150,C19="Esp. + Pel.",200,C19="Espelhamento 2x",100)} -> 180 | S19: =(T19*X19)+(U19*Y19)+(V19*Z19)+((M19+N19)*(R19)) -> 187.026 | T19: {=_xlfn.IFS(C19="Calandra",0.4,C19="Felpagem",0.3,C19="Dublagem Spun",0.8,C19="Dublagem Cretone",0.8,C19="Dublagem Cretone PES",0.8,C19="Espelhamento",0.8,C19="Peletização",0.5,C19="Dublagem Spun - MO",0.8,C19="Dublagem Cretone - MO",0.8,C19="Dublagem Cretone PES - MO",0.8,C19="Espelhamento - MO",0.8,C19="Emborrachamento",1,C19="Malha",0,C19="Dublagem Barreira",1,C19="Pel. + Cal.",0.4,C19="Fel. + Pel. + Cal.",0.5,C19="Pel. + Spun",0.8,C19="Espelhamento - L: 1,45m",0.8,C19="Espelhamento - L: 1,65m",0.8,C19="Estampagem",1,C19="Fel. + Cal.",0.4,C19="Dublagem Juta",0.8,C19="Dublagem Cretone - MO (Juta)",0.8,C19="Dublagem Tapete",0.8,C19="Esp. + Pel.",0.8,C19="Espelhamento 2x",0.8)} -> 0.8 | U19: 1 | V19: 1 | X19: 39.67 | Y19: 38.51 | Z19: 116.78
B20: By For man | C20: Felpagem | E20: 1 | F20: 1.1 | G20: =F20 -> 1.1 | H20: metro linear | I20: =G20/E20 -> 1.1 | J20: 45663 | L20: =G20-M20-N20 -> 1.1 | M20: =IF(B20="Texion Textil",0,IF(C20="Malha",'Custos insumos'!$B$24,IF(C20="Dublagem Cretone",'Custos insumos'!$D$7,IF(C20="Dublagem Spun",'Custos insumos'!$D$4,IF(C20="Espelhamento",'Custos insumos'!$B$11,IF(C20="Espelhamento 2x",2*'Custos insumos'!$B$11,IF(C20="Esp. + Pel.",'Custos insumos'!$B$11,IF(C20="Pel. + Spun",'Custos insumos'!$D$4,IF(C20="Dublagem Cretone PES",'Custos insumos'!$D$7,IF(C20="Dublagem Barreira",'Custos insumos'!$D$11,IF(C20="Dublagem - MO + Filme",'Custos insumos'!$D$4,IF(C20="Dublagem Cretone HM50",'Custos insumos'!$D$26,IF(C20="Dublagem Cretone HM70",'Custos insumos'!$F$10,))))))))))))) -> 0 | N20: =IF(B20="Texion Textil",0,IF(B20="Três Elos",0,IF(C20="Malha",0,IF(C20="Dublagem Cretone",'Custos insumos'!$D$23,IF(C20="Dublagem Spun",'Custos insumos'!$D$19,IF(C20="Espelhamento",0,IF(C20="Espelhamento 2x",0,IF(C20="Esp. + Pel.",0,IF(C20="Pel. + Spun",'Custos insumos'!$D$19,IF(C20="Dublagem Cretone PES",'Custos insumos'!$F$25,IF(C20="Dublagem Barreira",'Custos insumos'!$D$22,))))))))))) -> 0 | P20: =(Q20-S20)/Q20 -> 0.43706734 | Q20: =G20*R20 -> 297 | R20: {=_xlfn.IFS(C20="Calandra",(350),C20="Peletização",(421),C20="Dublagem Spun",(250),C20="Dublagem Cretone PES",(180),C20="Felpagem",(270/E20),C20="Emborrachamento",(200),C20="Espelhamento",(250),C20="Malha",(1),C20="Dublagem Cretone",(180),C20="Malha",(1),C20="Dublagem Spun - MO",250,C20="Dublagem Cretone - MO",180,C20="Dublagem Cretone PES - MO",180,C20="Espelhamento - MO",250,C20="Emborrachamento",100,C20="Malha",0,C20="Dublagem Barreira",100,C20="Pel. + Cal.",350,C20="Fel. + Pel. + Cal.",270,C20="Pel. + Spun",250,C20="Espelhamento - L: 1,45m",200,C20="Espelhamento - L: 1,65m",200,C20="Estampagem",100,C20="Fel. + Cal.",270,C20="Dublagem Juta",180,C20="Dublagem Cretone - MO (Juta)",180,C20="Dublagem Tapete",150,C20="Esp. + Pel.",200,C20="Espelhamento 2x",100)} -> 270 | S20: =(T20*X20)+(U20*Y20)+(V20*Z20)+((M20+N20)*(R20)) -> 167.191 | T20: {=_xlfn.IFS(C20="Calandra",0.4,C20="Felpagem",0.3,C20="Dublagem Spun",0.8,C20="Dublagem Cretone",0.8,C20="Dublagem Cretone PES",0.8,C20="Espelhamento",0.8,C20="Peletização",0.5,C20="Dublagem Spun - MO",0.8,C20="Dublagem Cretone - MO",0.8,C20="Dublagem Cretone PES - MO",0.8,C20="Espelhamento - MO",0.8,C20="Emborrachamento",1,C20="Malha",0,C20="Dublagem Barreira",1,C20="Pel. + Cal.",0.4,C20="Fel. + Pel. + Cal.",0.5,C20="Pel. + Spun",0.8,C20="Espelhamento - L: 1,45m",0.8,C20="Espelhamento - L: 1,65m",0.8,C20="Estampagem",1,C20="Fel. + Cal.",0.4,C20="Dublagem Juta",0.8,C20="Dublagem Cretone - MO (Juta)",0.8,C20="Dublagem Tapete",0.8,C20="Esp. + Pel.",0.8,C20="Espelhamento 2x",0.8)} -> 0.3 | U20: 1 | V20: 1 | X20: 39.67 | Y20: 38.51 | Z20: 116.78
B21: Calango - Marcos | C21: Peletização | G21: 1 | L21: =G21-M21-N21 -> 1 | M21: =IF(B21="Texion Textil",0,IF(C21="Malha",'Custos insumos'!$B$24,IF(C21="Dublagem Cretone",'Custos insumos'!$D$7,IF(C21="Dublagem Spun",'Custos insumos'!$D$4,IF(C21="Espelhamento",'Custos insumos'!$B$11,IF(C21="Espelhamento 2x",2*'Custos insumos'!$B$11,IF(C21="Esp. + Pel.",'Custos insumos'!$B$11,IF(C21="Pel. + Spun",'Custos insumos'!$D$4,IF(C21="Dublagem Cretone PES",'Custos insumos'!$D$7,IF(C21="Dublagem Barreira",'Custos insumos'!$D$11,IF(C21="Dublagem - MO + Filme",'Custos insumos'!$D$4,IF(C21="Dublagem Cretone HM50",'Custos insumos'!$D$26,IF(C21="Dublagem Cretone HM70",'Custos insumos'!$F$10,))))))))))))) -> 0 | N21: =IF(B21="Texion Textil",0,IF(B21="Três Elos",0,IF(C21="Malha",0,IF(C21="Dublagem Cretone",'Custos insumos'!$D$23,IF(C21="Dublagem Spun",'Custos insumos'!$D$19,IF(C21="Espelhamento",0,IF(C21="Espelhamento 2x",0,IF(C21="Esp. + Pel.",0,IF(C21="Pel. + Spun",'Custos insumos'!$D$19,IF(C21="Dublagem Cretone PES",'Custos insumos'!$F$25,IF(C21="Dublagem Barreira",'Custos insumos'!$D$22,))))))))))) -> 0 | P21: =(Q21-S21)/Q21 -> 0.58402613 | Q21: =G21*R21 -> 421 | R21: {=_xlfn.IFS(C21="Calandra",(350),C21="Peletização",(421),C21="Dublagem Spun",(250),C21="Dublagem Cretone PES",(180),C21="Felpagem",(270/E21),C21="Emborrachamento",(200),C21="Espelhamento",(250),C21="Malha",(1),C21="Dublagem Cretone",(180),C21="Malha",(1),C21="Dublagem Spun - MO",250,C21="Dublagem Cretone - MO",180,C21="Dublagem Cretone PES - MO",180,C21="Espelhamento - MO",250,C21="Emborrachamento",100,C21="Malha",0,C21="Dublagem Barreira",100,C21="Pel. + Cal.",350,C21="Fel. + Pel. + Cal.",270,C21="Pel. + Spun",250,C21="Espelhamento - L: 1,45m",200,C21="Espelhamento - L: 1,65m",200,C21="Estampagem",100,C21="Fel. + Cal.",270,C21="Dublagem Juta",180,C21="Dublagem Cretone - MO (Juta)",180,C21="Dublagem Tapete",150,C21="Esp. + Pel.",200,C21="Espelhamento 2x",100)} -> 421 | S21: =(T21*X21)+(U21*Y21)+(V21*Z21)+((M21+N21)*(R21)) -> 175.125 | T21: {=_xlfn.IFS(C21="Calandra",0.4,C21="Felpagem",0.3,C21="Dublagem Spun",0.8,C21="Dublagem Cretone",0.8,C21="Dublagem Cretone PES",0.8,C21="Espelhamento",0.8,C21="Peletização",0.5,C21="Dublagem Spun - MO",0.8,C21="Dublagem Cretone - MO",0.8,C21="Dublagem Cretone PES - MO",0.8,C21="Espelhamento - MO",0.8,C21="Emborrachamento",1,C21="Malha",0,C21="Dublagem Barreira",1,C21="Pel. + Cal.",0.4,C21="Fel. + Pel. + Cal.",0.5,C21="Pel. + Spun",0.8,C21="Espelhamento - L: 1,45m",0.8,C21="Espelhamento - L: 1,65m",0.8,C21="Estampagem",1,C21="Fel. + Cal.",0.4,C21="Dublagem Juta",0.8,C21="Dublagem Cretone - MO (Juta)",0.8,C21="Dublagem Tapete",0.8,C21="Esp. + Pel.",0.8,C21="Espelhamento 2x",0.8)} -> 0.5 | U21: 1 | V21: 1 | X21: 39.67 | Y21: 38.51 | Z21: 116.78
B22: Calango - Marcos | C22: Blackout | L22: =G22-M22-N22 -> 0 | M22: =IF(B22="Texion Textil",0,IF(C22="Malha",'Custos insumos'!$B$24,IF(C22="Dublagem Cretone",'Custos insumos'!$D$7,IF(C22="Dublagem Spun",'Custos insumos'!$D$4,IF(C22="Espelhamento",'Custos insumos'!$B$11,IF(C22="Espelhamento 2x",2*'Custos insumos'!$B$11,IF(C22="Esp. + Pel.",'Custos insumos'!$B$11,IF(C22="Pel. + Spun",'Custos insumos'!$D$4,IF(C22="Dublagem Cretone PES",'Custos insumos'!$D$7,IF(C22="Dublagem Barreira",'Custos insumos'!$D$11,IF(C22="Dublagem - MO + Filme",'Custos insumos'!$D$4,IF(C22="Dublagem Cretone HM50",'Custos insumos'!$D$26,IF(C22="Dublagem Cretone HM70",'Custos insumos'!$F$10,))))))))))))) -> 0 | N22: =IF(B22="Texion Textil",0,IF(B22="Três Elos",0,IF(C22="Malha",0,IF(C22="Dublagem Cretone",'Custos insumos'!$D$23,IF(C22="Dublagem Spun",'Custos insumos'!$D$19,IF(C22="Espelhamento",0,IF(C22="Espelhamento 2x",0,IF(C22="Esp. + Pel.",0,IF(C22="Pel. + Spun",'Custos insumos'!$D$19,IF(C22="Dublagem Cretone PES",'Custos insumos'!$F$25,IF(C22="Dublagem Barreira",'Custos insumos'!$D$22,))))))))))) -> 0 | P22: =(Q22-S22)/Q22 -> #N/A | Q22: =G22*R22 -> #N/A | R22: {=_xlfn.IFS(C22="Calandra",(350),C22="Peletização",(421),C22="Dublagem Spun",(250),C22="Dublagem Cretone PES",(180),C22="Felpagem",(270/E22),C22="Emborrachamento",(200),C22="Espelhamento",(250),C22="Malha",(1),C22="Dublagem Cretone",(180),C22="Malha",(1),C22="Dublagem Spun - MO",250,C22="Dublagem Cretone - MO",180,C22="Dublagem Cretone PES - MO",180,C22="Espelhamento - MO",250,C22="Emborrachamento",100,C22="Malha",0,C22="Dublagem Barreira",100,C22="Pel. + Cal.",350,C22="Fel. + Pel. + Cal.",270,C22="Pel. + Spun",250,C22="Espelhamento - L: 1,45m",200,C22="Espelhamento - L: 1,65m",200,C22="Estampagem",100,C22="Fel. + Cal.",270,C22="Dublagem Juta",180,C22="Dublagem Cretone - MO (Juta)",180,C22="Dublagem Tapete",150,C22="Esp. + Pel.",200,C22="Espelhamento 2x",100)} -> #N/A | S22: =(T22*X22)+(U22*Y22)+(V22*Z22)+((M22+N22)*(R22)) -> #N/A | T22: {=_xlfn.IFS(C22="Calandra",0.4,C22="Felpagem",0.3,C22="Dublagem Spun",0.8,C22="Dublagem Cretone",0.8,C22="Dublagem Cretone PES",0.8,C22="Espelhamento",0.8,C22="Peletização",0.5,C22="Dublagem Spun - MO",0.8,C22="Dublagem Cretone - MO",0.8,C22="Dublagem Cretone PES - MO",0.8,C22="Espelhamento - MO",0.8,C22="Emborrachamento",1,C22="Malha",0,C22="Dublagem Barreira",1,C22="Pel. + Cal.",0.4,C22="Fel. + Pel. + Cal.",0.5,C22="Pel. + Spun",0.8,C22="Espelhamento - L: 1,45m",0.8,C22="Espelhamento - L: 1,65m",0.8,C22="Estampagem",1,C22="Fel. + Cal.",0.4,C22="Dublagem Juta",0.8,C22="Dublagem Cretone - MO (Juta)",0.8,C22="Dublagem Tapete",0.8,C22="Esp. + Pel.",0.8,C22="Espelhamento 2x",0.8)} -> #N/A | U22: 1 | V22: 1 | X22: 39.67 | Y22: 38.51 | Z22: 116.78
B23: Calmart | C23: Peletização | E23: 1 | F23: 0.65 | G23: =F23 -> 0.65 | H23: metro linear | I23: =G23/E23 -> 0.65 | J23: 45663 | L23: =G23-M23-N23 -> 0.65 | M23: =IF(B23="Texion Textil",0,IF(C23="Malha",'Custos insumos'!$B$24,IF(C23="Dublagem Cretone",'Custos insumos'!$D$7,IF(C23="Dublagem Spun",'Custos insumos'!$D$4,IF(C23="Espelhamento",'Custos insumos'!$B$11,IF(C23="Espelhamento 2x",2*'Custos insumos'!$B$11,IF(C23="Esp. + Pel.",'Custos insumos'!$B$11,IF(C23="Pel. + Spun",'Custos insumos'!$D$4,IF(C23="Dublagem Cretone PES",'Custos insumos'!$D$7,IF(C23="Dublagem Barreira",'Custos insumos'!$D$11,IF(C23="Dublagem - MO + Filme",'Custos insumos'!$D$4,IF(C23="Dublagem Cretone HM50",'Custos insumos'!$D$26,IF(C23="Dublagem Cretone HM70",'Custos insumos'!$F$10,))))))))))))) -> 0 | N23: =IF(B23="Texion Textil",0,IF(B23="Três Elos",0,IF(C23="Malha",0,IF(C23="Dublagem Cretone",'Custos insumos'!$D$23,IF(C23="Dublagem Spun",'Custos insumos'!$D$19,IF(C23="Espelhamento",0,IF(C23="Espelhamento 2x",0,IF(C23="Esp. + Pel.",0,IF(C23="Pel. + Spun",'Custos insumos'!$D$19,IF(C23="Dublagem Cretone PES",'Custos insumos'!$F$25,IF(C23="Dublagem Barreira",'Custos insumos'!$D$22,))))))))))) -> 0 | T23: {=_xlfn.IFS(C23="Calandra",0.4,C23="Felpagem",0.3,C23="Dublagem Spun",0.8,C23="Dublagem Cretone",0.8,C23="Dublagem Cretone PES",0.8,C23="Espelhamento",0.8,C23="Peletização",0.5,C23="Dublagem Spun - MO",0.8,C23="Dublagem Cretone - MO",0.8,C23="Dublagem Cretone PES - MO",0.8,C23="Espelhamento - MO",0.8,C23="Emborrachamento",1,C23="Malha",0,C23="Dublagem Barreira",1,C23="Pel. + Cal.",0.4,C23="Fel. + Pel. + Cal.",0.5,C23="Pel. + Spun",0.8,C23="Espelhamento - L: 1,45m",0.8,C23="Espelhamento - L: 1,65m",0.8,C23="Estampagem",1,C23="Fel. + Cal.",0.4,C23="Dublagem Juta",0.8,C23="Dublagem Cretone - MO (Juta)",0.8,C23="Dublagem Tapete",0.8,C23="Esp. + Pel.",0.8,C23="Espelhamento 2x",0.8)} -> 0.5
B24: Calmart | C24: Dublagem Cretone - MO | E24: 1 | F24: =1.19+1.15 -> 2.34 | G24: 2.74 | H24: metro linear | I24: =G24/E24 -> 2.74 | J24: 45663 | K24: Mão de obra e filme | L24: =G24-M24-N24 -> 1.174 | M24: ='Custos insumos'!$H$7 -> 1.566 | N24: 0 | P24: =(Q24-S24)/Q24 -> 0.049257908 | Q24: =G24*R24 -> 493.2 | R24: {=_xlfn.IFS(C24="Calandra",(350),C24="Peletização",(421),C24="Dublagem Spun",(250),C24="Dublagem Cretone PES",(180),C24="Felpagem",(270/E24),C24="Emborrachamento",(200),C24="Espelhamento",(250),C24="Malha",(1),C24="Dublagem Cretone",(180),C24="Malha",(1),C24="Dublagem Spun - MO",250,C24="Dublagem Cretone - MO",180,C24="Dublagem Cretone PES - MO",180,C24="Espelhamento - MO",250,C24="Emborrachamento",100,C24="Malha",0,C24="Dublagem Barreira",100,C24="Pel. + Cal.",350,C24="Fel. + Pel. + Cal.",270,C24="Pel. + Spun",250,C24="Espelhamento - L: 1,45m",200,C24="Espelhamento - L: 1,65m",200,C24="Estampagem",100,C24="Fel. + Cal.",270,C24="Dublagem Juta",180,C24="Dublagem Cretone - MO (Juta)",180,C24="Dublagem Tapete",150,C24="Esp. + Pel.",200,C24="Espelhamento 2x",100)} -> 180 | S24: =(T24*X24)+(U24*Y24)+(V24*Z24)+((M24+N24)*(R24)) -> 468.906 | T24: {=_xlfn.IFS(C24="Calandra",0.4,C24="Felpagem",0.3,C24="Dublagem Spun",0.8,C24="Dublagem Cretone",0.8,C24="Dublagem Cretone PES",0.8,C24="Espelhamento",0.8,C24="Peletização",0.5,C24="Dublagem Spun - MO",0.8,C24="Dublagem Cretone - MO",0.8,C24="Dublagem Cretone PES - MO",0.8,C24="Espelhamento - MO",0.8,C24="Emborrachamento",1,C24="Malha",0,C24="Dublagem Barreira",1,C24="Pel. + Cal.",0.4,C24="Fel. + Pel. + Cal.",0.5,C24="Pel. + Spun",0.8,C24="Espelhamento - L: 1,45m",0.8,C24="Espelhamento - L: 1,65m",0.8,C24="Estampagem",1,C24="Fel. + Cal.",0.4,C24="Dublagem Juta",0.8,C24="Dublagem Cretone - MO (Juta)",0.8,C24="Dublagem Tapete",0.8,C24="Esp. + Pel.",0.8,C24="Espelhamento 2x",0.8)} -> 0.8 | U24: 1 | V24: 1 | X24: 39.67 | Y24: 38.51 | Z24: 116.78
B25: Calueto | C25: Dublagem Cretone - MO | D25: Seda | G25: 7.5 | P25: =(Q25-S25)/Q25 -> 0.86146222 | Q25: =G25*R25 -> 1350 | R25: {=_xlfn.IFS(C25="Calandra",(350),C25="Peletização",(421),C25="Dublagem Spun",(250),C25="Dublagem Cretone PES",(180),C25="Felpagem",(270/E25),C25="Emborrachamento",(200),C25="Espelhamento",(250),C25="Malha",(1),C25="Dublagem Cretone",(180),C25="Malha",(1),C25="Dublagem Spun - MO",250,C25="Dublagem Cretone - MO",180,C25="Dublagem Cretone PES - MO",180,C25="Espelhamento - MO",250,C25="Emborrachamento",100,C25="Malha",0,C25="Dublagem Barreira",100,C25="Pel. + Cal.",350,C25="Fel. + Pel. + Cal.",270,C25="Pel. + Spun",250,C25="Espelhamento - L: 1,45m",200,C25="Espelhamento - L: 1,65m",200,C25="Estampagem",100,C25="Fel. + Cal.",270,C25="Dublagem Juta",180,C25="Dublagem Cretone - MO (Juta)",180,C25="Dublagem Tapete",150,C25="Esp. + Pel.",200,C25="Espelhamento 2x",100)} -> 180 | S25: =(T25*X25)+(U25*Y25)+(V25*Z25)+((M25+N25)*(R25)) -> 187.026 | T25: {=_xlfn.IFS(C25="Calandra",0.4,C25="Felpagem",0.3,C25="Dublagem Spun",0.8,C25="Dublagem Cretone",0.8,C25="Dublagem Cretone PES",0.8,C25="Espelhamento",0.8,C25="Peletização",0.5,C25="Dublagem Spun - MO",0.8,C25="Dublagem Cretone - MO",0.8,C25="Dublagem Cretone PES - MO",0.8,C25="Espelhamento - MO",0.8,C25="Emborrachamento",1,C25="Malha",0,C25="Dublagem Barreira",1,C25="Pel. + Cal.",0.4,C25="Fel. + Pel. + Cal.",0.5,C25="Pel. + Spun",0.8,C25="Espelhamento - L: 1,45m",0.8,C25="Espelhamento - L: 1,65m",0.8,C25="Estampagem",1,C25="Fel. + Cal.",0.4,C25="Dublagem Juta",0.8,C25="Dublagem Cretone - MO (Juta)",0.8,C25="Dublagem Tapete",0.8,C25="Esp. + Pel.",0.8,C25="Espelhamento 2x",0.8)} -> 0.8 | U25: 1 | V25: 1 | X25: 39.67 | Y25: 38.51 | Z25: 116.78
B26: Coleção Textil | C26: Peletização | E26: 1 | F26: 0.75 | G26: =F26 -> 0.75 | H26: metro linear | I26: =G26/E26 -> 0.75 | J26: 45663 | L26: 0.75 | M26: =IF(B26="Texion Textil",0,IF(C26="Malha",'Custos insumos'!$B$24,IF(C26="Dublagem Cretone",'Custos insumos'!$D$7,IF(C26="Dublagem Spun",'Custos insumos'!$D$4,IF(C26="Espelhamento",'Custos insumos'!$B$11,IF(C26="Espelhamento 2x",2*'Custos insumos'!$B$11,IF(C26="Esp. + Pel.",'Custos insumos'!$B$11,IF(C26="Pel. + Spun",'Custos insumos'!$D$4,IF(C26="Dublagem Cretone PES",'Custos insumos'!$D$7,IF(C26="Dublagem Barreira",'Custos insumos'!$D$11,IF(C26="Dublagem - MO + Filme",'Custos insumos'!$D$4,IF(C26="Dublagem Cretone HM50",'Custos insumos'!$D$26,IF(C26="Dublagem Cretone HM70",'Custos insumos'!$F$10,))))))))))))) -> 0 | N26: =IF(B26="Texion Textil",0,IF(B26="Três Elos",0,IF(C26="Malha",0,IF(C26="Dublagem Cretone",'Custos insumos'!$D$23,IF(C26="Dublagem Spun",'Custos insumos'!$D$19,IF(C26="Espelhamento",0,IF(C26="Espelhamento 2x",0,IF(C26="Esp. + Pel.",0,IF(C26="Pel. + Spun",'Custos insumos'!$D$19,IF(C26="Dublagem Cretone PES",'Custos insumos'!$F$25,IF(C26="Dublagem Barreira",'Custos insumos'!$D$22,))))))))))) -> 0 | P26: =(Q26-S26)/Q26 -> 0.44536817 | Q26: =G26*R26 -> 315.75 | R26: {=_xlfn.IFS(C26="Calandra",(350),C26="Peletização",(421),C26="Dublagem Spun",(250),C26="Dublagem Cretone PES",(180),C26="Felpagem",(270/E26),C26="Emborrachamento",(200),C26="Espelhamento",(250),C26="Malha",(1),C26="Dublagem Cretone",(180),C26="Malha",(1),C26="Dublagem Spun - MO",250,C26="Dublagem Cretone - MO",180,C26="Dublagem Cretone PES - MO",180,C26="Espelhamento - MO",250,C26="Emborrachamento",100,C26="Malha",0,C26="Dublagem Barreira",100,C26="Pel. + Cal.",350,C26="Fel. + Pel. + Cal.",270,C26="Pel. + Spun",250,C26="Espelhamento - L: 1,45m",200,C26="Espelhamento - L: 1,65m",200,C26="Estampagem",100,C26="Fel. + Cal.",270,C26="Dublagem Juta",180,C26="Dublagem Cretone - MO (Juta)",180,C26="Dublagem Tapete",150,C26="Esp. + Pel.",200,C26="Espelhamento 2x",100)} -> 421 | S26: =(T26*X26)+(U26*Y26)+(V26*Z26)+((M26+N26)*(R26)) -> 175.125 | T26: {=_xlfn.IFS(C26="Calandra",0.4,C26="Felpagem",0.3,C26="Dublagem Spun",0.8,C26="Dublagem Cretone",0.8,C26="Dublagem Cretone PES",0.8,C26="Espelhamento",0.8,C26="Peletização",0.5,C26="Dublagem Spun - MO",0.8,C26="Dublagem Cretone - MO",0.8,C26="Dublagem Cretone PES - MO",0.8,C26="Espelhamento - MO",0.8,C26="Emborrachamento",1,C26="Malha",0,C26="Dublagem Barreira",1,C26="Pel. + Cal.",0.4,C26="Fel. + Pel. + Cal.",0.5,C26="Pel. + Spun",0.8,C26="Espelhamento - L: 1,45m",0.8,C26="Espelhamento - L: 1,65m",0.8,C26="Estampagem",1,C26="Fel. + Cal.",0.4,C26="Dublagem Juta",0.8,C26="Dublagem Cretone - MO (Juta)",0.8,C26="Dublagem Tapete",0.8,C26="Esp. + Pel.",0.8,C26="Espelhamento 2x",0.8)} -> 0.5 | U26: 1 | V26: 1 | X26: 39.67 | Y26: 38.51 | Z26: 116.78
B27: Coleção Textil | C27: Peletização | D27: Duas passadas | E27: 2 | F27: 1.25 | G27: =F27 -> 1.25 | H27: metro linear | I27: =G27/E27 -> 0.625 | J27: 45663 | L27: =G27-M27-N27 -> 1.25 | M27: =IF(B27="Texion Textil",0,IF(C27="Malha",'Custos insumos'!$B$24,IF(C27="Dublagem Cretone",'Custos insumos'!$D$7,IF(C27="Dublagem Spun",'Custos insumos'!$D$4,IF(C27="Espelhamento",'Custos insumos'!$B$11,IF(C27="Espelhamento 2x",2*'Custos insumos'!$B$11,IF(C27="Esp. + Pel.",'Custos insumos'!$B$11,IF(C27="Pel. + Spun",'Custos insumos'!$D$4,IF(C27="Dublagem Cretone PES",'Custos insumos'!$D$7,IF(C27="Dublagem Barreira",'Custos insumos'!$D$11,IF(C27="Dublagem - MO + Filme",'Custos insumos'!$D$4,IF(C27="Dublagem Cretone HM50",'Custos insumos'!$D$26,IF(C27="Dublagem Cretone HM70",'Custos insumos'!$F$10,))))))))))))) -> 0 | N27: =IF(B27="Texion Textil",0,IF(B27="Três Elos",0,IF(C27="Malha",0,IF(C27="Dublagem Cretone",'Custos insumos'!$D$23,IF(C27="Dublagem Spun",'Custos insumos'!$D$19,IF(C27="Espelhamento",0,IF(C27="Espelhamento 2x",0,IF(C27="Esp. + Pel.",0,IF(C27="Pel. + Spun",'Custos insumos'!$D$19,IF(C27="Dublagem Cretone PES",'Custos insumos'!$F$25,IF(C27="Dublagem Barreira",'Custos insumos'!$D$22,))))))))))) -> 0 | P27: =(Q27-S27)/Q27 -> 0.6672209 | Q27: =G27*R27 -> 526.25 | R27: {=_xlfn.IFS(C27="Calandra",(350),C27="Peletização",(421),C27="Dublagem Spun",(250),C27="Dublagem Cretone PES",(180),C27="Felpagem",(270/E27),C27="Emborrachamento",(200),C27="Espelhamento",(250),C27="Malha",(1),C27="Dublagem Cretone",(180),C27="Malha",(1),C27="Dublagem Spun - MO",250,C27="Dublagem Cretone - MO",180,C27="Dublagem Cretone PES - MO",180,C27="Espelhamento - MO",250,C27="Emborrachamento",100,C27="Malha",0,C27="Dublagem Barreira",100,C27="Pel. + Cal.",350,C27="Fel. + Pel. + Cal.",270,C27="Pel. + Spun",250,C27="Espelhamento - L: 1,45m",200,C27="Espelhamento - L: 1,65m",200,C27="Estampagem",100,C27="Fel. + Cal.",270,C27="Dublagem Juta",180,C27="Dublagem Cretone - MO (Juta)",180,C27="Dublagem Tapete",150,C27="Esp. + Pel.",200,C27="Espelhamento 2x",100)} -> 421 | S27: =(T27*X27)+(U27*Y27)+(V27*Z27)+((M27+N27)*(R27)) -> 175.125 | T27: {=_xlfn.IFS(C27="Calandra",0.4,C27="Felpagem",0.3,C27="Dublagem Spun",0.8,C27="Dublagem Cretone",0.8,C27="Dublagem Cretone PES",0.8,C27="Espelhamento",0.8,C27="Peletização",0.5,C27="Dublagem Spun - MO",0.8,C27="Dublagem Cretone - MO",0.8,C27="Dublagem Cretone PES - MO",0.8,C27="Espelhamento - MO",0.8,C27="Emborrachamento",1,C27="Malha",0,C27="Dublagem Barreira",1,C27="Pel. + Cal.",0.4,C27="Fel. + Pel. + Cal.",0.5,C27="Pel. + Spun",0.8,C27="Espelhamento - L: 1,45m",0.8,C27="Espelhamento - L: 1,65m",0.8,C27="Estampagem",1,C27="Fel. + Cal.",0.4,C27="Dublagem Juta",0.8,C27="Dublagem Cretone - MO (Juta)",0.8,C27="Dublagem Tapete",0.8,C27="Esp. + Pel.",0.8,C27="Espelhamento 2x",0.8)} -> 0.5 | U27: 1 | V27: 1 | X27: 39.67 | Y27: 38.51 | Z27: 116.78
B28: Compomax | C28: Felpagem | E28: 3 | F28: 0.4 | G28: 0.42 | H28: metro linear | I28: =G28/E28 -> 0.14 | J28: 45663 | L28: =G28-M28-N28 -> 0.42 | M28: =IF(B28="Texion Textil",0,IF(C28="Malha",'Custos insumos'!$B$24,IF(C28="Dublagem Cretone",'Custos insumos'!$D$7,IF(C28="Dublagem Spun",'Custos insumos'!$D$4,IF(C28="Espelhamento",'Custos insumos'!$B$11,IF(C28="Espelhamento 2x",2*'Custos insumos'!$B$11,IF(C28="Esp. + Pel.",'Custos insumos'!$B$11,IF(C28="Pel. + Spun",'Custos insumos'!$D$4,IF(C28="Dublagem Cretone PES",'Custos insumos'!$D$7,IF(C28="Dublagem Barreira",'Custos insumos'!$D$11,IF(C28="Dublagem - MO + Filme",'Custos insumos'!$D$4,IF(C28="Dublagem Cretone HM50",'Custos insumos'!$D$26,IF(C28="Dublagem Cretone HM70",'Custos insumos'!$F$10,))))))))))))) -> 0 | N28: =IF(B28="Texion Textil",0,IF(B28="Três Elos",0,IF(C28="Malha",0,IF(C28="Dublagem Cretone",'Custos insumos'!$D$23,IF(C28="Dublagem Spun",'Custos insumos'!$D$19,IF(C28="Espelhamento",0,IF(C28="Espelhamento 2x",0,IF(C28="Esp. + Pel.",0,IF(C28="Pel. + Spun",'Custos insumos'!$D$19,IF(C28="Dublagem Cretone PES",'Custos insumos'!$F$25,IF(C28="Dublagem Barreira",'Custos insumos'!$D$22,))))))))))) -> 0 | P28: =(Q28-S28)/Q28 -> -3.4230423 | Q28: =G28*R28 -> 37.8 | R28: {=_xlfn.IFS(C28="Calandra",(350),C28="Peletização",(421),C28="Dublagem Spun",(250),C28="Dublagem Cretone PES",(180),C28="Felpagem",(270/E28),C28="Emborrachamento",(200),C28="Espelhamento",(250),C28="Malha",(1),C28="Dublagem Cretone",(180),C28="Malha",(1),C28="Dublagem Spun - MO",250,C28="Dublagem Cretone - MO",180,C28="Dublagem Cretone PES - MO",180,C28="Espelhamento - MO",250,C28="Emborrachamento",100,C28="Malha",0,C28="Dublagem Barreira",100,C28="Pel. + Cal.",350,C28="Fel. + Pel. + Cal.",270,C28="Pel. + Spun",250,C28="Espelhamento - L: 1,45m",200,C28="Espelhamento - L: 1,65m",200,C28="Estampagem",100,C28="Fel. + Cal.",270,C28="Dublagem Juta",180,C28="Dublagem Cretone - MO (Juta)",180,C28="Dublagem Tapete",150,C28="Esp. + Pel.",200,C28="Espelhamento 2x",100)} -> 90 | S28: =(T28*X28)+(U28*Y28)+(V28*Z28)+((M28+N28)*(R28)) -> 167.191 | T28: {=_xlfn.IFS(C28="Calandra",0.4,C28="Felpagem",0.3,C28="Dublagem Spun",0.8,C28="Dublagem Cretone",0.8,C28="Dublagem Cretone PES",0.8,C28="Espelhamento",0.8,C28="Peletização",0.5,C28="Dublagem Spun - MO",0.8,C28="Dublagem Cretone - MO",0.8,C28="Dublagem Cretone PES - MO",0.8,C28="Espelhamento - MO",0.8,C28="Emborrachamento",1,C28="Malha",0,C28="Dublagem Barreira",1,C28="Pel. + Cal.",0.4,C28="Fel. + Pel. + Cal.",0.5,C28="Pel. + Spun",0.8,C28="Espelhamento - L: 1,45m",0.8,C28="Espelhamento - L: 1,65m",0.8,C28="Estampagem",1,C28="Fel. + Cal.",0.4,C28="Dublagem Juta",0.8,C28="Dublagem Cretone - MO (Juta)",0.8,C28="Dublagem Tapete",0.8,C28="Esp. + Pel.",0.8,C28="Espelhamento 2x",0.8)} -> 0.3 | U28: 1 | V28: 1 | X28: 39.67 | Y28: 38.51 | Z28: 116.78
B29: Covolan Benefic. | C29: Peletização | E29: 1 | F29: 0.55 | G29: 0.65 | H29: metro linear | I29: =G29/E29 -> 0.65 | J29: 45663 | L29: =G29-M29-N29 -> 0.65 | M29: =IF(B29="Texion Textil",0,IF(C29="Malha",'Custos insumos'!$B$24,IF(C29="Dublagem Cretone",'Custos insumos'!$D$7,IF(C29="Dublagem Spun",'Custos insumos'!$D$4,IF(C29="Espelhamento",'Custos insumos'!$B$11,IF(C29="Espelhamento 2x",2*'Custos insumos'!$B$11,IF(C29="Esp. + Pel.",'Custos insumos'!$B$11,IF(C29="Pel. + Spun",'Custos insumos'!$D$4,IF(C29="Dublagem Cretone PES",'Custos insumos'!$D$7,IF(C29="Dublagem Barreira",'Custos insumos'!$D$11,IF(C29="Dublagem - MO + Filme",'Custos insumos'!$D$4,IF(C29="Dublagem Cretone HM50",'Custos insumos'!$D$26,IF(C29="Dublagem Cretone HM70",'Custos insumos'!$F$10,))))))))))))) -> 0 | N29: =IF(B29="Texion Textil",0,IF(B29="Três Elos",0,IF(C29="Malha",0,IF(C29="Dublagem Cretone",'Custos insumos'!$D$23,IF(C29="Dublagem Spun",'Custos insumos'!$D$19,IF(C29="Espelhamento",0,IF(C29="Espelhamento 2x",0,IF(C29="Esp. + Pel.",0,IF(C29="Pel. + Spun",'Custos insumos'!$D$19,IF(C29="Dublagem Cretone PES",'Custos insumos'!$F$25,IF(C29="Dublagem Barreira",'Custos insumos'!$D$22,))))))))))) -> 0 | P29: =(Q29-S29)/Q29 -> 0.21931299 | Q29: =G29*R29 -> 273.65 | R29: {=_xlfn.IFS(C29="Calandra",(350),C29="Peletização",(421),C29="Dublagem Spun",(250),C29="Dublagem Cretone PES",(180),C29="Felpagem",(270/E29),C29="Emborrachamento",(200),C29="Espelhamento",(250),C29="Malha",(1),C29="Dublagem Cretone",(180),C29="Malha",(1),C29="Dublagem Spun - MO",250,C29="Dublagem Cretone - MO",180,C29="Dublagem Cretone PES - MO",180,C29="Espelhamento - MO",250,C29="Emborrachamento",100,C29="Malha",0,C29="Dublagem Barreira",100,C29="Pel. + Cal.",350,C29="Fel. + Pel. + Cal.",270,C29="Pel. + Spun",250,C29="Espelhamento - L: 1,45m",200,C29="Espelhamento - L: 1,65m",200,C29="Estampagem",100,C29="Fel. + Cal.",270,C29="Dublagem Juta",180,C29="Dublagem Cretone - MO (Juta)",180,C29="Dublagem Tapete",150,C29="Esp. + Pel.",200,C29="Espelhamento 2x",100)} -> 421 | S29: =(T29*X29)+(U29*Y29)+(V29*Z29)+((M29+N29)*(R29)) -> 213.635 | T29: {=_xlfn.IFS(C29="Calandra",0.4,C29="Felpagem",0.3,C29="Dublagem Spun",0.8,C29="Dublagem Cretone",0.8,C29="Dublagem Cretone PES",0.8,C29="Espelhamento",0.8,C29="Peletização",0.5,C29="Dublagem Spun - MO",0.8,C29="Dublagem Cretone - MO",0.8,C29="Dublagem Cretone PES - MO",0.8,C29="Espelhamento - MO",0.8,C29="Emborrachamento",1,C29="Malha",0,C29="Dublagem Barreira",1,C29="Pel. + Cal.",0.4,C29="Fel. + Pel. + Cal.",0.5,C29="Pel. + Spun",0.8,C29="Espelhamento - L: 1,45m",0.8,C29="Espelhamento - L: 1,65m",0.8,C29="Estampagem",1,C29="Fel. + Cal.",0.4,C29="Dublagem Juta",0.8,C29="Dublagem Cretone - MO (Juta)",0.8,C29="Dublagem Tapete",0.8,C29="Esp. + Pel.",0.8,C29="Espelhamento 2x",0.8)} -> 0.5 | U29: 2 | V29: 1 | X29: 39.67 | Y29: 38.51 | Z29: 116.78
